Workbook

Sheet 1、邮件流程目录
A1: 运营邮件流程
A2: 1.通用邮件中寻找是否有合适的邮件可以复用
A3: 2.若无通用模板可以使用，选择合适的结尾，本地化回来之后使用邮件生成表生成完整邮件发送即可
A4: 通用邮件目录
A5: 版本更新 | B5: 更新后补偿 | C5: 账号封禁 | D5: 不正当游戏封号 | E5: 开服合服 | F5: 开新服
B6: 延迟更新公告 | D6: 非法获得宝石道具封号 | F6: 合服公告
D7: 发布广告封号 | F7: 合服补偿
A8: 服务器维护 | B8: 临时维护 | D8: 恶意获利封号
B9: 维护超时 | D9: 恶意刷资源被处理
D10: 恶意增加战力被处理 | E10: 更新调整 | F10: 英雄平衡性调整补偿
A11: 问卷调查 | B11: 问卷发放 | D11: 举报类BUG（利用游戏漏洞获利）奖励 | F11: 数值平衡性调整补偿
B12: 问卷调查奖励 | D12: 体验类BUG（影响玩家体验）奖励 | F12: 平衡性调整说明
D13: 全服表扬
A14: 故障问题 | B14: 问题已解决 | E14: 活动相关 更新至2021.8.13 | F14: 决战卫星之巅开启
B15: 数据异常 | F15: 狂飙拉力赛任务无法完成问题已解决
B16: 游戏卡顿 | F16: 怒气值异常问题修复
B17: 部队丢失 | F17: 决战卫星之巅奖励丢失
B18: 部队丢失修复 | F18: 决战卫星之巅时间调整
B19: 活动排名异常修复 | F19: 地图改动补偿
B20: 邮件回档 | F20: 新版本问题已修复
B21: 奖励补发 | F21: 活动异常下线
E23: 问卷公告

Sheet 2、通用邮件模板
A1: 文本显色规则： 绿色：邮件里带跳转功能的超链接 黄色：除超链接以外的重点信息，例如 将在10分钟后维护，本次更新将重置您的主城位置
A2: 使用场景 | C2: cn | D2: en-loc | E2: fr | F2: de | G2: po | H2: zh | I2: id | J2: th | K2: sp | L2: ru | M2: tr | N2: vi | O2: it | P2: pl
A3: 版本更新 | B3: 更新后补偿 | C3: 版本更新礼物 | D3: Version Update Reward | E3: Récompense pour la mise à jour | F3: Versions-Update-Belohnung | G3: Recompensa de Atualização | H3: 版本更新禮物 | I3: Hadiah Pembaruan Versi | J3: รางวัลการอัปเดตเวอร์ชัน | K3: Recompensa por actualización de versión | L3: Награда за обновление версии | M3: Sürüm Güncelleme Ödülü | N3: Phần thưởng cập nhật phiên bản
C4: 亲爱的指挥官：\n\n感谢您的更新，在此我们送上一份更新礼物，祝您玩得开心！\n\n我们会继续关注大家的反馈和建议，通过持续优化提升游戏品质，给您带来更好的游戏体验。\n\n欢迎大家通过Discord官方社区或游戏内客服服务和我们积极沟通。\n[-1#Official Discord](herf=https://discord.gg/RncnPNw)\n\n罗杰副官 | D4: Dear Captain,\n\nThanks for updating! We've included a small update reward for you. Happy gaming!\n\nWe will continue to listen to your feedback and keep optimizing to bring you a better gaming experience.\n\nPlease don't hesitate to get in touch with us via Discord or the in-game customer support. [-1#Official Discord](herf=https://discord.gg/RncnPNw)\n\nDeputy Roger | F4: Lieber Captain,\n\nvielen Dank, dass du das Update durchgeführt hast! Wir haben eine kleine Update-Belohnung für dich beigefügt. Viel Spaß beim Spielen!\n\nWir werden auch in Zukunft auf dein Feedback hören und das Spiel weiter optimieren, um dir ein noch besseres Spielerlebnis zu bieten.\n\nBitte zögere nicht, mit uns über Discord oder den Ingame-Kundensupport in Kontakt zu treten. [-1#Offizieller Discord](herf=https://discord.gg/RncnPNw)\n\nAdjudant Roger | G4: Caro Capitão,\n\nAgradecemos por fazer a atualização! Incluímos uma pequena recompensa de atualização para você. Bons jogos!\n\nContinuaremos a ouvir seu feedback, mantendo assim a experiência de jogo otimizada.\n\nNão deixe de entrar em contato conosco no Discord ou no suporte ao cliente dentro do jogo. [-1#Discord Oficial](herf=https://discord.gg/RncnPNw)\n\nDelegado Roger | H4: 親愛的指揮官：\n\n感謝您的更新，在此我們送上一份更新禮物，祝您玩得開心！\n\n我們會繼續關注大家的反饋和建議，通過持續優化提升遊戲品質，給您帶來更好的遊戲體驗。\n\n歡迎大家通過Discord官方社區或遊戲內客服服務和我們積極溝通。\n[-1#Official Discord](herf=https://discord.gg/RncnPNw)\n\n羅傑副官 | I4: Kapten yang terhormat,\n\nTerima kasih telah melakukan pembaruan! Kami telah menyertakan hadiah pembaruan kecil untukmu. Selamat bermain game!\n\nKami akan terus mendengarkan umpan balikmu dan terus mengoptimalkan untuk memberikan pengalaman bermain game yang lebih baik.\n\nJangan ragu untuk menghubungi kami melalui Discord atau dukungan pelanggan dalam game. [-1#Official Discord](herf=https://discord.gg/RncnPNw)\n\nDeputi Roger | J4: ถึงท่านผู้บัญชาการ\n\nขอบคุณสำหรับการอัปเดต! เราเลยขอมอบของรางวัลการอัปเดตชิ้นเล็ก ๆ นี้ให้ ขอให้มีความสุขในการเล่นเกมนะ!\n\nเราพร้อมรับฟังความคิดเห็นของนายและปรับปรุงอย่างต่อเนื่องเพื่อนำเสนอประสบการณ์การเล่นเกมที่ดียิ่ง ๆ ขึ้นไป\n\nโปรดอย่าลังเลที่จะติดต่อเราผ่านทาง Discord หรือฝ่ายสนับสนุนลูกค้าในเกม [-1#Official Discord](herf=https://discord.gg/RncnPNw)\n\nท่านรองโรเจอร์ | K4: Querido Capitán,\n\n¡Gracias por actualizar! ¡Hemos incluido una pequeña recompensa por actualización para ti! Felices juegos. \n\nContinuaremos escuchando tus comentarios y nos mantendremos optimizando para traerte una mejor experiencia de juego.\n\nPor favor, no dudes en ponerte en contacto con nosotros mediante Discord o a través del soporte al cliente del juego. [-1#Discord Oficial](herf=https://discord.gg/RncnPNw)\n\nComisario Roger | L4: Уважаемый капитан!\n\nСпасибо, что обновляете игру! Мы отправляем вам небольшую награду за обновление. Счастливой игры!\n\nМы продолжим изучать ваши отзывы и оптимизировать качество игры, чтобы оставить у вас наилучшие впечатления.\n\nВы в любой момент можете написать нам в Discord или в игровую службу поддержки. [-1#Сервер Discord](herf=https://discord.gg/RncnPNw)\n\nПомощник Роджер | M4: Sevgili Kaptan,\n\nGüncellediğin için teşekkürler! Senin için küçük bir güncelleme ödülümüz var. Mutlu oyunlar!\n\nGeri bildirimlerini dinlemeye ve sana daha iyi bir deneyim sunmak adına optimize etmeye devam edeceğiz.\n\nDiscord üzerinden veya oyun içi müşteri desteğinden bize ulaşabilirsin. [-1#Resmî Discord](herf=https://discord.gg/RncnPNw)\n\nYardımcı Roger | N4: Thưa Thủ Lĩnh,\n\nCảm ơn các bạn đã cập nhật! Chúng tôi đã đính kèm một phần thưởng cập nhật nhỏ dành cho bạn. Chúc bạn chơi game vui vẻ!\n\nChúng tôi sẽ tiếp tục lắng nghe phản hồi của bạn để tiếp tục tối ưu hóa và mang lại cho bạn trải nghiệm chơi game tốt hơn.\n\nVui lòng liên hệ với chúng tôi qua Discord hoặc bộ phận hỗ trợ khách hàng trong trò chơi. [-1#Discord chính thức](herf=https://discord.gg/RncnPNw)\n\nPhụ tá Roger
B5: 延迟更新公告 | C5: 0.22.0版本更新延迟公告 | D5: Version 0.22.0 Update Delay | E5: Retard de mise à jour 0.22.0 | F5: Version 0.22.0 Update-Verzögerung | G5: Adiamento da atualização 0.22.0 | H5: 0.22.0版本更新延遲公告 | I5: Penundaan Pembaruan Versi 0.22.0 | J5: ความล่าช้าในการอัปเดตเวอร์ชัน 0.22.0 | K5: Retraso en la actualización a la versión 0.22.0 | L5: Задержка обновления до версии 0.22.0 | M5: Sürüm 0.22.0 Güncelleme Ertelemesi | N5: Trì hoãn Cập nhật phiên bản 0.22.0
C6: 亲爱的指挥官：\n\n0.22.0版本更新时间将会被<color=#ffa200>延迟</color>，具体时间我们将另行通知。\n\n感谢您对Age of Apes的理解与支持，祝愿火箭发射顺利！\n\n罗杰副官 | D6: Dear Captain,\n\nThe version 0.22.0 update has been <color=#ffa200>delayed</color>. We will notify you as soon as the new update time is confirmed.\n\nThank you for your understanding and support. See you around the Tavern!\n\nDeputy Roger | E6: Cher capitaine,\n\nLa mise à jour 0.22.0 a pris du <color=#ffa200>retard</color>. Nous vous tiendrons informé dès que l'horaire de fin des opérations sera confirmé.\n\nMerci pour votre compréhension et votre soutien. A bientôt à la taverne!\n\nRoger l'assistant | F6: Lieber Captain,\n\nDas Update auf die Version 0.22.0 hat sich <color=#ffa200>verzögert</color. Wir werden dich benachrichtigen, sobald der neue Update-Zeitpunkt bestätigt ist.\n\nVielen Dank für dein Verständnis und deine Unterstützung. Wir sehen uns in der Taverne!\n\nAdjudant Roger | G6: Caro Capitão,\n\nA atualização para a versão 0.22.0 foi <color=#ffa200>adiada</color. Notificaremos você assim que a nova data de atualização for confirmada.\n\nNossa equipe agradece seu apoio e compreensão. Vemos você na taverna!\n\nDelegado Roger | H6: 親愛的指揮官：\n\n0.22.0版本更新時間將會被<color=#ffa200>延遲</color>，具體時間我們將另行通知。\n\n感謝你對Age of Apes的理解與支持，祝愿火箭發射順利！\n\n羅傑副官 | I6: Kapten yang terhormat,\n\nPembaruan versi 0.22.0 telah <color=#ffa200>ditunda</color. Kami akan memberitahukanmu segera setelah waktu pembaruan terkini dikonfirmasi.\n\nTerima kasih atas pengertian dan dukunganmu. Sampai jumpa di sekitar Kedai!\n\nDeputi Roger | J6: ถึงท่านผู้บัญชาการ\n\nการอัปเดตเวอร์ชัน 0.22.0 <color=#ffa200>เกิดความล่าช้า</color> เราจะแจ้งให้นายทราบทันทีที่มีการยืนยันเวลาอัปเดตใหม่\n\nขอขอบคุณสำหรับความเข้าใจและการสนับสนุนของนาย แล้วไว้เจอกันแถว ๆ โรงแรมนะ!\n\nท่านรองโรเจอร์ | K6: Querido Capitán, \n\nLa actualización a la versión 0.22.0 ha sido <color=#ffa200>retrasada</color. Te notificaremos tan pronto como el horario de la nueva actualización este confirmado. \n\nGracias por tu comprensión y apoyo. ¡Nos vemos en la Taberna!\n\nComisario Roger | L6: Уважаемый капитан!\n\nОбновление до версии 0.22.0 <color=#ffa200>отложено</color>. Как только мы узнаем точное время обновления, мы вам сообщим.\n\nСпасибо за понимание и поддержку. Увидимся в таверне!\n\nПомощник Роджер | M6: Sevgili Kaptan,\n\nSürüm 0.22.0 güncellemesi <color=#ffa200>ertelendi</color. Yeni güncelleme zamanı belli olduğunda seni bilgilendireceğiz.\n\nAnlayışın ve desteğin için teşekkürler. Tavernada görüşürüz!\n\nYardımcı Roger | N6: Thưa Thủ Lĩnh,\n\nBản cập nhật của phiên bản 0.22.0 sẽ <color=#ffa200>bị hoãn lại</color. Chúng tôi sẽ thông báo ngay sau khi xác nhận xong thời gian cập nhật mới.\n\nCảm ơn các bạn đã thông cảm và hỗ trợ. Hẹn gặp lại ở Tửu Quán nhé!\n\nPhụ tá Roger
A7: 服务器维护 | B7: 临时维护 | C7: 临时维护公告 | D7: Server Maintenance Notice | E7: Maintenance des serveurs | F7: Hinweis zur Serverwartung | G7: Aviso de manutenção do servidor | H7: 臨時維護公告 | I7: Pemberitahuan Pemeliharaan Server | J7: ประกาศการบำรุงรักษาเซิร์ฟเวอร์ | K7: Aviso de Mantenimiento de Servidor | L7: Уведомление об обслуживании сервера | M7: Sunucu Bakımı Bildirimi | N7: Thông báo bảo trì máy chủ
C8: 亲爱的指挥官：\n\n为了更好地帮助你领导这座城市，我们将在<color=#ffa200>2021-04-01 00:00 UTC</color>进入维护状态，维护时长大约为<color=#ffa200>30分钟</color>，维护期间你将无法正常进入游戏。\n为您带来不便深感歉意，在此为您送上一份补偿，请注意查收。\n本次维护不排除延迟开启的可能，如若延迟，请关注社区发布的具体开服时间。感谢您对Age of Apes的理解与支持，祝愿火箭发射顺利！\n[-1#Official Discord](herf=https://discord.gg/RncnPNw)\n\n罗杰副官 | D8: Dear Captain,\n\nTo help you better lead your City, we'll be performing server maintenance starting at <color=#ffa200>2021-04-01 00:00 UTC</color>. It'll take approximately <color=#ffa200>30 minutes</color>. You will not be able to access the game during this time.\n\nWe apologize for the inconvenience and have included a small gift for you as compensation.\n\nMaintenance may take longer. If so, please stay tuned for updates posted to our Monkey Community.\n\nThanks for your understanding and support. See you around the Tavern!\n\n[-1#Official Discord](herf=https://discord.gg/RncnPNw)\n\nDeputy Roger | E8: Cher capitaine,\n\nPour vous aider à mieux gérer votre ville, nous prévoyons des opérations de maintenance des serveurs à partir du <color=#ffa200>01/04/2021 à 00:00 (TU)</color>. Elles prendront environ <color=#ffa200>30 minutes</color>. Pendant cette période, vous ne pourrez pas accéder au jeu.\n\nNous vous prions de nous excuser pour ce désagrément et vous offrons un petit cadeau en dédommagement.\n\nIl se peut que les opérations de maintenance prennent plus de temps. Pour en être informé, nous vous invitons à rejoindre notre communauté des singes.\n\nMerci pour votre compréhension et votre soutien. A bientôt à la taverne!\n\n[-1#Discord officiel](herf=https://discord.gg/RncnPNw)\n\nRoger l'assistant | F8: Lieber Captain,\n\nDamit du deine Stadt besser führen kannst, werden wir beginnend um <color=#ffa200>01.04.2021 00:00 UTC</color> eine Serverwartung durchführen. Sie wird etwa <color=#ffa200>30 Minuten</color> dauern. Während dieser Zeit wirst du nicht auf das Spiel zugreifen können.\n\nWir entschuldigen uns für die Unannehmlichkeiten und haben als Entschädigung ein kleines Geschenk für dich beigefügt.\n\nDie Wartungsarbeiten können möglicherweise länger dauern. Wenn dies der Fall ist, halte dich bitte über unsere Affen-Community auf dem Laufenden.\n\nVielen Dank für dein Verständnis und deine Unterstützung. Wir sehen uns in der Taverne!\n\n[-1#Offizieller Discord](herf=https://discord.gg/RncnPNw)\n\nAdjudant Roger | G8: Caro Capitão,\n\nPara ajudar você a melhorar a liderança de sua cidade, vamos fazer uma manutenção de servidor em <color=#ffa200>01/04/2021, às 00:00 (fuso UTC)</color>. Ela demorará cerca de <color=#ffa200>30 minutos</color>. Não será possível acessar o jogo durante este período.\n\nLamentamos pelo inconveniente e, por isso, incluímos um pequeno presente para você como compensação.\n\nA manutenção pode levar mais tempo. Se este for o caso, haverá atualizações sobre isso em nossa Comunidade dos Macacos\n\nNossa equipe agradece seu apoio e compreensão. Vemos você na taverna!\n\n[-1#Discord Oficial](herf=https://discord.gg/RncnPNw)\n\nDelegado Roger | H8: 親愛的指揮官：\n\n為了更好地幫助你領導這座城市，我們將在<color=#ffa200>2021-04-01 00:00 UTC</color>進入維護狀態，維護時長大約為<color=#ffa200>30分鐘< /color>，維護期間你將無法正常進入遊戲。\n為您帶來不便深感歉意，在此為您送上一份補償，請注意查收。\n本次維護不排除延遲開啟的可能，如若延遲，請關注社區發布的具體開服時間。感謝你對Age of Apes的理解與支持，祝愿火箭發射順利！\n[-1#Official Discord](herf=https://discord.gg/RncnPNw)\n\n羅傑副官 | I8: Kapten yang terhormat,\n\nUntuk membantumu memimpin Kota dengan lebih baik, kami akan melakukan pemeliharaan server pada <color=#ffa200>2021-04-01 00:00 UTC</color>. Pemeliharan akan memerlukan waktu sekitar <color=#ffa200>30 menit</color>. Kamu tidak akan bisa mengakses game selama waktu tersebut.\n\nKami mohon maaf atas ketidaknyamanannya dan telah menyertakan hadiah kecil untukmu sebagai kompensasi.\n\nPemeliharaan mungkin memerlukan waktu lebih lama. Jika demikian, nantikan pembaruan yang diposting di Komunitas Kera kami.\n\nTerima kasih atas pengertian dan dukunganmu. Sampai jumpa di sekitar Kedai!\n\n[-1#Official Discord](herf=https://discord.gg/RncnPNw)\n\nDeputi Roger | J8: ถึงท่านผู้บัญชาการ\n\nเพื่อช่วยให้นายบัญชาการเมืองของนายได้ดีขึ้น เราจะดำเนินการบำรุงรักษาเซิร์ฟเวอร์โดยเริ่มตั้งแต่วันที่<color=#ffa200> 01-04-2021 00:00 ตามเวลา UTC</color> โดยจะใช้เวลาประมาณ<color=#ffa200> 30 นาที </color>ซึ่งนายจะไม่สามารถเข้าเกมได้ในช่วงเวลาดังกล่าว\n\nขออภัยในความไม่สะดวก และเราขอมอบของรางวัลเล็ก ๆ น้อย ๆ นี้ให้เป็นการชดเชย\n\nการบำรุงรักษาอาจใช้เวลานานกว่าที่แจ้งไว้ได้ หากเป็นเช่นนั้น โปรดติดตามการอัปเดตที่เราจะโพสต์ไว้ในชุมชนเหล่าลิงของเรา\n\nขอขอบคุณสำหรับความเข้าใจและการสนับสนุนของนาย แล้วไว้เจอกันแถว ๆ โรงแรมนะ!\n\n[-1#Official Discord](herf=https://discord.gg/RncnPNw)\n\nท่านรองโรเจอร์ | K8: Querido Capitán, \n\nPara ayudarte a liderear mejor a tu Ciudad estaremos realizando un mantenimiento del servidor comenzando el día: <color=#ffa200>01-04-2021 00:00 UTC</color>. Tomará aproximadamente <color=#ffa200>30 minutos</color>. No podrás acceder al juego durante este periodo. \n\nNos disculpamos por el inconveniente y hemos incluido un pequeño regalo para ti como compensación. \n\nEl mantenimiento puede durar más tiempo. Si es así, mantente sintonizado para actualizaciones publicadas en nuestra Comunidad Mono. \n\nGracias por tu comprensión y apoyo. ¡Nos vemos en la Taberna!\n\n[-1#Discord Oficial](herf=https://discord.gg/RncnPNw)\n\nComisario Roger | L8: Уважаемый капитан!\n\nЧтобы помочь вам лучше руководить вашим городом, мы проводим техобслуживание начиная с <color=#ffa200>00:00 01.04.2021 (UTC)</color>. Обслуживание займет около <color=#ffa200>30 минут</color>, и в это время вы не сможете войти в игру.\n\nПриносим извинения за неудобства и отправляем вам небольшой подарок в качестве компенсации!\n\nЕсть вероятность, что обслуживание займет больше времени. В этом случае следите за новостями в нашем обезьяньем сообществе.\n\nСпасибо за понимание и поддержку. Увидимся в таверне!\n\n[-1#Официальный Discord](herf=https://discord.gg/RncnPNw)\n\nПомощник Роджер | M8: Sevgili Kaptan,\n\nŞehrine daha iyi liderlik etmeni sağlamak için <color=#ffa200>01.04.2021, 00.00’da (UTC)</color> başlayacak bir sunucu bakımı gerçekleştireceğiz</color>. Yaklaşık <color=#ffa200>30 dakika</color> sürecek. Bu süre içerisinde oyuna erişemeyeceksin.\n\nVerdiğimiz sıkıntıdan ötürü özür dileriz, bunun telafisi olarak sana küçük bir hediye sunuyoruz.\n\nBakım daha uzun sürebilir. Bu durumda, Maymun Topluluğumuzda paylaşılan güncellemeleri lütfen takip et.\n\nAnlayışın ve desteğin için teşekkürler. Tavernada görüşürüz!\n\n[-1#Resmî Discord](herf=https://discord.gg/RncnPNw)\n\nYardımcı Roger | N8: Thưa Thủ Lĩnh,\n\nĐể giúp bạn lãnh đạo Thành phố của mình ngày một tốt hơn, chúng tôi sẽ tiến hành bảo trì máy chủ, bắt đầu từ <color=#ffa200>00:00 ngày 01/04/2021 UTC</color>. Thời gian bảo trì sẽ kéo dài trong khoảng <color=#ffa200>30 phút</color>. Bạn sẽ không thể truy cập vào ứng dụng trong khoảng thời gian này.\n\nChúng tôi xin lỗi vì sự bất tiện này và xin phép được tặng một món quà nhỏ để bù đắp cho bạn.\n\nThời gian bảo trì có thể kéo dài lâu hơn. Nếu việc đó xảy ra, hãy theo dõi các tin tức cập nhật đăng trong Cộng đồng Khỉ của chúng tôi.\n\nCảm ơn bạn đã thông cảm và hỗ trợ. Hẹn gặp lại ở Tửu Quán nhé!\n\n[-1#Discord chính thức](herf=https://discord.gg/RncnPNw)\n\nPhụ tá Roger
B9: 维护超时 | C9: 维护超时说明 | D9: Maintenance Delay | E9: Retard de maintenance | F9: Wartungsverzögerung | G9: Atraso na manutenção | H9: 維護超時說明 | I9: Penundaan Pemeliharaan | J9: ความล่าช้าในการบำรุงรักษา | K9: Retraso del Mantenimiento | L9: Продление техобслуживания | M9: Bakım Ertelemesi | N9: Hoãn bảo trì
C10: 亲爱的指挥官：\n\n你好，由于城市电路发生故障，我们在<color=#ffa200>00:00 UTC</color>开始的系统维护花费了比预估更多的维护时间，现在维护已经结束，你可以正常登录游戏。\n为您带来不便深感歉意，在此为您送上一份补偿，请注意查收。\n\n感谢您对Age of Apes的理解与支持，祝愿火箭发射顺利！\n\n罗杰副官 | D10: Dear Captain,\n\nDue to issues in the city circuits, the maintenance that started at <color=#ffa200>00:00 UTC</color> took longer than expected. Maintenance has now finished and you may log in normally.\n\nWe apologize for the inconvenience and have included a small gift for you as compensation.\n\nThanks for your understanding and support. See you around the Tavern!\n\nDeputy Roger | E10: Cher capitaine,\n\nEn raison d'un dysfonctionnement des circuits de la ville, les opérations de maintenance, qui ont débuté à <color=#ffa200>00:00 (TU)</color>, ont pris plus de temps que prévu. Elles sont à présent achevées et vous pouvez vous connecter normalement.\n\nNous vous prions de nous excuser pour ce désagrément et vous offrons un petit cadeau en dédommagement.\n\nMerci pour votre compréhension et votre soutien. A bientôt à la taverne!\n\nRoger l'assistant | F10: Lieber Captain,\n\nAufgrund von Problemen in den Schaltkreisen der Stadt hat die Wartung, die um <color=#ffa200>00:00 UTC</color> begann, länger gedauert als erwartet. Die Wartungsarbeiten sind nun beendet und du kannst dich normal einloggen.\n\nWir entschuldigen uns für die Unannehmlichkeiten und haben als Entschädigung ein kleines Geschenk für dich beigefügt.\n\nVielen Dank für dein Verständnis und deine Unterstützung. Wir sehen uns in der Taverne!\n\nAdjudant Roger | G10: Caro Capitão,\n\nDevido a problemas nos circuitos da cidade, a manutenção que começou <color=#ffa200>à 00:00 (fuso UTC)</color> levou mais do que o esperado. A manutenção terminou e você pode agora entrar normalmente.\n\nLamentamos pelo inconveniente e, por isso, incluímos um pequeno presente para você como compensação.\n\nNossa equipe agradece seu apoio e compreensão. Vemos você na taverna!\n\nDelegado Roger | H10: 親愛的指揮官：\n\n你好，由於城市電路發生故障，我們在<color=#ffa200>00:00 UTC</color>開始的系統維護花費了比預估更多的維護時間，現在維護已經結束，你可以正常登錄遊戲。\n為您帶來不便深感歉意，在此為您送上一份補償，請注意查收。\n\n感謝你對Age of Apes的理解與支持，祝愿火箭發射順利！\n\n羅傑副官 | I10: Kapten yang terhormat,\n\nKarena masalah di sirkuit kota, perawatan yang dimulai pada <color=#ffa200>00:00 UTC</color> akan memerlukan waktu lebih lama daripada yang diperkirakan. Pemeliharaan telah selesai dan kamu bisa masuk secara normal.\n\nKami mohon maaf atas ketidaknyamanannya dan telah menyertakan hadiah kecil untukmu sebagai kompensasi.\n\nTerima kasih atas pengertian dan dukunganmu. Sampai jumpa di sekitar Kedai!\n\nDeputi Roger | J10: ถึงท่านผู้บัญชาการ\n\nเนื่องจากเกิดปัญหาในวงจรของเมือง การบำรุงรักษาที่เริ่มในเวลา<color=#ffa200> 00:00 UTC</color> จึงใช้เวลานานกว่าที่คาดไว้ ขณะนี้การบำรุงรักษาเสร็จสิ้นแล้ว นายสามารถเข้าสู่ระบบได้ตามปกติ\n\nขออภัยในความไม่สะดวก เราจึงขอมอบของขวัญเล็ก ๆ น้อย ๆ นี้ให้เป็นการชดเชย\n\nขอขอบคุณสำหรับความเข้าใจและการสนับสนุนของนาย แล้วไว้เจอกันแถว ๆ โรงแรมนะ!\n\nท่านรองโรเจอร์ | K10: Querido Capitán, \n\nDebido a problemas con los circuitos de la ciudad, el mantenimiento que había comenzado a las <color=#ffa200>00:00 UTC</color> tomo más tiempo de lo esperado. El mantenimiento ahora ha terminado y ya puedes conectarte normalmente. \n\nNos disculpamos por el inconveniente y hemos incluido un pequeño regalo para ti como compensación.\n\nGracias por tu comprensión y apoyo. ¡Nos vemos en la Taberna!\n\nComisario Roger | L10: Уважаемый капитан!\n\nИз-за проблем в городских сетях техобслуживание, которое началось в <color=#ffa200>00:00 (UTC)</color>, заняло больше времени, чем ожидалось. Сейчас оно закончено, и вы можете войти в игру в обычном режиме.\n\nПриносим извинения за доставленные неудобства и отправляем вам небольшой подарок в качестве компенсации!\n\nСпасибо за понимание и поддержку. Увидимся в таверне!\n\nПомощник Роджер | M10: Sevgili Kaptan,\n\nŞehir devrelerindeki sorunlar yüzünden <color=#ffa200>00.00’da (UTC)</color> başlayan bakım beklenenden uzun sürdü. Bakım şimdi tamamlandı, normal şekilde giriş yapabilirsin.\n\nVerdiğimiz sıkıntıdan ötürü özür dileriz, bunun telafisi olarak sana küçük bir hediye sunuyoruz.\n\nAnlayışın ve desteğin için teşekkürler. Tavernada görüşürüz!\n\nYardımcı Roger | N10: Thưa Thủ Lĩnh,\n\nDo các vấn đề về mạch điện trong thành phố, thời gian bảo trì bắt đầu lúc <color=#ffa200>00:00 UTC</color> đã kéo dài hơn dự kiến. Quá trình bảo trì hiện đã kết thúc và bạn có thể đăng nhập bình thường.\n\nChúng tôi xin lỗi vì sự bất tiện này và xin phép được tặng một món quà nhỏ để bù đắp cho bạn.\n\nCảm ơn bạn đã thông cảm và hỗ trợ. Hẹn gặp lại ở Tửu Quán nhé!\n\nPhụ tá Roger
A11: 问卷调查 | B11: 问卷发放 | C11: 问卷调查 | D11: Survey | E11: Enquête | F11: Umfrage | G11: Pesquisa | H11: 問卷調查 | I11: Survei | J11: แบบสำรวจ | K11: Encuesta | L11: Опрос | M11: Anket | N11: Khảo sát | O11: Sondaggio | P11: Ankieta | Q11: استبيان
C12: 亲爱的指挥官：\n\n恭喜您被选为幸运猴子，来参与我们的问卷调研！为了给您提供更好的游戏体验，您的建议非常重要。在问卷填写完毕后，您将会获得一份很棒的奖励！\n详细规则\n1. 在<color=#ffa200>2021-01-21 00:00 UTC</color>之前完成问卷，您将获得<color=#ffa200>200CD</color>奖励；\n2. 奖励将会在<color=#ffa200>2021-1-27 00:00 UTC</color>之前发放；\n3. 每位玩家只能获得一次奖励；\n4. 您填写的内容我们仅供内部分析使用；\n[-1#问卷](herf=http://questionnaire.tap4fun.com/jq/104274483.aspx?sojumpparm=%7Buser_id%7D)\n\n罗杰副官 | D12: Dear Captain,\n\nCongratulations! You have been selected as one of the lucky monkeys to participate in our survey! In order to provide you with a better gaming experience, we would like to know your suggestions about the game. After completing the survey, you will receive a great reward!\n\nParticipation Rules:\n\n1. Complete the survey before <color=#ffa200>2021-01-21 00:00 UTC</color> to receive <color=#ffa200>200 CDs</color>.\n2. The reward will be issued before <color=#ffa200>2021-1-27 00:00 UTC</color>.\n3. Each player can only get the reward once.\n4. Your survey answers are for internal analysis only.\n\n[-1#Survey](herf=https://www.surveymonkey.com/r/TNW9665?user_id=%7Buser_id%7D)\n\nDeputy Roger | E12: Cher capitaine,\n\nFélicitations! Vous faites partie des rares chanceux sélectionnés pour participer à notre enquête! Afin de vous proposer une expérience de jeu optimale, nous aimerions connaître vos suggestions. Après avoir rempli le questionnaire, vous recevrez une belle récompense!\n\nRèglement:\n\n1. Répondez à l'enquête avant le <color=#ffa200>21/01/2021 à 00:00 (TU)</color> pour recevoir <color=#ffa200>200 CD</color>.\n2. La récompense sera transmise avant le <color=#ffa200>27/01/2021 à 00:00 (TU)</color>.\n3. Une seule récompense par joueur.\n4. Vos réponses à l'enquête seront utilisées pour analyse en interne uniquement.\n\n[-1#Enquête](herf=https://www.surveymonkey.com/r/TNW9665?user_id=%7Buser_id%7D)\n\nRoger l'assistant | F12: Lieber Captain,\n\nHerzlichen Glückwunsch! Du wurdest als einer der glücklichen Affen ausgewählt, die an unserer Umfrage teilnehmen dürfen! Um dir ein besseres Spielerlebnis bieten zu können, möchten wir gerne deine Vorschläge zum Spiel hören. Nach Beendigung der Umfrage erhältst du eine tolle Belohnung!\n\nTeilnahmeregeln:\n\n1. Schließe die Umfrage vor dem <color=#ffa200>21.01.21 00:00 UTC</color> ab, um <color=#ffa200>200 CDs</color> zu erhalten.\n2. Die Belohnung wird vor dem <color=#ffa200>27.01.2021 00:00 Uhr UTC</color> ausgegeben.\n3. Jeder Spieler kann die Belohnung nur einmal erhalten.\n4. Deine Antworten auf die Umfrage sind nur für die interne Auswertung bestimmt.\n\n[-1#Umfrage](herf=https://www.surveymonkey.com/r/TNW9665?user_id=%7Buser_id%7D)\n\nAdjudant Roger | G12: Caro Capitão,\n\nParabéns! Você foi um dos macacos sortudos escolhidos para participar de nossa pesquisa! Para fornecer uma experiência de jogo melhor para você, gostaríamos de ouvir sua opinião sobre o jogo. Ao completar a pesquisa, você receberá uma grande recompensa!\n\nRegras para participar:\n\n1. Conclua a pesquisa antes de <color=#ffa200>21/01/2021, à 00:00 (UTC)</color> para receber <color=#ffa200>200 CDs</color>.\n2. A recompensa será enviada antes de <color=#ffa200>27/01/2021, à 00:00 (UTC)</color>.\n3. Cada jogador só pode conseguir a recompensa uma vez.\n4. Suas respostas serão usadas somente para análise interna de nossa equipe.\n\n[-1#Pesquisa](herf=https://www.surveymonkey.com/r/TNW9665?user_id=%7Buser_id%7D)\n\nDelegado Roger | H12: 親愛的指揮官：\n\n恭喜您被選為幸運猴子，來參與我們的問卷調研！為了給您提供更好的遊戲體驗，您的建議非常重要。在問卷填寫完畢後，您將會獲得一份很棒的獎勵！\n詳細規則\n1. 在<color=#ffa200>2021-01-21 00:00 UTC</color>之前完成問卷，您將獲得<color=#ffa200>200CD</color>獎勵；\n2. 獎勵將會在<color=#ffa200>2021-1-27 00:00 UTC</color>之前發放；\n3. 每位玩家只能獲得一次獎勵；\n4. 您填寫的內容我們僅供內部分析使用；\n[-1#問卷](herf=http://questionnaire.tap4fun.com/jq/104274483.aspx?sojumpparm=%7Buser_id%7D)\n\n羅傑副官 | I12: Kapten yang terhormat,\n\nSelamat! Kamu terpilih sebagai salah satu kera yang beruntung untuk berpartisipasi dalam survei kami! Untuk memberimu pengalaman bermain game yang lebih baik, kami ingin mengetahui saranmu tentang game. Setelah menyelesaikan survei, kamu akan menerima hadiah besar!\n\nAturan Partisipasi:\n\n1. Selesaikan survei sebelum <color=#ffa200>2021-01-21 00:00 UTC</color> untuk menerima <color=#ffa200>200 CD</color>.\n2. Hadiah akan diberikan sebelum <color=#ffa200>2021-1-27 00:00 UTC</color>.\n3. Setiap pemain hanya bisa mendapatkan hadiahnya sekali.\n4. Jawaban surveimu hanya untuk analisis internal.\n\n[-1#Survey](herf=https://www.surveymonkey.com/r/TNW9665?user_id=%7Buser_id%7D)\n\nDeputi Roger | J12: ถึงท่านผู้บัญชาการ\n\nยินดีด้วย! นายได้รับเลือกให้เป็นหนึ่งในลิงผู้โชคดีจากการเข้าร่วมแบบสำรวจของเรา! เพื่อให้นายได้รับประสบการณ์การเล่นเกมที่ดีขึ้น เราต้องการทราบข้อเสนอแนะของนายเกี่ยวกับเกมนี้ ซึ่งนายจะได้รับรางวัลก้อนโตหลังจากทำแบบสำรวจเสร็จแล้ว!\n\nกติกาการเข้าร่วม:\n\n1. ตอบแบบสำรวจให้เสร็จสิ้นก่อน<color=#ffa200> 21-01-2021 00:00 ตามเวลา UTC</color> เพื่อรับ<color=#ffa200> ซีดี 200 แผ่น</color>\n2. คุณจะได้รับรางวัลก่อนวันที่<color=#ffa200> 27-01-2021 00:00 ตามเวลา UTC</color>\n3. ผู้เล่นแต่ละคนสามารถรับรางวัลได้เพียงครั้งเดียว\n4. คำตอบจากแบบสำรวจของนายใช้สำหรับการวิเคราะห์ภายในเท่านั้น\n\n[-1#Survey](herf=https://www.surveymonkey.com/r/TNW9665?user_id=%7Buser_id%7D)\n\nท่านรองโรเจอร์ | K12: Querido Capitán, \n\n¡Felicidades! Has sido seleccionado como uno de los monos suertudos para participar en nuestra encuesta. Para poder proporcionarte una mejor experiencia de juego, nos gustaría conocer tus sugerencias con relación al juego. ¡Tras de completar la encuesta, recibirás una gran recompensa! \n\nReglas de participación: \n\n1. Completa la encuesta antes del <color=#ffa200>21-01-2021 00:00 UTC</color> para recibir <color=#ffa200>200 CD</color>.\n2. La recompensa será emitida después del <color=#ffa200>27-1-2021 00:00 UTC</color>.\n3. Cada jugador solamente podrá obtener la recompensa una vez. \n4. Tus respuestas a la encuesta solamente son para análisis interno.\n\n[-1#Encuesta](herf=https://www.surveymonkey.com/r/TNW9665?user_id=%7Buser_id%7D)\n\nComisario Roger | L12: Уважаемый капитан!\n\nПоздравляем! Вам повезло попасть в число счастливчиков, отобранных для участия в опросе! Чтобы обеспечить вам наилучшие впечатления от игры, мы хотим выслушать ваши предложения. Когда вы пройдете опрос, то получите отличную награду!\n\nПравила участия:\n\n1. Пройдите опрос до <color=#ffa200>00:00 21.01.2021 (UTC)</color>, чтобы получить в награду <color=#ffa200>200 CD</color>.\n2. Награда будет выдана до <color=#ffa200>00:00 27.01.2021 (UTC)</color>.\n3. Каждый игрок может получить награду только один раз.\n4. Ваши ответы в опросе предназначены исключительно для внутреннего анализа.\n\n[-1#Survey](herf=https://www.surveymonkey.com/r/TNW9665?user_id=%7Buser_id%7D)\n\nПомощник Роджер | M12: Sevgili Kaptan,\n\nTebrikler! Anketimize katılacak şanslı maymunlardan biri olarak seçildin! Sana daha iyi bir oyun deneyimi sunabilmek için oyunla ilgili tavsiyelerini öğrenmek istiyoruz. Anketi tamamladıktan sonra harika bir ödül alacaksın!\n\nKatılım Kuralları:\n\n1. Anketi <color=#ffa200>21.01.2021, 00.00’dan (UTC)</color> önce tamamla ve <color=#ffa200>200 CD</color> kazan.\n2. Ödül <color=#ffa200>27.01.2021, 00.00’dan (UTC)</color> önce verilecek.\n3. Her oyuncu ödülü sadece bir kez alabilir.\n4. Anket cevapların sadece dâhilî analiz için kullanılacak.\n\n[-1#Anket]\n(herf=https://www.surveymonkey.com/r/TNW9665?user_id=%7Buser_id%7D)\n\nYardımcı Roger | N12: Thưa Thủ Lĩnh,\n\nXin chúc mừng! Bạn là một trong những chú khỉ may mắn được chọn để tham gia khảo sát của chúng tôi! Để có thể cung cấp một trải nghiệm trò chơi tốt hơn, chúng tôi muốn tìm hiểu các đề xuất của bạn về trò chơi. Sau khi hoàn thành khảo sát, bạn sẽ nhận được một phần thưởng thú vị!\n\nNội quy tham gia:\n\n1. Hoàn thành khảo sát trước <color=#ffa200>00:00 UTC ngày 21/01/2021</color> để nhận <color=#ffa200>200 CD</color>.\n2. Phần thưởng sẽ được phát trước <color=#ffa200>00:00 UTC ngày 27/01/2021</color>.\n3. Mỗi người chơi chỉ có thể nhận phần thưởng một lần duy nhất.\n4. Câu trả lời khảo sát của bạn chỉ được sử dụng để phân tích nội bộ.\n\n-1#Khảo sát](herf=https://www.surveymonkey.com/r/TNW9665?user_id=%7Buser_id%7D)\n\nPhụ tá Roger | O12: Caro Capitano,\n\nCongratulazioni! Sei stato selezionato tra le scimmie fortunate che potranno partecipare al nostro sondaggio! Per offrire una migliore esperienza di gioco, vorremmo conoscere i tuoi suggerimenti. Dopo aver completato il sondaggio, riceverai una grande ricompensa!\n\nRegole di partecipazione:\n\n1. Completa il sondaggio prima del <color=#ffa200>21/01/2022 00:00 UTC</color> per ricevere <color=#ffa200>200 CD</color>.\n2. La ricompensa verrà inviata prima del <color=#ffa200>27/01/2022 00>00 UTC</color>.\n3. Ogni giocatore può ottenere la ricompensa solo una volta.\n4. Le risposte del sondaggio sono solo per scopi di analisi interne.\n\n[-1#Survey](herf=https://www.surveymonkey.com/r/TNW9665?user_id=%7Buser_id%7D)\n\nSottotenente Roger | P12: Kapitanie,\n\nGratulacje! Jesteś jedną ze szczęśliwych małp wybranych do udziału w naszej ankiecie! Aby zapewnić lepsze wrażenia graczy, chcemy poznać Twoje sugestie dotyczące gry. Po wypełnieniu ankiety otrzymasz wspaniałą nagrodę!\n\nZasady udziału:\n\n1. Wypełnij ankietę do <color=#ffa200>21.01.2021, do godz. 00:00 (UTC)</color>, aby otrzymać <color=#ffa200>200 CD</color>.\n2. Nagroda zostanie przyznana do <color=#ffa200>27.01.2021, do godz. 00:00 (UTC)</color>.\n3. Każdy gracz może otrzymać nagrodę tylko raz.\n4. Odpowiedzi udzielone w ankiecie zostaną wykorzystane wyłącznie do wewnętrznej analizy.\n\n[-1#Survey](herf=https://www.surveymonkey.com/r/TNW9665?user_id=%7Buser_id%7D)\n\nZastępca Roger | Q12: عزيزي الزعيم،\n\n تهانينا! لقد تم اختيارك كواحد من الزعماء المحظوظين للمشاركة في الاستبيان الخاص بنا! من أجل تزويدك بتجربة لعب أفضل، نود أن نعرف اقتراحاتك حول اللعبة. بعد إكمال الاستبيان، ستحصل على مكافأة رائعة!\n\n قواعد المشاركة:\n\n1. أكمل الاستبيان قبل <color=#ffa200>2021-01-21 00:00 UTC</color> لتحصل على <color=#ffa200>200 قرص CD</color>. سيتم إصدار المكافأة قبل <color=#ffa200>2021-1-27 00:00 UTC</color>.\n3. يمكن لكل لاعب الحصول على المكافأة مرة واحدة فقط.\n4. إجابات الاستطلاع الخاصة بك هي للتحليل الداخلي فقط.\n\n[-1#استبيان](herf=https://www.surveymonkey.com/r/TNW9665?user_id=%7Buser_id%7D)\n\nالنائب روجر
B13: 问卷奖励 | C13: 问卷调查奖励 | D13: Survey Reward | E13: Récompense pour l'enquête | F13: Umfrage-Belohnung | G13: Recompensa de pesquisa | H13: 問卷調查獎勵 | I13: Hadiah Survei | J13: รางวัลของแบบสำรวจ | K13: Recompensa por la Encuesta | L13: Награда за опрос | M13: Anket Ödülü | N13: Quà khảo sát | O13: Ricompensa per il sondaggio | P13: Nagroda za ankietę | Q13: مكافآت الاستبيان
C14: 亲爱的指挥官：\n\n感谢您抽出宝贵的时间参与我们的问卷调查。您的反馈将帮助我们改善并为您带来更好的游戏体验。\n\n请收下您的奖励。期待和您在小酒馆喝一杯！\n\n罗杰副官 | D14: Dear Captain,\n\nThank you for taking to time to complete the survey. Your valuable feedback will help us improve and bring you a better gaming experience.\n\nPlease claim your survey reward. See you around the Tavern!\n\nDeputy Roger | E14: Cher capitaine,\n\nMerci d'avoir pris le temps de répondre à l'enquête. Vos précieux commentaires nous aideront à améliorer le jeu pour vous proposer une expérience optimale.\n\nVous pouvez récupérer votre récompense. A bientôt à la taverne!\n\nRoger l'assistant | F14: Lieber Captain,\n\nVielen Dank, dass du dir die Zeit genommen hast, die Umfrage auszufüllen. Dein wertvolles Feedback wird uns helfen, uns zu verbessern und dir ein besseres Spielerlebnis zu bieten.\n\nBitte fordere deine Belohnung ein. Wir sehen uns in der Taverne!\n\nAdjudant Roger | G14: Caro Capitão,\n\nAgradecemos por concluir a pesquisa. Seu feedback valioso nos ajudará a melhorar ainda mais a experiência de jogo para você.\n\nResgate sua recompensa pela pesquisa. Vemos você na taverna!\n\nDelegado Roger | H14: 親愛的指揮官：\n\n感謝您抽出寶貴的時間參與我們的問卷調查。您的反饋將幫助我們改善並為您帶來更好的遊戲體驗。\n\n請收下您的獎勵。期待和您在小酒館喝一杯！\n\n羅傑副官 | I14: Kapten yang terhormat,\n\nTerima kasih telah meluangkan waktu untuk menyelesaikan survei. Umpan balikmu yang berharga akan membantu kami meningkatkan dan memberikan pengalaman bermain game yang lebih baik.\n\nKlaim hadiah surveimu. Sampai jumpa di sekitar Kedai!\n\nDeputi Roger | J14: ถึงท่านผู้บัญชาการ\n\nขอขอบคุณที่สละเวลาทำแบบสำรวจ ความคิดเห็นที่มีค่าของนายจะช่วยให้เราปรับปรุงและนำเสนอประสบการณ์การเล่นเกมที่ดียิ่งขึ้นได้\n\nรีบไปรับรางวัลแบบสำรวจของนายสิ แล้วไว้เจอกันแถว ๆ โรงแรมนะ!\n\nท่านรองโรเจอร์ | K14: Querido Capitán, \n\nGracias por tomarte el tiempo para completar la encuesta. Tus valiosos comentarios nos ayudarán a mejorar y ofrecerte una mejor experiencia de juego. \n\nPor favor, reclama tu recompensa de la encuesta. ¡Nos vemos en la Taberna! \n\nComisario Roger | L14: Уважаемый капитан!\n\nСпасибо, что нашли время пройти наш опрос. Ваши ценные отзывы помогут нам совершенствоваться и дарить вам еще лучшие впечатления от игры.\n\nПожалуйста, заберите свою награду за участие. Увидимся в таверне!\n\nПомощник Роджер | M14: Sevgili Kaptan,\n\nZaman ayırıp anketimizi doldurduğun için teşekkürler. Değerli geri bildirimin gelişmemize ve sana daha iyi bir oyun deneyimi sunmamıza yardım edecek.\n\nLütfen anket ödülünü al. Tavernada görüşürüz!\n\nYardımcı Roger | N14: Thưa Thủ Lĩnh,\n\nCảm ơn bạn đã dành thời gian hoàn thành khảo sát. Phản hồi quý giá của bạn sẽ giúp chúng tôi cải thiện và cung cấp cho bạn trải nghiệm trò chơi tốt hơn.\n\nVui lòng nhận phần thưởng khảo sát của bạn. Hẹn gặp lại ở Tửu Quán nhé!\n\nPhụ tá Roger | O14: Caro Capitano,\n\nGrazie per aver dedicato del tempo al sondaggio. Il tuo prezioso feedback ci aiuterà a migliorare e offrire un'esperienza di gioco migliore.\n\nRiscatta la ricompensa per il sondaggio. Ci vediamo alla Taverna!\n\nSottotenente Roger | P14: Kapitanie,\n\nDziękujemy za czas poświęcony na wypełnienie ankiety. Twój wartościowy wkład pomoże nam poprawić wrażenia wszystkich graczy.\n\nOdbierz swoją nagrodę za ankietę. Do zobaczenia w Tawernie!\n\nZastępca Roger | Q14: عزيزي الزعيم،\n\n شكرًا لك على تخصيص بعض الوقت لإكمال الاستبيان. ستساعدنا ملاحظاتك القيّمة على التحسين وستجلب لك تجربة لعب أفضل.\n\n الرجاء إكتساب مكافأة الاستبيان. أراك حول المقهى!\n\n النائب روجر
A15: 故障问题 | B15: 问题已解决 | C15: 问题修复说明 | D15: Issue Fixed | E15: Problème résolu | F15: Problem behoben | G15: Problemas resolvidos | H15: 問題修復說明 | I15: Perbaikan Masalah | J15: แก้ไขปัญหาแล้ว | K15: Problema Resuelto | L15: Проблема решена | M15: Sorun Düzeltildi | N15: Đã khắc phục sự cố
C16: 亲爱的指挥官：\n\n你好，目前我们已经紧急修复了电路，城市已经<color=#ffa200>恢复正常</color>。\n为您带来不便深感歉意，在此为您送上一份补偿，请注意查收。\n我们将不断改进，希望能得到你的理解与支持，祝愿火箭发射顺利！\n\n罗杰副官 | D16: Dear Captain,\n\nOur team has successfully fixed the circuits and your City has <color=#ffa200>returned to normal</color>.\n\nWe apologize for the inconvenience and have included a small gift for you as compensation.\n\nThank you for your understanding and support as we continue to improve. See you around the Tavern!\n\nDeputy Roger | E16: Cher capitaine,\n\nNotre équipe a réussi à réparer les circuits et la situation est de <color=#ffa200>retour à la normale</color>.\n\nNous vous prions de nous excuser pour ce désagrément et vous offrons un petit cadeau en dédommagement.\n\nMerci pour votre compréhension et votre soutien. A bientôt à la taverne!\n\nRoger l'assistant | F16: Lieber Captain,\n\nUnser Team hat die Schaltkreise erfolgreich repariert und deine Stadt ist <color=#ffa200>zur Normalität zurückgekehrt</color>.\n\nWir entschuldigen uns für die Unannehmlichkeiten und haben als Entschädigung ein kleines Geschenk für dich beigefügt.\n\nVielen Dank für dein Verständnis und deine Unterstützung, während wir uns weiter verbessern. Wir sehen uns in der Taverne!\n\nAdjudant Roger | G16: Caro Capitão,\n\nNossa equipe foi bem-sucedida em consertar os circuitos e sua cidade <color=#ffa200>já voltou ao normal</color>.\n\nLamentamos pelo inconveniente e, por isso, incluímos um pequeno presente para você como compensação.\n\nNossa equipe agradece sua compreensão e apoio ao passo que continuamos melhorando. Vemos você na taverna!\n\nDelegado Roger | H16: 親愛的指揮官：\n\n你好，目前我們已經緊急修復了電路，城市已經<color=#ffa200>恢復正常</color>。\n為您帶來不便深感歉意，在此為您送上一份補償，請注意查收。\n我們將不斷改進，希望能得到你的理解與支持，祝愿火箭發射順利！\n\n羅傑副官 | I16: Kapten yang terhormat,\n\nTim kami berhasil memperbaiki sirkuit dan Kotamu telah <color=#ffa200>kembali normal</color>.\n\nKami mohon maaf atas ketidaknyamanannya dan telah menyertakan hadiah kecil untukmu sebagai kompensasi.\n\nTerima kasih atas pengertian dan dukunganmu sementara kami terus meningkatkan game. Sampai jumpa di sekitar Kedai!\n\nDeputi Roger | J16: ถึงท่านผู้บัญชาการ\n\nทีมของเราได้แก้ไขวงจรเรียบร้อยแล้ว และเมืองของนายก็<color=#ffa200>กลับสู่สภาวะปกติแล้ว</color>\n\nขออภัยในความไม่สะดวก เราจึงขอมอบของขวัญเล็ก ๆ น้อย ๆ นี้ให้เป็นการชดเชย\n\nขอขอบคุณสำหรับความเข้าใจและการสนับสนุนการปรับปรุงอย่างต่อเนื่องของเรา แล้วไว้เจอกันแถว ๆ โรงแรมนะ!\n\nท่านรองโรเจอร์ | K16: Querido Capitán, \n\nNuestro equipo ha corregido exitosamente los circuitos y tu Ciudad ha <color=#ffa200>regresado a la normalidad</color>.\n\nNos disculpamos por el inconveniente y hemos incluido un pequeño regalo para ti como compensación. \n\nGracias por tu comprensión y apoyo mientras continuamos mejorando. ¡Nos vemos en la Taberna!\n\nComisario Roger | L16: Уважаемый капитан!\n\nНаша команда успешно починила все микросхемы, и ваш город <color=#ffa200>вернулся к нормальной жизни</color>.\n\nПриносим извинения за неудобства и отправляем вам небольшой подарок в качестве компенсации!\n\nСпасибо за понимание и поддержку наших мер по улучшению игры. Увидимся в таверне!\n\nПомощник Роджер | M16: Sevgili Kaptan,\n\nEkibimiz devreleri başarıyla onardı ve Şehrin <color=#ffa200>normale döndü</color>.\n\nVerdiğimiz sıkıntıdan ötürü özür dileriz, bunun telafisi olarak sana küçük bir hediye sunuyoruz.\n\nGelişme sürecimizdeki anlayışın ve desteğin için teşekkürler. Tavernada görüşürüz!\n\nYardımcı Roger | N16: Thưa Thủ Lĩnh,\n\nĐội ngũ của chúng tôi đã sửa mạch điện thành công và Thành phố của bạn đã <color=#ffa200>trở lại bình thường</color>.\n\nChúng tôi xin lỗi vì sự bất tiện này và xin phép được tặng một món quà nhỏ để bù đắp cho bạn.\n\nCảm ơn các bạn đã thông cảm và ủng hộ trong thời gian chúng tôi tiếp tục cải thiện trò chơi. Hẹn gặp lại ở Tửu Quán nhé!\n\nPhụ tá Roger
B17: 数据异常 | C17: 紧急问题说明 | D17: Urgent Fix Ongoing | E17: Résolution urgente en cours | F17: Dringende Fehlerbehebung im Gange | G17: Ajuste urgente em andamento | H17: 緊急問題說明 | I17: Perbaikan Mendesak Sedang Berlangsung | J17: กำลังดำเนินการแก้ไขอย่างเร่งด่วน | K17: Arreglo urgente en curso | L17: Срочное исправление | M17: Acil Tamir Devam Ediyor | N17: Chúng tôi đang khẩn trương sửa lỗi
C18: 亲爱的指挥官：\n\n由于城市电路故障，你的城市可能会出现<color=#ffa200>数据异常</color>等情况，我们<color=#ffa200>正在紧急修复</color>电路。\n为您带来不便深感歉意，在此为您送上一份补偿，请注意查收。\n感谢您对Age of Apes的理解与支持，祝愿火箭发射顺利！\n\n罗杰副官 | D18: Dear Captain,\n\nDue to circuit malfunctions, your City may experience <color=#ffa200>data errors</color> or other issues. We are working hard to <color=#ffa200>fix these issues as quickly as possible</color>.\n\nWe apologize for the inconvenience and have included a small gift for you as compensation.\n\nThank you for your understanding and support. See you around the Tavern!\n\nDeputy Roger | E18: Cher capitaine,\n\nEn raison du dysfonctionnement d'un circuit, votre ville peut présenter des <color=#ffa200>erreurs de données</color> ou d'autres soucis. Nous travaillons dur pour <color=#ffa200>résoudre ces problèmes aussi vite que possible</color>.\n\nNous vous prions de nous excuser pour ce désagrément et vous offrons un petit cadeau en dédommagement.\n\nMerci pour votre compréhension et votre soutien. A bientôt à la taverne!\n\nRoger l'assistant | F18: Lieber Captain,\n\nAufgrund von Schaltkreisfehlern kann es in deiner Stadt zu <color=#ffa200>Datenfehlern</color> oder anderen Problemen kommen. Wir arbeiten hart daran, <color=#ffa200>diese Probleme so schnell wie möglich zu beheben</color>.\n\nWir entschuldigen uns für die Unannehmlichkeiten und haben als Entschädigung ein kleines Geschenk für dich beigefügt.\n\nVielen Dank für dein Verständnis und deine Unterstützung. Wir sehen uns in der Taverne!\n\nAdjudant Roger | G18: Caro Capitão,\n\nDevido a um mal funcionamento dos circuitos, sua cidade talvez enfrente<color=#ffa200> erros nos dados</color> ou outros problemas. Estamos trabalhando muito para <color=#ffa200>resolver esses problemas o quanto antes</color>.\n\nLamentamos pelo inconveniente e, por isso, incluímos um pequeno presente para você como compensação.\n\nNossa equipe agradece seu apoio e compreensão. Vemos você na taverna!\n\nDelegado Roger | H18: 親愛的指揮官：\n\n由於城市電路故障，你的城市可能會出現<color=#ffa200>數據異常</color>等情況，我們<color=#ffa200>正在緊急修復</color>電路。\n為您帶來不便深感歉意，在此為您送上一份補償，請注意查收。\n感謝你對Age of Apes的理解與支持，祝愿火箭發射順利！\n\n羅傑副官 | I18: Kapten yang terhormat,\n\nSehubungan dengan kerusakan sirkuit, Kotamu mungkin mengalami <color=#ffa200>kesalahan data</color> atau masalah lain. Kami bekerja keras untuk <color=#ffa200>memperbaiki masalah ini secepat mungkin</color>.\n\nKami mohon maaf atas ketidaknyamanannya dan telah menyertakan hadiah kecil untukmu sebagai kompensasi.\n\nTerima kasih atas pengertian dan dukunganmu. Sampai Jumpa di Sekitar Kedai!\n\nDeputi Roger | J18: ถึงท่านผู้บัญชาการ\n\nเนื่องจากวงจรทำงานผิดปกติ เมืองของนายอาจประสบ<color=#ffa200>การผิดพลาดเกี่ยวกับข้อมูล</color>หรือปัญหาอื่น ๆ ซึ่งเรากำลังดำเนินการอย่างเต็มที่เพื่อ<color=#ffa200>แก้ไขปัญหาเหล่านี้โดยเร็วที่สุด</color>\n\nขออภัยในความไม่สะดวก เราจึงขอมอบของขวัญเล็ก ๆ น้อย ๆ นี้ให้เป็นการชดเชย\n\nขอขอบคุณสำหรับความเข้าใจและการสนับสนุนของนาย แล้วไว้เจอกันแถว ๆ โรงแรมนะ!\n\nท่านรองโรเจอร์ | K18: Querido Capitán, \n\nDebido a unos fallos en los circuitos tu Ciudad puede experimentar <color=#ffa200>errores de datos</color> u otros problemas. Estamos trabajando duro para <color=#ffa200>corregir estos problemas tan pronto como sea posible</color>.\n\nNos disculpamos por el inconveniente y hemos incluido un pequeño regalo para ti como compensación. \n\nGracias por tu comprensión y apoyo. ¡Nos vemos en la Taberna!\n\nComisario Roger | L18: Уважаемый капитан!\n\nИз-за сбоев в работе микросхем в вашем городе могут возникнуть <color=#ffa200>ошибки данных</color> или другие проблемы. Мы прилагаем все усилия, чтобы <color=#ffa200>исправить эти неполадки как можно скорее</color>.\n\nПриносим извинения за неудобства и отправляем вам небольшой подарок в качестве компенсации!\n\nСпасибо за понимание и поддержку. Увидимся в таверне!\n\nПомощник Роджер | M18: Sevgili Kaptan,\n\nDevre bozuklukları nedeniyle Şehrin <color=#ffa200>veri hataları</color> veya başka sorunlar yaşayabilir. <color=#ffa200>Bu sorunları olabildiğince hızlı çözmek</color> için çalışıyoruz.\n\nVerdiğimiz sıkıntıdan ötürü özür dileriz, bunun telafisi olarak sana küçük bir hediye sunuyoruz.\n\nAnlayışın ve desteğin için teşekkürler. Tavernada görüşürüz!\n\nYardımcı Roger | N18: Thưa Thủ Lĩnh,\n\nDo sự cố trục trặc về mạch điện, Thành phố của bạn có thể gặp <color=#ffa200>lỗi dữ liệu</color> hoặc các vấn đề khác. Chúng tôi đang hết sức nỗ lực để <color=#ffa200>khắc phục sự cố sớm nhất có thể</color>.\n\nChúng tôi xin lỗi vì sự bất tiện này và xin phép được tặng một món quà nhỏ để bù đắp cho bạn.\n\nCảm ơn bạn đã thông cảm và hỗ trợ. Hẹn gặp lại ở Tửu Quán nhé!\n\nPhụ tá Roger
B19: 游戏卡顿 | C19: 紧急问题说明 | D19: Urgent Fix Ongoing | E19: Résolution urgente en cours | F19: Dringende Fehlerbehebung im Gange | G19: Ajuste urgente em andamento | H19: 緊急問題說明 | I19: Perbaikan Mendesak Sedang Berlangsung | J19: กำลังดำเนินการแก้ไขอย่างเร่งด่วน | K19: Arreglo urgente en curso | L19: Срочное исправление | M19: Acil Tamir Devam Ediyor | N19: Chúng tôi đang khẩn trương sửa lỗi
C20: 亲爱的指挥官：\n\n由于城市电路故障，你的城市可能会出现<color=#ffa200>游戏卡顿</color>等情况，我们<color=#ffa200>正在紧急修复</color>电路。\n为您带来不便深感歉意，在此为您送上一份补偿，请注意查收。\n感谢您对Age of Apes的理解与支持，祝愿火箭发射顺利！\n\n罗杰副官 | D20: Dear Captain,\n\nDue to circuit malfunctions, your City may experience <color=#ffa200>freezes</color> or other issues. We are working hard to <color=#ffa200>fix these issues as quickly as possible</color>.\n\nWe apologize for the inconvenience and have included a small gift for you as compensation.\n\nThank you for your understanding and support. See you around the Tavern!\n\nDeputy Roger | E20: Cher capitaine,\n\nEn raison du dysfonctionnement d'un circuit, votre ville peut se <color=#ffa200>figer</color> ou présenter d'autres soucis. Nous travaillons dur pour <color=#ffa200>résoudre ces problèmes aussi vite que possible</color>.\n\nNous vous prions de nous excuser pour ce désagrément et vous offrons un petit cadeau en dédommagement.\n\nMerci pour votre compréhension et votre soutien. A bientôt à la taverne!\n\nRoger l'assistant | F20: Lieber Captain,\n\nAufgrund von Schaltkreisfehlern kann es in deiner Stadt zu <color=#ffa200>Programmabstürzen</color> oder anderen Problemen kommen. Wir arbeiten hart daran, <color=#ffa200>diese Probleme so schnell wie möglich zu beheben</color>.\n\nWir entschuldigen uns für die Unannehmlichkeiten und haben als Entschädigung ein kleines Geschenk für dich beigefügt.\n\nVielen Dank für dein Verständnis und deine Unterstützung. Wir sehen uns in der Taverne!\n\nAdjudant Roger" | G20: Caro Capitão,\n\nDevido a um mal funcionamento dos circuitos, sua cidade talvez enfrente <color=#ffa200>travamentos</color> ou outros problemas. Estamos trabalhando muito para <color=#ffa200>resolver esses problemas o quanto antes</color>.\n\nLamentamos pelo inconveniente e, por isso, incluímos um pequeno presente para você como compensação.\n\nNossa equipe agradece seu apoio e compreensão. Vemos você na taverna!\n\nDelegado Roger | H20: 親愛的指揮官：\n\n由於城市電路故障，你的城市可能會出現<color=#ffa200>遊戲卡頓</color>等情況，我們<color=#ffa200>正在緊急修復</color>電路。\n為您帶來不便深感歉意，在此為您送上一份補償，請注意查收。\n感謝你對Age of Apes的理解與支持，祝愿火箭發射順利！\n\n羅傑副官 | I20: Kapten yang terhormat,\n\nSehubungan dengan kerusakan sirkuit, Kotamu mungkin mengalami <color=#ffa200>freezes</color> atau masalah lain. Kami bekerja keras untuk <color=#ffa200>memperbaiki masalah ini secepat mungkin</color>.\n\nKami mohon maaf atas ketidaknyamanannya dan telah menyertakan hadiah kecil untukmu sebagai kompensasi.\n\nTerima kasih atas pengertian dan dukunganmu. Sampai Jumpa di Sekitar Kedai!\n\nDeputi Roger | J20: ถึงท่านผู้บัญชาการ\n\nเนื่องจากวงจรทำงานผิดปกติ เมืองของนายอาจประสบปัญหา<color=#ffa200>อาการค้าง</color>หรือปัญหาอื่น ๆ ได้ ซึ่งเรากำลังดำเนินการอย่างเต็มที่เพื่อ<color=#ffa200>แก้ไขปัญหาเหล่านี้โดยเร็วที่สุด</color>\n\nขออภัยในความไม่สะดวก เราจึงขอมอบของขวัญเล็ก ๆ น้อย ๆ นี้ให้เป็นการชดเชย\n\nขอขอบคุณสำหรับความเข้าใจและการสนับสนุนของนาย แล้วไว้เจอกันแถว ๆ โรงแรมนะ!\n\nท่านรองโรเจอร์ | K20: Querido Capitán, \n\nDebido a unos fallos en los circuitos tu Ciudad puede experimentar <color=#ffa200>bloqueos</color> u otros problemas. Estamos trabajando duro para <color=#ffa200>corregir estos problemas tan pronto como sea posible</color>.\n\nNos disculpamos por el inconveniente y hemos incluido un pequeño regalo para ti como compensación. \n\nGracias por tu comprensión y apoyo. ¡Nos vemos en la Taberna!\n\nComisario Roger | L20: Уважаемый капитан!\n\nИз-за сбоев в работе микросхем в вашем городе могут возникнуть <color=#ffa200>зависания</color> или другие проблемы. Мы прилагаем все усилия, чтобы <color=#ffa200>исправить эти неполадки как можно скорее</color>.\n\nПриносим извинения за неудобства и отправляем вам небольшой подарок в качестве компенсации!\n\nСпасибо за понимание и поддержку. Увидимся в таверне!\n\nПомощник Роджер | M20: Sevgili Kaptan,\n\nDevre bozuklukları nedeniyle Şehrin <color=#ffa200>donmalar</color> veya başka sorunlar yaşayabilir. <color=#ffa200>Bu sorunları olabildiğince hızlı çözmek</color> için çalışıyoruz.\n\nVerdiğimiz sıkıntıdan ötürü özür dileriz, bunun telafisi olarak sana küçük bir hediye sunuyoruz.\n\nAnlayışın ve desteğin için teşekkürler. Tavernada görüşürüz!\n\nYardımcı Roger | N20: Thưa Thủ Lĩnh,\n\nDo sự cố trục trặc về mạch điện, Thành phố của bạn có thể gặp <color=#ffa200>lỗi ngưng vận hành</color> hoặc các vấn đề khác. Chúng tôi đang hết sức nỗ lực để <color=#ffa200>khắc phục sự cố sớm nhất có thể</color>.\n\nChúng tôi xin lỗi vì sự bất tiện này và xin phép được tặng một món quà nhỏ để bù đắp cho bạn.\n\nCảm ơn bạn đã thông cảm và hỗ trợ. Hẹn gặp lại ở Tửu Quán nhé!\n\nPhụ tá Roger
B21: 部队丢失 | C21: 部队异常说明 | D21: Troop Data Error | E21: Erreur de données liées aux troupes | F21: Truppendatenfehler | G21: Erro nos dados de tropas | H21: 部隊異常說明 | I21: Kesalahan Data Pasukan | J21: ข้อผิดพลาดเกี่ยวกับข้อมูลกองทหาร | K21: Error en los Datos de la Tropa | L21: Ошибка данных войск | M21: Birlik Verisi Hatası | N21: Lỗi dữ liệu binh lính
C22: 亲爱的指挥官：\n\n你好，由于城市电路发生故障，你的部队可能会出现<color=#ffa200>丢失</color>的情况。我们正在处理解决这个问题。\n为您带来不便深感歉意，在此为您送上一份补偿，请注意查收。\n我们将不断改进，希望能得到你的理解与支持，祝愿火箭发射顺利！\n\n罗杰副官 | D22: Dear Captain,\n\nDue to circuit malfunctions, you may experience problems with <color=#ffa200>missing troops</color>. We are currently working to fix this issue.\n\nWe apologize for the inconvenience and have included a small gift for you as compensation.\n\nThank you for your understanding and support as we continue to improve. See you around the Tavern!\n\nDeputy Roger | E22: Cher capitaine,\n\nEn raison du dysfonctionnement d'un circuit, vous avez peut-être constaté des <color=#ffa200>troupes manquantes</color>. Nous travaillons actuellement à résoudre ce souci.\n\nNous vous prions de nous excuser pour ce désagrément et vous offrons un petit cadeau en dédommagement.\n\nMerci pour votre compréhension et votre soutien. A bientôt à la taverne!\n\nRoger l'assistant | F22: Lieber Captain,\n\nAufgrund von Schaltkreisfehlern kann es bei dir zu Problemen mit <color=#ffa200>fehlenden Truppen</color> kommen. Wir arbeiten aktuell daran, dieses Problem zu beheben.\n\nWir entschuldigen uns für die Unannehmlichkeiten und haben als Entschädigung ein kleines Geschenk für dich beigefügt.\n\nVielen Dank für dein Verständnis und deine Unterstützung, während wir uns weiter verbessern. Wir sehen uns in der Taverne!\n\nAdjudant Roger | G22: Caro Capitão,\n\nDevido a um mal funcionamento dos circuitos, você talvez tenha problemas com <color=#ffa200>tropas perdidas</color>. Estamos trabalhando para resolver esse problema.\n\nLamentamos pelo inconveniente e, por isso, incluímos um pequeno presente para você como compensação.\n\nNossa equipe agradece sua compreensão e apoio ao passo que continuamos melhorando. Vemos você na taverna!\n\nDelegado Roger | H22: 親愛的指揮官：\n\n你好，由於城市電路發生故障，你的部隊可能會出現<color=#ffa200>丟失</color>的情況。我們正在處理解決這個問題。\n為您帶來不便深感歉意，在此為您送上一份補償，請注意查收。\n我們將不斷改進，希望能得到你的理解與支持，祝愿火箭發射順利！\n\n羅傑副官 | I22: Kapten yang terhormat,\n\nSehubungan dengan kerusakan sirkuit, kamu mungkin mengalami masalah dengan <color=#ffa200>pasukan yang hilang</color>. Kami sedang berusaha untuk memperbaiki masalah ini.\n\nKami mohon maaf atas ketidaknyamanannya dan telah menyertakan hadiah kecil untukmu sebagai kompensasi.\n\nTerima kasih atas pengertian dan dukunganmu sementara kami terus meningkatkan game. Sampai jumpa di sekitar Kedai!\n\nDeputi Roger | J22: ถึงท่านผู้บัญชาการ\n\nเนื่องจากวงจรทำงานผิดปกติ นายอาจประสบปัญหา<color=#ffa200>กองทหารสูญหาย</color> ซึ่งในขณะนี้ เรากำลังดำเนินการแก้ไขปัญหานี้อย่างเต็มที่\n\nขออภัยในความไม่สะดวก เราจึงขอมอบของขวัญเล็ก ๆ น้อย ๆ ให้เป็นการชดเชย\n\nขอขอบคุณสำหรับความเข้าใจและการสนับสนุนการปรับปรุงอย่างต่อเนื่องของเรา แล้วไว้เจอกันแถว ๆ โรงแรมนะ!\n\nท่านรองโรเจอร์ | K22: Querido Capitán, \n\nDebido a unos fallos en los circuitos, puedes experimentar problemas con <color=#ffa200>tropas faltantes</color>. Estamos trabajando en este momento para corregir este problema.\n\nNos disculpamos por el inconveniente y hemos incluido un pequeño regalo para ti como compensación. \n\nGracias por tu comprensión y apoyo mientras continuamos mejorando. ¡Nos vemos en la Taberna!\n\nComisario Roger | L22: Уважаемый капитан!\n\nИз-за сбоев в работе микросхем в вашем городе могут возникнуть проблемы с <color=#ffa200>исчезновением войск</color>. Мы прилагаем все усилия, чтобы исправить эти неполадки.\n\nПриносим извинения за неудобства и отправляем вам небольшой подарок в качестве компенсации!\n\nСпасибо за понимание и поддержку наших мер по улучшению игры. Увидимся в таверне!\n\nПомощник Роджер | M22: Sevgili Kaptan,\n\nDevre bozuklukları nedeniyle <color=#ffa200>eksik birlikler</color> konusunda sorun yaşayabilirsin. Bu sorunu çözmek için şu anda çalışıyoruz.\n\nVerdiğimiz sıkıntıdan ötürü özür dileriz, bunun telafisi olarak sana küçük bir hediye sunuyoruz.\n\nGelişme sürecimizdeki anlayışın ve desteğin için teşekkürler. Tavernada görüşürüz!\n\nYardımcı Roger | N22: Thưa Thủ Lĩnh,\n\nDo sự cố trục trặc về mạch điện, bạn có thể gặp tình trạng <color=#ffa200>binh lính mất tích</color>. Chúng tôi hiện đang tìm cách khắc phục sự cố này.\n\nChúng tôi xin lỗi vì sự bất tiện này và xin phép được tặng một món quà nhỏ để bù đắp cho bạn.\n\nCảm ơn bạn đã thông cảm và ủng hộ trong thời gian chúng tôi tiếp tục cải thiện trò chơi. Hẹn gặp lại ở Tửu Quán nhé!\n\nPhụ tá Roger
B23: 部队丢失修复 | C23: 部队异常修复说明 | D23: Troop Data Error Fixed | E23: Résolution de l'erreur de données liées aux troupes | F23: Truppendatenfehler behoben | G23: Erro nos dados de tropas resolvido | H23: 部隊異常修復說明 | I23: Kesalahan Data Pasukan Diperbaiki | J23: แก้ไขข้อผิดพลาดเกี่ยวกับข้อมูลกองทหารแล้ว | K23: Error en los Datos de la Tropa corregido | L23: Ошибка данных войск исправлена | M23: Birlik Verisi Hatası Düzeltildi | N23: Đã khắc phục lỗi dữ liệu binh lính
C24: 亲爱的指挥官：\n\n由于城市里令人不安的蟑螂，你的城市可能遇到了<color=#ffa200>部队损失</color>。我们的团队已经解决了这个问题，所有的部队都回来了!你可以检查一下，他们已经回到你的城市了!我们对你遇到的麻烦感到抱歉。\n感谢您对Age of Apes的理解和支持。祝你能喝到所有的香蕉冰沙!\n\n罗杰副官 | D24: Dear Captain,\n\nDue to circuit malfunctions, you may have experienced problems with <color=#ffa200>missing troops</color>. We have fixed the issue and all of your troops have returned to your City! Make an inspection, we're sure you'll find them all present and accounted for.\n\nWe apologize for the inconvenience and will work hard to bring you a better gaming experience.\n\nThank you for your understanding and support. See you around the Tavern!\n\nDeputy Roger | E24: Cher capitaine,\n\nEn raison du dysfonctionnement d'un circuit, vous avez peut-être constaté des <color=#ffa200>troupes manquantes</color>. Nous avons résolu le problème et toutes vos troupes sont de retour dans votre ville. Vous pouvez effectuer une inspection, nous sommes certains qu'elles répondront toutes à l'appel.\n\nNous vous prions de nous excuser pour ce désagrément. Nous continuons de travailler dur pour vous proposer une expérience de jeu optimale.\n\nMerci pour votre compréhension et votre soutien. A bientôt à la taverne!\n\nRoger l'assistant | F24: Lieber Captain,\n\nAufgrund von Schaltkreisfehlern kann es sein, dass du Probleme mit <color=#ffa200>fehlenden Truppen</color> hattest. Wir haben das Problem behoben und alle deine Truppen sind in deine Stadt zurückgekehrt! Mach eine Inspektion, wir sind sicher, du wirst sie alle anwesend und bereit vorfinden.\n\nWir entschuldigen uns für die Unannehmlichkeiten und werden hart daran arbeiten, dir ein besseres Spielerlebnis zu bieten.\n\nVielen Dank für dein Verständnis und deine Unterstützung. Wir sehen uns in der Taverne!\n\nAdjudant Roger | G24: Caro Capitão,\n\nDevido a um mal funcionamento dos circuitos, você talvez notou alguns problemas com <color=#ffa200>tropas perdidas</color>. Resolvemos esse problema e todas as suas tropas devem ter retornado para a sua cidade! Confira suas tropas. Temos certeza de que você as encontrará conforme o esperado.\n\nLamentamos pelo ocorrido e trabalharemos ainda mais para melhorar sua experiência dentro do jogo.\n\nNossa equipe agradece seu apoio e compreensão. Vemos você na taverna!\n\nDelegado Roger | H24: 親愛的指揮官：\n\n由於城市裡令人不安的蟑螂，你的城市可能遇到了<color=#ffa200>部隊損失</color>。我們的團隊已經解決了這個問題，所有的部隊都回來了!你可以檢查一下，他們已經回到你的城市了!我們對你遇到的麻煩感到抱歉。\n感謝您對Age of Apes的理解和支持。祝你能喝到所有的香蕉冰沙!\n\n羅傑副官 | I24: Kapten yang terhormat,\n\nSehubungan dengan kerusakan sirkuit, kamu mungkin mengalami masalah dengan <color=#ffa200>pasukan yang hilang</color>. Kami telah memperbaiki masalah tersebut dan semua pasukanmu telah kembali ke Kotamu! Lakukan pemeriksaan, kami yakin kamu akan menemukan semuanya ada dan dipertanggungjawabkan.\n\nKami mohon maaf atas ketidaknyamanan ini dan akan bekerja keras untuk memberikanmu pengalaman bermain game yang lebih baik.\n\nTerima kasih atas pengertian dan dukunganmu. Sampai Jumpa di Sekitar Kedai!\n\nDeputi Roger | J24: ถึงท่านผู้บัญชาการ\n\nเนื่องจากวงจรทำงานผิดปกติ นายอาจประสบปัญหา<color=#ffa200>กองทหารสูญหาย</color> ซึ่งเราได้จัดการแก้ไขปัญหาและกองทหารทั้งหมดของนายก็ได้กลับไปที่เมืองของนายแล้ว! ลองไปตรวจสอบดูนะ เรามั่นใจว่านายจะพบกองทหารของนายอยู่กันพร้อมหน้าเลยล่ะ\n\nขออภัยในความไม่สะดวก และเราจะพยายามอย่างเต็มที่เพื่อให้นายได้รับประสบการณ์การเล่นเกมที่ดียิ่ง ๆ ขึ้นไป\n\nขอขอบคุณสำหรับความเข้าใจและการสนับสนุนของนาย แล้วไว้เจอกันแถว ๆ โรงแรมนะ!\n\nท่านรองโรเจอร์ | K24: Querido Capitán, \n\nDebido a unos fallos en los circuitos, puedes experimentar problemas con <color=#ffa200>tropas faltantes</color>. Hemos corregido este problema y, ¡todas tus tropas han regresado a la Ciudad! Haz una inspección para asegurarte de que las encuentres presentes y contabilizadas.\n\nNos disculpamos por el inconveniente y trabajaremos duro para traerte una mejor experiencia de juego. \n\nGracias por tu comprensión y apoyo. ¡Nos vemos en la Taberna!\n\nComisario Roger | L24: Уважаемый капитан!\n\nИз-за сбоев в работе микросхем вы могли столкнуться с <color=#ffa200>исчезновением войск</color>. Мы исправили эту проблему, и ваши войска вернулись в город. Можете проверить: мы уверены, что вы найдете их в целости и сохранности.\n\nПриносим извинения за неудобства — мы будем усердно работать, чтобы дарить вам лучшие впечатления от игры.\n\nСпасибо за понимание и поддержку. Увидимся в таверне!\n\nПомощник Роджер | M24: Sevgili Kaptan,\n\nDevre bozuklukları nedeniyle <color=#ffa200>eksik birlikler</color> konusunda sorun yaşamış olabilirsin. Sorunu çözdük ve tüm birliklerin Şehrine döndü! Teftiş yap, hepsini yerli yerinde ve olması gereken sayıda bulacağına eminiz.\n\nVerdiğimiz sıkıntıdan ötürü özür dileriz ve sana daha iyi bir oyun deneyimi sunmak için çok çalışacağız.\n\nAnlayışın ve desteğin için teşekkürler. Tavernada görüşürüz!\n\nYardımcı Roger | N24: Thưa Thủ Lĩnh,\n\nDo sự cố trục trặc về mạch điện, bạn có thể đã gặp phải tình trạng <color=#ffa200>binh lính mất tích</color>. Chúng tôi đã khắc phục xong sự cố và tất cả binh lính đã trở về Thành phố của bạn! Kiểm tra nhé, chúng tôi chắc chắn bạn sẽ thấy tất cả binh lính đều xuất hiện không thiếu một ai đâu.\n\nChúng tôi chân thành xin lỗi vì sự bất tiện này và sẽ làm việc chăm chỉ để mang lại cho bạn những trải nghiệm tốt hơn trong trò chơi.\n\nCảm ơn bạn đã thông cảm và hỗ trợ. Hẹn gặp lại ở Tửu Quán nhé!\n\nPhụ tá Roger
B25: 活动排名异常修复 | C25: 活动排名积分已解决 | D25: Ranking Points Issue Fixed | E25: Résolution d'un problème de classement | F25: Problem mit Ranglistenpunkten behoben | G25: Resolução do problema nos pontos de classificação | H25: 活動排名積分已解決 | I25: Masalah Poin Peringkat Diperbaiki | J25: แก้ไขปัญหาเกี่ยวกับคะแนนอันดับ | K25: Problema con los Puntos de Clasificación corregido | L25: Исправлена проблема с очками рейтинга | M25: Sıralama Puanları Sorunu Düzeltildi | N25: Đã khắc phục sự cố điểm BXH
C26: 亲爱的指挥官：\n\n你好，由于城市电路发生故障，少数玩家的<color=#ffa200>活动排名积分</color>出现了<color=#ffa200>计算错误</color>的情况。我们已经处理了这个问题，后续活动的积分将<color=#ffa200>正常显示</color>。\n为您带来不便深感歉意，在此为您送上一份补偿，请注意查收。\n我们将不断改进，希望能得到你的理解与支持，祝愿火箭发射顺利！\n\n罗杰副官 | D26: Dear Captain,\n\nDue to circuit malfunctions, some players experienced <color=#ffa200>calculation errors</color> in their <color=#ffa200>event ranking points</color>. We have fixed this issue and ranking points will <color=#ffa200>display normally</color> going forward.\n\nWe apologize for the inconvenience and have included a small gift for you as compensation.\n\nThank you for your understanding and support as we continue to improve. See you around the Tavern!\n\nDeputy Roger | E26: Cher capitaine,\n\nEn raison du dysfonctionnement d'un circuit, certains joueurs ont constaté des <color=#ffa200>erreurs de calcul</color> dans leur <color=#ffa200>score de classement dans un évènement</color>. Nous avons résolu le problème et les scores affichés sont de <color=#ffa200>retour à la normale</color>.\n\nNous vous prions de nous excuser pour ce désagrément et vous offrons un petit cadeau en dédommagement.\n\nMerci pour votre compréhension et votre soutien. Nous travaillons dur pour continuer à nous améliorer. A bientôt à la taverne!\n\nRoger l'assistant | F26: Lieber Captain,\n\nAufgrund von Schaltkreisfehlern kam es bei einigen Spielern zu <color=#ffa200>Berechnungsfehlern</color> bei ihren <color=#ffa200>Event-Ranglistenpunkten</color>. Wir haben dieses Problem behoben und die Ranglistenpunkte werden in Zukunft <color=#ffa200>normal angezeigt</color>.\n\nWir entschuldigen uns für die Unannehmlichkeiten und haben als Entschädigung ein kleines Geschenk für dich beigefügt.\n\nVielen Dank für dein Verständnis und deine Unterstützung, während wir uns weiter verbessern. Wir sehen uns in der Taverne!\n\nAdjudant Roger | G26: Caro Capitão,\n\nDevido a um mal funcionamento dos circuitos, alguns jogadores notaram <color=#ffa200>erros de cálculo</color> em seus <color=#ffa200>pontos de classificação de eventos</color>. Resolvemos o problema e os pontos de classificação estão sendo <color=#ffa200>mostrados normalmente</color> a partir de agora.\n\nLamentamos pelo inconveniente e, por isso, incluímos um pequeno presente para você como compensação.\n\nNossa equipe agradece sua compreensão e apoio ao passo que continuamos melhorando. Vemos você na taverna!\n\nDelegado Roger | H26: 親愛的指揮官：\n\n你好，由於城市電路發生故障，少數玩家的<color=#ffa200>活動排名積分</color>出現了<color=#ffa200>計算錯誤</color>的情況。我們已經處理了這個問題，後續活動的積分將<color=#ffa200>正常顯示</color>。\n為您帶來不便深感歉意，在此為您送上一份補償，請注意查收。\n我們將不斷改進，希望能得到你的理解與支持，祝愿火箭發射順利！\n\n羅傑副官 | I26: Kapten yang terhormat,\n\nSehubungan dengan kerusakan sirkuit, sejumlah pemain mengalami <color=#ffa200>kesalahan perhitungan</color> pada <color=#ffa200>poin peringkat acara</color>. Kami telah memperbaiki masalah ini dan poin peringkat akan <color=#ffa200>ditampilkan secara normal</color> selanjutnya.\n\nKami mohon maaf atas ketidaknyamanannya dan telah menyertakan hadiah kecil untukmu sebagai kompensasi.\n\nTerima kasih atas pengertian dan dukunganmu sementara kami terus meningkatkan game. Sampai jumpa di sekitar Kedai!\n\nDeputi Roger | J26: ถึงท่านผู้บัญชาการ\n\nเนื่องจากวงจรทำงานผิดปกติ ผู้เล่นบางคนอาจพบ<color=#ffa200>ข้อผิดพลาดในการคำนวณ</color><color=#ffa200>คะแนนอันดับกิจกรรม</color> เราได้แก้ไขปัญหานี้แล้วและคะแนนอันดับจะ<color=#ffa200>แสดงอันดับที่ถูกต้อง</color>ในอนาคต\n\nขออภัยในความไม่สะดวก เราจึงขอมอบของขวัญเล็ก ๆ น้อย ๆ ให้เป็นการชดเชย\n\nขอขอบคุณสำหรับความเข้าใจและการสนับสนุนการปรับปรุงอย่างต่อเนื่องของเรา แล้วไว้เจอกันแถว ๆ โรงแรมนะ!\n\nท่านรองโรเจอร์ | K26: Querido Capitán, \n\nDebido a unos fallos en los circuitos, algunos jugadores han experimentado <color=#ffa200>errores de cálculo</color> en sus <color=#ffa200>puntos de clasificación del evento</color>. Hemos corregido este problema y los puntos de clasificación ahora <color=#ffa200>se desplegarán normalmente</color> de aquí en adelante.\n\nNos disculpamos por el inconveniente y hemos incluido un pequeño regalo para ti como compensación. \n\nGracias por tu comprensión y apoyo mientras continuamos mejorando. ¡Nos vemos en la Taberna!\n\nComisario Roger | L26: Уважаемый капитан!\n\nИз-за сбоев в работе микросхем некоторые игроки столкнулись с <color=#ffa200>ошибками подсчета</color> <color=#ffa200>очков рейтинга в событии</color>. Мы исправили эту проблему, и теперь очки рейтинга будут <color=#ffa200>отображаться нормально</color>.\n\nПриносим извинения за неудобства и отправляем вам небольшой подарок в качестве компенсации!\n\nСпасибо за понимание и поддержку наших мер по улучшению игры. Увидимся в таверне!\n\nПомощник Роджер | M26: Sevgili Kaptan,\n\nDevre bozuklukları yüzünden bazı oyuncular <color=#ffa200>etkinlik sıralama puanlarında</color> <color=#ffa200>hesaplama hatalarıyla</color> karşılaştılar. Bu sorunu düzelttik ve sıralama puanları bundan sonra <color=#ffa200>normal şekilde görüntülenecek</color>.\n\nVerdiğimiz sıkıntıdan ötürü özür dileriz, bunun telafisi olarak sana küçük bir hediye sunuyoruz.\n\nGelişme sürecimizdeki anlayışın ve desteğin için teşekkürler. Tavernada görüşürüz!\n\nYardımcı Roger | N26: Thưa Thủ Lĩnh,\n\nDo sự cố trục trặc về mạch điện, một vài người chơi đã gặp phải <color=#ffa200>lỗi tính toán</color> trong <color=#ffa200>việc tính điểm xếp hạng</color>. Chúng tôi đã khắc phục sự cố này và điểm xếp hạng sẽ <color=#ffa200>hiển thị bình thường</color> trong tương lai\n\nChúng tôi xin lỗi vì sự bất tiện này và xin phép được tặng một món quà nhỏ để bù đắp cho bạn.\n\nCảm ơn bạn đã thông cảm và ủng hộ trong thời gian chúng tôi tiếp tục cải thiện trò chơi. Hẹn gặp lại ở Tửu Quán nhé!\n\nPhụ tá Roger
B27: 回档邮件 | C27: 通知：数据已修复 | D27: Data Error Fixed | E27: Résolution d'une erreur de données | F27: Datenfehler behoben | G27: Resolvido o erro nos dados | H27: 通知：數據已修復 | I27: Kesalahan Data Diperbaiki | J27: แก้ไขข้อผิดพลาดเกี่ยวกับข้อมูลแล้ว | K27: Corrección en el error de Datos | L27: Исправлена ошибка в данных | M27: Veri Hatası Düzeltildi | N27: Đã khắc phục lỗi dữ liệu
C28: 亲爱的指挥官：\n\n由于系统故障，导致一些玩家收到多封相同的邮件，重复领取了邮件中的50 CD道具。\n我们的团队已经解决了这个问题，同时，我们会将您的数据<color=#ffa200>回档至问题发生前</color>（即UTC时间2020年02月18日20:00之前）。\n\n我们无比珍视您在Age of Apes投入的心血和宝贵的时间，回档给您带来的损失，我们深感抱歉。\n请收下我们为您准备的赔偿：\n\n我们真诚地感谢您对Age of Apes的支持、包容和热爱。\n\n罗杰副官 | D28: Dear Captain,\n\nDue to circuit malfunctions, some players received the same mail multiple times by mistake and repeatedly claimed the attached 50 CDs item.\n\nWe have fixed this issue and will be <color=#ffa200>restoring your data to before the problem occurred</color> (i.e. before 2020-02-18 20:00 UTC).\n\nWe appreciate the time and effort you've put into Age of Apes and sincerely apologize for any loss caused by the data restoration. We've included a small gift for you as compensation:\n\nThank you very much for your support and understanding.\n\nDeputy Roger | E28: Cher capitaine,\n\nEn raison du dysfonctionnement d'un circuit, certains joueurs ont reçu plusieurs fois le même message et ont récupéré les 50 CD qu'il contenait à de multiples reprises.\n\nNous avons résolu le problème et nous allons <color=#ffa200>restaurer vos données à l'état antérieur au problème</color> (c'est-à-dire avant le 18/02/2020 à 20:00 TU).\n\nNous sommes conscients du temps et des efforts que vous investissez dans Age of Apes. C'est pourquoi nous vous prions de nous excuser pour les éventuelles pertes dues à la restauration des données. Voici un petit cadeau en dédommagement:\n\nMerci infiniment pour votre compréhension et votre soutien.\n\nRoger l'assistant | F28: Lieber Captain,\n\nAufgrund von Schaltkreisfehlern haben einige Spieler fälschlicherweise dieselbe Mail mehrfach erhalten und wiederholt das angehängte 50-CDs-Item beansprucht.\n\nWir haben dieses Problem behoben und werden <color=#ffa200>deine Daten auf den Stand vor dem Auftreten des Problems zurücksetzen</color> (d.h. vor 28.02.2020 20:00 UTC).\n\nWir schätzen die Zeit und Mühe, die du in Age of Apes gesteckt hast und entschuldigen uns aufrichtig für den Verlust, der durch die Datenwiederherstellung entstanden ist. Als Entschädigung haben wir ein kleines Geschenk für dich beigefügt:\n\nVielen Dank für dein Verständnis und deine Unterstützung.\n\nAdjudant Roger | G28: Caro Capitão,\n\nDevido a um mal funcionamento dos circuitos, alguns jogadores receberam a mesma mensagem várias vezes por engano e resgataram mais de uma vez o item de 50 CDs que estava no anexo.\n\nResolvemos este problema e <color=#ffa200>restauramos os dados para antes do problema ter acontecido</color>, ou seja, antes de 18/02/2020, às 20:00 (UTC).\n\nAgradecemos pelo seu tempo e esforços em Ages of Apes e lamentamos por quaisquer perdas causadas pela restauração desses dados. Incluímos um pequeno presente para você como compensação:\n\nAgradecemos pelo apoio e compreensão.\n\nDelegado Roger | H28: 親愛的指揮官：\n\n由於系統故障，導致一些玩家收到多封相同的郵件，重複領取了郵件中的50 CD道具。\n我們的團隊已經解決了這個問題，同時，我們會將您的數據<color=#ffa200>回檔至問題發生前</color>（即UTC時間2020年02月18日20:00之前）。\n\n我們無比珍視您在Age of Apes投入的心血和寶貴的時間，回檔給您帶來的損失，我們深感抱歉。\n請收下我們為您準備的賠償：\n\n我們真誠地感謝您對Age of Apes的支持、包容和熱愛。\n\n羅傑副官 | I28: Kapten yang terhormat,\n\nSehubungan dengan kerusakan sirkuit, sejumlah pemain menerima email yang sama beberapa kali secara tidak sengaja dan berulang kali mengklaim item 50 CD yang disertakan.\n\nKami telah memperbaiki masalah ini dan akan <color=#ffa200>memulihkan datamu ke sebelum masalah terjadi</color> (i.e. before 2020-02-18 20:00 UTC).\n\nKami menghargai waktu dan upaya yang kamu lakukan untuk Age of Apes dan dengan tulus meminta maaf atas kerugian yang disebabkan oleh pemulihan data. Kami telah menyertakan hadiah kecil untukmu sebagai kompensasi:\n\nTerima kasih banyak atas dukungan dan pengertiannya.\n\nDeputi Roger | J28: ถึงท่านผู้บัญชาการ\n\nเนื่องจากวงจรทำงานผิดปกติ ทำให้ผู้เล่นบางคนได้รับจดหมายฉบับเดียวกันซ้ำหลายครั้งโดยไม่ได้ตั้งใจ และได้รับไอเทมซีดี 50 แผ่นที่แนบไปซ้ำ ๆ\n\nเราได้แก้ไขปัญหานี้แล้ว และจะ<color=#ffa200>กู้คืนข้อมูลของนายไปในช่วงก่อนที่ปัญหาจะเกิดขึ้น</color> (เช่น ก่อนวันที่ 18-02-2020 20:00 ตามเวลา UTC)\n\nขอขอบคุณที่สละเวลาและความพยายามที่มีให้กับ Age of Apes และขออภัยเป็นอย่างยิ่งสำหรับความสูญเสียใด ๆ ที่เกิดขึ้นจากการกู้คืนข้อมูล เราจึงขอมอบของขวัญเล็ก ๆ น้อย ๆ ให้เป็นการชดเชย:\n\nขอขอบคุณอย่างยิ่งสำหรับการสนับสนุนและความเข้าใจของนาย\n\nท่านรองโรเจอร์ | K28: Querido Capitán, \n\nDebido a unos fallos en los circuitos algunos jugadores recibieron el mismo correo múltiples veces por error y pudieron reclamar repetidamente el artículo de 50 CD adjunto. \n\nHemos corregido este error y estaremos <color=#ffa200>restaurando tus datos al punto antes de que el problema ocurriera</color> (por ejemplo, antes del 18-02-2020 20:00 UTC).\n\nApreciamos el tiempo y esfuerzo que haz puesto en Age of Apes y sinceramente nos disculpamos por cualquier pérdida de datos provocada por esta restauración de datos. Hemos incluido un pequeño regalo para ti como compensación:\n\nMuchas gracias por tu apoyo y comprensión. \n\nComisario Roger | L28: Уважаемый капитан!\n\nИз-за сбоев в работе микросхем некоторые игроки ошибочно получили одно и то же письмо несколько раз и несколько раз забрали приложенный предмет на 50 CD.\n\nМы исправили эту проблему и проведем <color=#ffa200>возврат данных к состоянию до произошедшей ошибки</color> (то есть до 20:00 18.02.2020 UTC).\n\nМы ценим то, сколько времени и сил вы вкладываете в Age of Apes, и приносим искренние извинения за потери, которые может вызвать восстановление данных. В качестве компенсации отправляем вам небольшой подарок:\n\nБольшое спасибо за понимание и поддержку.\n\nПомощник Роджер | M28: Sevgili Kaptan,\n\nDevre bozuklukları yüzünden bazı oyuncular yanlışlıkla aynı postayı birden fazla kez aldılar ve ekteki 50 CD’lik eşyayı tekrar tekrar aldılar.\n\nBu sorunu düzelttik ve <color=#ffa200>verini sorun ortaya çıkmadan önceki hâliyle geri getireceğiz</color> (ör. 18.02.2020, 20.00 (UTC) öncesi).\n\nAge of Apes’e ayırdığın zaman ve tüm çabaların için teşekkürler, veri geri getirmeden kaynaklanan kayıplar için içtenlikle özür dileriz. Telafi olarak sana küçük bir hediye sunuyoruz:\n\nDesteğin ve anlayışın için çok teşekkürler.\n\nYardımcı Roger | N28: Thưa Thủ Lĩnh,\n\nDo sự cố trục trặc về mạch điện, một lá thư đã được gửi đến một số người chơi nhiều lần do nhầm lẫn và người chơi liên tục nhận các vật phẩm trị giá 50 CD được đính kèm trong thư.\n\nChúng tôi đã khắc phục sự cố này và sẽ <color=#ffa200>khôi phục dữ liệu của bạn trước khi có vấn đề xảy ra</color> (ví dụ trước 20:00 ngày 18/02/2020 UTC).\n\nChúng tôi vô cùng trân trọng thời gian và công sức mà bạn đã bỏ ra cho Age of Apes, và chân thành xin lỗi vì mọi tổn thất do quá trình khôi phục dữ liệu gây ra. Chúng tôi đã gửi kèm một món quà nhỏ cho bạn để đền bù:\n\nChúng tôi vô cùng cảm ơn các bạn đã thông cảm và ủng hộ.\n\nPhụ tá Roger
B29: 奖励补发 | C29: 奖励补偿发放 | D29: Reward Re-Send | E29: Renvoi de récompenses | F29: Belohnung erneut gesendet | G29: Reenvio de recompensa | H29: 獎勵補償發放 | I29: Hadiah Dikirim Ulang | J29: การส่งรางวัลซ้ำ | K29: Re-envío de la Recompensa | L29: Повторная отправка наград | M29: Ödüllerin Yeniden Yollanması | N29: Gửi lại phần thưởng
C30: 亲爱的指挥官：\n\n由于游戏内数据异常，导致您在{0}中<color=#ffa200>没有收到对应的奖励</color>，我们已经修复了这个问题，因此给您带来的不便我们深感歉意，在此将奖励补发给您，请注意查收：\n\n感谢您对Age of Apes的理解与支持，祝愿火箭发射顺利！\n\n罗杰副官 | D30: Dear Captain,\n\nDue to data abnormalities, you <color=#ffa200>did not receive the corresponding rewards</color> for {0}. We have fixed this issue and have included the appropriate rewards here. Please claim them below.\n\nThank you for your understanding and support of Age of Apes. May the bananas be with you and see you around the Tavern!\n\nDeputy Roger | E30: Cher capitaine,\n\nEn raison d'une erreur de données, <color=#ffa200>vous n'avez pas reçu les récompenses</color> liées à {0}. Nous avons résolu ce problème et vous transmettons lesdites récompenses. Veuillez les récupérer ci-dessous.\n\nMerci pour votre compréhension et votre soutien à Age of Apes. Gardez la banane, et à bientôt à la taverne!\n\nRoger l'assistant | F30: Lieber Captain,\n\nAufgrund von Datenanomalien hast du <color=#ffa200>nicht die entsprechenden Belohnungen</color> für {0} erhalten. Wir haben dieses Problem behoben und die entsprechenden Belohnungen hier beigefügt. Bitte fordere sie unten ein.\n\nVielen Dank für dein Verständnis und deine Unterstützung von Age of Apes. Mögen die Bananen mit dir sein und wir sehen uns in der Taverne!\n\nAdjudant Roger | G30: Caro Capitão,\n\nDevido a alguns problemas com os dados, você <color=#ffa200>não recebeu as seguintes recompensas</color> para {0}. Resolvemos este problemas e incluímos as recompensas correspondentes aqui. Resgate-as abaixo.\n\nNossa equipe agradece sua compreensão e apoio a Age of Apes. Que as bananas estejam com você! Nos vemos na taverna!\n\nDelegado Roger | H30: 親愛的指揮官：\n\n由於遊戲內數據異常，導致您在{0}中<color=#ffa200>沒有收到對應的獎勵</color>，我們已經修復了這個問題，因此給您帶來的不便我們深感歉意，在此將獎勵補發給您，請注意查收：\n\n感謝您對Age of Apes的理解與支持，祝愿火箭發射順利！\n\n羅傑副官 | I30: Kapten yang terhormat,\n\nSehubungan dengan ketidaknormalan data, kamu <color=#ffa200>tidak menerima hadiah yang sesuai</color> for {0}. Kami telah memperbaiki masalah ini dan telah menyertakan hadiah yang sesuai di sini. Klaim di bawah ini.\n\nTerima kasih atas pengertian dan dukunganmu terhadap Age of Apes. Semoga pisang menyertaimu dan sampai jumpa di sekitar Kedai!\n\nDeputi Roger | J30: ถึงท่านผู้บัญชาการ\n\nเนื่องจากข้อมูลผิดปกติ นายจึงอาจ<color=#ffa200>ไม่ได้รับรางวัล</color>ของ{0}ตามที่กำหนด เราได้แก้ไขปัญหานี้แล้วและได้มอบรางวัลที่ถูกต้องมาให้ที่นี่แล้ว รีบไปรับรางวัลด้านล่างได้เลย\n\nขอขอบคุณสำหรับความเข้าใจและการสนับสนุน Age of Apes ของนาย ขอให้กล้วยจงสถิตย์อยู่กับนาย แล้วไว้เจอกันแถว ๆ โรงแรมนะ!\n\nท่านรองโรเจอร์ | K30: Querido Capitán, \n\nDebido a una anormalidad de datos, no <color=#ffa200>recibiste las recompensas correspondientes</color> por {0}. Hemos corregido este problema y hemos incluido las recompensas apropiadas aquí. Por favor, reclámalas debajo.\n\nGracias por tu comprensión y apoyo a Age of Apes. Que las bananas te acompañen y, ¡nos vemos en la Taberna!\n\nComisario Roger | L30: Уважаемый капитан!\n\nВ связи с аномальными игровыми данными вы <color=#ffa200>не получили соответствующую награду</color> за событие «{0}». Мы исправили эту проблему и отправляем ваши награды. Пожалуйста, заберите их ниже.\n\nСпасибо за понимание и поддержку Age of Apes. Да пребудут с вами бананы — и увидимся в таверне!\n\nПомощник Роджер | M30: Sevgili Kaptan,\n\nVeri anormallikleri nedeniyle {0} ile <color=#ffa200>ilgili ödülleri almadın</color>. Bu sorunu düzelttik ve ilgili ödülleri şu an buraya ekledik. Lütfen bunları aşağıdan al.\n\nAnlayışınız ve Age of Apes’e verdiğiniz destek için teşekkür ederiz. Muzlar seninle olsun, Tavernada görüşmek üzere!\n\nYardımcı Roger | N30: Thưa Thủ Lĩnh,\n\nDo xảy ra bất thường trong dữ liệu, bạn <color=#ffa200>không nhận được phần thưởng tương ứng</color> cho {0}. Chúng tôi đã khắc phục sự cố này và đã gửi kèm một phần thưởng thích hợp trong thông báo này. Vui lòng nhận phần thưởng ở bên dưới.\n\nCảm ơn lòng thông cảm và tinh thần hỗ trợ Age of Apes của bạn. Chúc kho của bạn luôn đầy chuối và hẹn gặp bạn ở Tửu Quán!\n\nPhụ tá Roger
B31: 地图改动补偿 | C31: 地图改动补偿 | D31: Map Change Compensation | E31: Dédommagement pour modification de la carte | F31: Entschädigung für Änderungen an der Karte | G31: Compensação pela Mudança de Mapa | H31: 地圖改動補償 | I31: Kompensasi Perubahan Peta | J31: การชดเชยการเปลี่ยนแปลงแผนที่ | K31: Compensación por cambio de mapa | L31: Компенсация за изменение карты | M31: Harita Değişikliği Telafisi | N31: Đền Bù Thay Đổi Bản Đồ
C32: 亲爱的指挥官：\n我们在最近的更新中修改了地图，这可能导致您丢失某些占领的地图单位、修建的帮派建筑，或基地被移动。\n以下是给您的补偿，请收下。 | D32: Dear Captain, \nWe made changes to the map in the most recent game update. This may have caused you to lose certain occupied map units or Gang buildings, or to have your City moved. \nWe have included a reward for you as compensation. Thank you for your understanding and support. | E32: Capitaine,\nNous avons modifié la carte lors de la dernière mise à jour du jeu. En raison de ces changements, vous avez peut-être perdu des unités, des bâtiments de gang, ou votre ville a été déplacée.\nVoici un cadeau en dédommagement. Merci pour votre compréhension et votre soutien. | F32: Hallo Captain, \nWir haben mit dem letzten Spielupdate Änderungen an der Karte vorgenommen. Dies kann dazu geführt haben, dass du bestimmte besetzte Karteneinheiten oder Clan-Gebäude verloren hast oder dass deine Stadt versetzt wurde. \nWir haben als Entschädigung eine Belohnung für dich beigefügt. Vielen Dank für dein Verständnis und deine Unterstützung. | G32: Caro Capitão, \nFizemos algumas mudanças no mapa na atualização mais recente do jogo. Isso pode ter feito você perder algumas unidades no mapa ocupado, estruturas da gangue ou sua cidade mudou de lugar. \nIncluímos uma recompensa para você como compensação. Nossa equipe agradece seu apoio e compreensão. | H32: 親愛的指揮官：\n我們在最近的更新中修改了地圖，這可能導致您丟失某些佔領的地圖單位、修建的幫派建築，或基地被移動。 \n以下是給您的補償，請收下。 | I32: Kapten yang terhormat, \nKami membuat perubahan pada peta di pembaruan game terkini. Ini mungkin akan mengakibatkanmu kehilangan unit peta atau bangunan Geng tertentu yang diduduki, atau memindahkan Kotamu. \nKami telah menyertakan hadiah untukmu sebagai kompensasi. Terima kasih atas pengertian dan dukunganmu. | J32: ถึงกัปตัน\nเราได้ทำการเปลี่ยนแปลงแผนที่ในการอัปเดตเกมล่าสุด ซึ่งอาจทำให้คุณสูญเสียหน่วยทหารที่ทำการครอบครองอยู่บนแผนที่หรือสิ่งปลูกสร้างของแก๊ง หรือเมืองของคุณอาจถูกย้ายตำแหน่ง\nเราจึงขอส่งรางวัลนี้มาให้คุณแทนคำขออภัย ขอขอบคุณสำหรับความเข้าใจและการสนับสนุนของคุณ | K32: Querido Capitán: \nHemos realizado cambios en el mapa durante la más reciente actualización del juego. Esto puede haber provocado que perdieras algunas unidades de mapa ocupadas o edificios de la Banda, o, que tu Ciudad se haya movido de lugar. \nHemos incluido una recompensa para ti como compensación. Gracias por tu comprensión y apoyo. | L32: Уважаемый капитан! \nВ последнем обновлении игры мы внесли изменения в карту. Это могло привести к потерям тех или иных оккупированных построек на карте или зданий банды, а также к перемещению вашего города. \nВ качестве компенсации мы отправляем вам эту награду. Спасибо за понимание и поддержку. | M32: Sevgili Kaptan, \nEn son oyun güncellemesinde haritada değişiklikler yaptık. Bu işgal edilen belirli harita birimlerini veya Çete binalarını kaybetmene veya Şehrinin taşınmasına neden olabilir. \nTelafi olarak senin için bir ödül ekledik. Anlayışın ve desteğin için teşekkürler. | N32: Thưa Thủ Lĩnh, \nChúng tôi đã thực hiện một số thay đổi về bản đồ trong bản cập nhật trò chơi gần đây nhất. Việc này có thể khiến bạn bị mất các đơn vị bản đồ hoặc các công trình Bang Hội đã chiếm đóng, hoặc Thành Phố của bạn bị di chuyển. \nChúng tôi đã đính kèm một phần thưởng để bù đắp cho bạn. Cảm ơn bạn đã thông cảm và ủng hộ chúng tôi.
A33: 账号封禁 | B33: 不正当游戏封号 | C33: 恶意使用Bug的玩家已被处理 | D33: Player Using Exploits Penalized | E33: Rappel à l'ordre d'un joueur exploitant des failles | F33: Bestrafung des Spielers, der Exploits ausgenutzt hat | G33: Penalização para jogadores abusando de bugs | H33: 惡意使用Bug的玩家已被處理 | I33: Pemain yang Menggunakan Eksploitasi Bug Dihukum | J33: การลงโทษผู้เล่นที่ใช้ประโยชน์จากช่องโหว่ | K33: Penalización a jugador aprovechándose del juego | L33: Наказан игрок, использовавший эксплойты | M33: İstismar Eden Oyuncu Cezalandırıldı | N33: Phạt người chơi có hành vi bóc lột
C34: 亲爱的指挥官：\n\n我们收到部分玩家反馈，有一名玩家<color=#ffa200>恶意利用游戏规则刷取资源</color>，导致游戏数据异常，我们已经对有异常操作的玩家<color=#ffa200>采取了措施</color>。\n很抱歉该bug影响到了您的体验，在此为您送上一份补偿，请注意查收。\n\n再次感谢玩家们对Age of Apes的支持和热爱。欢迎您报告任何注意到的错误和异常行为，这有助于我们为所有人提供更好的游戏体验。\n\n罗杰副官 | D34: Dear Captain,\n\nWe received feedback regarding a player who <color=#ffa200>exploited in-game bugs to illegally obtain resources</color>, causing data abnormalities in the game. Please rest assured we have already <color=#ffa200>taken measures</color> against the player.\n\nWe apologize for any negative experience you may have had as a result. Here's a special gift to make it up to you.\n\nThanks again for your support. If you notice any errors or abnormal behavior, please don't hesitate to report them. Your feedback helps us to provide a better gaming experience for all players.\n\nDeputy Roger | E34: Cher capitaine,\n\nIl a été porté à notre connaissance qu'un joueur <color=#ffa200>exploitait des failles dans le jeu pour obtenir illégalement des ressources</color>, ce qui a causé des incohérences dans les données. Ne vous inquiétez pas, nous avons d'ores et déjà <color=#ffa200>pris des mesures</color> à l'encontre de ce joueur.\n\nNous vous prions de nous excuser pour les désagréments que vous avez pu subir. Voici un cadeau spécial pour nous faire pardonner.\n\nMerci encore pour votre soutien. Si vous constatez des erreurs ou des comportements anormaux, n'hésitez pas à nous en faire part. Vos commentaires nous aident à proposer une expérience optimale pour tous les joueurs.\n\nRoger l'assistant | F34: Lieber Captain,\n\nWir sind auf einen Spieler aufmerksam gemacht worden, der <color=#ffa200>Programmfehler im Spiel ausgenutzt hat, um illegal Ressourcen zu erhalten</color> und dadurch Datenanomalien im Spiel verursacht hat. Bitte sei versichert, dass wir bereits <color=#ffa200>Maßnahmen</color> gegen diesen Spieler ergriffen haben.\n\nWir entschuldigen uns für jegliche negative Erfahrung, die du dadurch gemacht hast. Hier ist ein besonderes Geschenk zur Wiedergutmachung für dich.\n\nNochmals vielen Dank für deine Unterstützung. Wenn du irgendwelche Fehler oder irreguläres Verhalten bemerkst, zögere bitte nicht, es zu melden. Dein Feedback hilft uns, ein besseres Spielerlebnis für alle Spieler zu gewährleisten.\n\nAdjudant Roger | G34: Caro Capitão,\n\nRecebemos feedback a respeito de um jogador que <color=#ffa200>abusou de bugs para obter recursos ilegalmente</color>, o que causou problemas nos dados do jogo. Saiba que já tomamos todas as <color=#ffa200>medidas cabíveis</color> a respeito deste jogador.\n\nLamentamos por qualquer inconveniente que isso possa ter causado a você. Você receberá um pequeno presente de compensação.\n\nNossa equipe agradece seu suporte. Caso note quaisquer erros ou comportamentos suspeitos, não deixe de falar conosco. Seu feedback nos ajuda a melhorar a experiência de jogo para todos os jogadores.\n\nDelegado Roger | H34: 親愛的指揮官：\n\n我們收到部分玩家反饋，有一名玩家<color=#ffa200>惡意利用遊戲規則刷取資源</color>，導致遊戲數據異常，我們已經對有異常操作的玩家<color=#ffa200>採取了措施</color>。\n很抱歉該bug影響到了您的體驗，在此為您送上一份補償，請注意查收。\n\n再次感謝玩家們對Age of Apes的支持和熱愛。歡迎您報告任何注意到的錯誤和異常行為，這有助於我們為所有人提供更好的遊戲體驗。\n\n羅傑副官 | I34: Kapten yang terhormat,\n\nKami menerima umpan balik terkait pemain yang <color=#ffa200>mengeksploitasi bug dalam game untuk mendapatkan sumber daya secara ilegal</color>, sehingga mengakibatkan ketidaknormalan data di dalam game. Yakinlah bahwa kami telah <color=#ffa200>mengambil tindakan</color> terhadap pemain tersebut.\n\nKami mohon maaf atas pengalaman negatif yang mungkin kamu alami. Ini hadiah spesial untuk menebusnya buatmu.\n\nTerima kasih sekali lagi atas dukunganmu. Jika kamu melihat adanya kesalahan atau perilaku tidak normal, jangan ragu untuk melaporkannya. Umpan balikmu membantu kami memberikan pengalaman bermain game yang lebih baik untuk semua pemain.\n\nDeputi Roger | J34: ถึงท่านผู้บัญชาการ\n\nเราได้รับข้อเสนอแนะเกี่ยวกับผู้เล่นที่<color=#ffa200>ใช้ประโยชน์จากข้อบกพร่องในเกมเพื่อรับทรัพยากรอย่างผิดกฎหมาย</color> ซึ่งทำให้ข้อมูลในเกมเกิดความผิดปกติ ขอนายโปรดมั่นใจว่าเราได้<color=#ffa200>ดำเนินมาตรการ</color>กับผู้เล่นที่มีพฤติกรรมดังกล่าวแล้ว\n\nเราขออภัยสำหรับประสบการณ์เชิงลบใด ๆ ที่นายอาจได้รับ เอาเป็นว่าเราขอมอบของขวัญสุดพิเศษชิ้นนี้ให้นายนะ\n\nขอขอบคุณอีกครั้งสำหรับการสนับสนุน หากนายสังเกตเห็นข้อผิดพลาดหรือพฤติกรรมที่ผิดปกติ โปรดอย่าลังเลที่จะรายงานเรา ความคิดเห็นของนายจะช่วยให้เราสามารถมอบประสบการณ์การเล่นเกมที่ดีขึ้นให้กับผู้เล่นทุกคนได้\n\nท่านรองโรเจอร์ | K34: Querido Capitán, \n\nHemos recibido comentarios con relación a un jugador que <color=#ffa200>aprovechándose de algunos problemas dentro del juego obtuvo recursos ilegalmente</color>, provocando anormalidades de datos en el juego. Por favor, ten la seguridad de que ya hemos <color=#ffa200>tomado medidas</color> contra el jugador.\n\nNos disculpamos por la experiencia negativa que hayas podido tener como resultado. Te presentamos un regalo especial para compensarte.\n\nMuchas gracias nuevamente por tu apoyo. Si te das cuenta de cualquier error o comportamiento anormal, por favor, no dudes en reportarlo. Tus comentarios nos ayudan a proporcionar una mejor experiencia de juego para todos los jugadores.\n\n\nComisario Roger | L34: Уважаемый капитан!\n\nМы получили сведения об игроке, который <color=#ffa200>использовал игровые ошибки, чтобы недопустимым образом получить ресурсы</color>. Это вызвало аномалию игровых данных. Сообщаем, что мы уже <color=#ffa200>приняли меры</color> против этого игрока. \n\nПриносим извинения за не самые лучшие впечатления, которые вы в результате могли получить. Вот вам особый подарок в качестве компенсации. \n\nЕще раз благодарим за поддержку. Если вы заметите какие-либо ошибки или аномальное поведение, пожалуйста, сразу сообщайте о них. Ваши отзывы помогают нам сделать игру лучше для всех игроков.\n\nПомощник Роджер | M34: Sevgili Kaptan,\n\n<color=#ffa200>Yasa dışı şekilde kaynak elde etmek için oyun içi hataları istismar eden</color> ve oyunda veri anormalliklerine yol açan bir oyuncuya dair geri bildirim aldık. Lütfen oyuncuya yönelik <color=#ffa200>önlemleri aldığımızdan</color> emin ol.\n\nBunun sonucunda yaşadığın her tür olumsuz deneyim için özür dileriz. Bu durumu telafi etme amaçlı özel bir hediyemiz var.\n\nDesteğin için bir kez daha teşekkürler. Herhangi bir hata veya anormal davranış görürsen, lütfen bunları raporlamaktan çekinme. Geri bildirimin tüm oyunculara daha iyi bir oyun deneyimi sunmamız konusunda bize yardımcı oluyor.\n\nYardımcı Roger | N34: Thưa Thủ Lĩnh,\n\nChúng tôi đã nhận được phản hồi về một người chơi <color=#ffa200>khai thác lỗi trong trò chơi để lấy tài nguyên bất hợp pháp</color>, gây ra các bất thường dữ liệu trong trò chơi. Hãy yên tâm, chúng tôi đã <color=#ffa200>tiến hành các biện pháp</color> để xử lý người chơi này.\n\nChúng tôi chân thành xin lỗi vì bất kỳ trải nghiệm tiêu cực nào mà bạn có thể đã gặp phải. Đây là một món quà đặc biệt dành cho bạn.\n\nMột lần nữa xin được cảm ơn bạn đã hỗ trợ. Nếu bạn nhận thấy bất kỳ lỗi hoặc hành vi bất thường nào, vui lòng báo cáo cho chúng tôi. Phản hồi của bạn giúp chúng tôi mang đến trải nghiệm trò chơi tốt hơn cho tất cả người chơi.\n\nPhụ tá Roger
B35: 非法获得宝石道具封号 | C35: 恶意使用Bug的玩家已被处理 | D35: Player Using Exploits Penalized | E35: Rappel à l'ordre d'un joueur exploitant des failles | F35: Bestrafung des Spielers, der Exploits ausgenutzt hat | G35: Penalização para jogadores abusando de bugs | H35: 惡意使用Bug的玩家已被處理 | I35: Pemain yang Menggunakan Eksploitasi Bug Dihukum | J35: การลงโทษผู้เล่นที่ใช้ประโยชน์จากช่องโหว่ | K35: Penalización a jugador aprovechándose del juego | L35: Наказан игрок, использовавший эксплойты | M35: İstismar Eden Oyuncu Cezalandırıldı | N35: Phạt người chơi có hành vi bóc lột
C36: 亲爱的指挥官：\n\n我们收到部分玩家反馈，有一名玩家<color=#ffa200>恶意利用游戏规则增加战力</color>，导致游戏数据异常，我们已经对有异常操作的玩家<color=#ffa200>采取了措施</color>。\n很抱歉该bug影响到了您的体验，在此为您送上一份补偿，请注意查收。\n\n再次感谢玩家们对Age of Apes的支持和热爱。欢迎您报告任何注意到的错误和异常行为，这有助于我们为所有人提供更好的游戏体验。\n\n罗杰副官 | D36: Dear Captain,\n\nWe received feedback regarding a player who <color=#ffa200>exploited in-game bugs to illegally increase power</color>, causing data abnormalities in the game. Please rest assured we have already <color=#ffa200>taken measures</color> against the player.\n\nWe apologize for any negative experience you may have had as a result. Here's a special gift to make it up to you.\n\nThanks again for your support. If you notice any errors or abnormal behavior, please don't hesitate to report them. Your feedback helps us to provide a better gaming experience for all players.\n\nDeputy Roger | E36: Cher capitaine,\n\nIl a été porté à notre connaissance qu'un joueur <color=#ffa200>exploitait des failles dans le jeu pour augmenter illégalement sa puissance</color>, ce qui a causé des incohérences dans les données. Ne vous inquiétez pas, nous avons d'ores et déjà <color=#ffa200>pris des mesures</color> à l'encontre de ce joueur.\n\nNous vous prions de nous excuser pour les désagréments que vous avez pu subir. Voici un cadeau spécial pour nous faire pardonner.\n\nMerci encore pour votre soutien. Si vous constatez des erreurs ou des comportements anormaux, n'hésitez pas à nous en faire part. C'est grâce à vos commentaires que nous pouvons proposer une expérience de jeu optimale pour tous les joueurs.\n\nRoger l'assistant | F36: Lieber Captain,\n\nWir sind auf einen Spieler aufmerksam gemacht worden, der <color=#ffa200>Programmfehler im Spiel ausgenutzt hat, um illegal seine Stärke zu erhöhen</color> und dadurch Datenanomalien im Spiel verursacht hat. Bitte sei versichert, dass wir bereits <color=#ffa200>Maßnahmen</color> gegen diesen Spieler ergriffen haben.\n\nWir entschuldigen uns für jegliche negative Erfahrung, die du dadurch gemacht hast. Hier ist ein besonderes Geschenk zur Wiedergutmachung für dich.\n\nNochmals vielen Dank für deine Unterstützung. Wenn du irgendwelche Fehler oder irreguläres Verhalten bemerkst, zögere bitte nicht, es zu melden. Dein Feedback hilft uns, ein besseres Spielerlebnis für alle Spieler zu gewährleisten.\n\nAdjudant Roger | G36: Caro Capitão,\n\nRecebemos feedback a respeito de um jogador que <color=#ffa200>abusou de bugs para aumentar o poder dele ilegalmente</color>, o que causou problemas nos dados do jogo. Saiba que já tomamos todas as <color=#ffa200>medidas cabíveis</color> a respeito deste jogador.\n\nLamentamos por qualquer inconveniente que isso possa ter causado a você. Você receberá um pequeno presente de compensação.\n\nNossa equipe agradece seu suporte. Caso note quaisquer erros ou comportamentos suspeitos, não deixe de falar conosco. Seu feedback nos ajuda a melhorar a experiência de jogo para todos os jogadores.\n\nDelegado Roger | H36: 親愛的指揮官：\n\n我們收到部分玩家反饋，有一名玩家<color=#ffa200>惡意利用遊戲規則增加戰力</color>，導致遊戲數據異常，我們已經對有異常操作的玩家<color=#ffa200>採取了措施</color>。\n很抱歉該bug影響到了您的體驗，在此為您送上一份補償，請注意查收。\n\n再次感謝玩家們對Age of Apes的支持和熱愛。歡迎您報告任何注意到的錯誤和異常行為，這有助於我們為所有人提供更好的遊戲體驗。\n\n羅傑副官 | I36: Kapten yang terhormat,\n\nKami menerima umpan balik terkait pemain yang <color=#ffa200>mengeksploitasi bug dalam game untuk meningkatkan kekuatan secara ilegal</color>, sehingga mengakibatkan ketidaknormalan data di dalam game. Yakinlah bahwa kami telah <color=#ffa200>mengambil tindakan</color> terhadap pemain tersebut.\n\nKami mohon maaf atas pengalaman negatif yang mungkin kamu alami. Ini hadiah spesial untuk menebusnya buatmu.\n\nTerima kasih sekali lagi atas dukunganmu. Jika kamu melihat adanya kesalahan atau perilaku tidak normal, jangan ragu untuk melaporkannya. Umpan balikmu membantu kami memberikan pengalaman bermain game yang lebih baik untuk semua pemain.\n\nDeputi Roger | J36: ถึงท่านผู้บัญชาการ\n\nเราได้รับข้อเสนอแนะเกี่ยวกับผู้เล่นที่<color=#ffa200>ใช้ประโยชน์จากข้อบกพร่องในเกมเพื่อเพิ่มพลังอย่างผิดกฎหมาย</color> ซึ่งทำให้ข้อมูลในเกมเกิดความผิดปกติ ขอนายโปรดมั่นใจว่าเราได้<color=#ffa200>ดำเนินมาตรการ</color>กับผู้เล่นที่มีพฤติกรรมดังกล่าวแล้ว\n\nเราขออภัยสำหรับประสบการณ์เชิงลบใด ๆ ที่นายอาจได้รับ เอาเป็นว่าเราขอมอบของขวัญสุดพิเศษชิ้นนี้ให้นายนะ\n\nขอขอบคุณอีกครั้งสำหรับการสนับสนุน หากนายสังเกตเห็นข้อผิดพลาดหรือพฤติกรรมที่ผิดปกติ โปรดอย่าลังเลที่จะรายงานเรา ความคิดเห็นของนายจะช่วยให้เราสามารถมอบประสบการณ์การเล่นเกมที่ดีขึ้นให้กับผู้เล่นทุกคนได้\n\nท่านรองโรเจอร์ | K36: Querido Capitán, \n\nHemos recibido comentarios con relación a un jugador que <color=#ffa200>aprovechándose de algunos problemas dentro del juego incrementó su poder</color>, provocando anormalidades de datos en el juego. Por favor, ten la seguridad de que ya hemos <color=#ffa200>tomado medidas</color> contra el jugador.\n\nNos disculpamos por la experiencia negativa que hayas podido tener como resultado. Te presentamos un regalo especial para compensarte.\n\nMuchas gracias nuevamente por tu apoyo. Si te das cuenta de cualquier error o comportamiento anormal, por favor, no dudes en reportarlo. Tus comentarios nos ayudan a proporcionar una mejor experiencia de juego para todos los jugadores.\n\n\nComisario Roger | L36: Уважаемый капитан!\n\nМы получили сведения об игроке, который <color=#ffa200>использовал игровые ошибки, чтобы недопустимым образом увеличить свою силу</color>. Это вызвало аномалию игровых данных. Сообщаем, что мы уже <color=#ffa200>приняли меры</color> против этого игрока. \n\nПриносим извинения за не самые лучшие впечатления, которые вы в результате могли получить. Вот вам особый подарок в качестве компенсации. \n\nЕще раз благодарим за поддержку. Если вы заметите какие-либо ошибки или аномальное поведение, пожалуйста, сразу сообщайте о них. Ваши отзывы помогают нам сделать игру лучше для всех игроков.\n\nПомощник Роджер | M36: Sevgili Kaptan,\n\n<color=#ffa200>Yasa dışı şekilde gücünü artırmak için oyun içi hataları istismar eden</color> ve oyunda veri anormalliklerine yol açan bir oyuncuya dair geri bildirim aldık. Lütfen oyuncuya yönelik <color=#ffa200>önlemleri aldığımızdan</color> emin ol.\n\nBunun sonucunda yaşadığın her tür olumsuz deneyim için özür dileriz. Bu durumu telafi etme amaçlı özel bir hediyemiz var.\n\nDesteğin için bir kez daha teşekkürler. Herhangi bir hata veya anormal davranış görürsen, lütfen bunları raporlamaktan çekinme. Geri bildirimin tüm oyunculara daha iyi bir oyun deneyimi sunmamız konusunda bize yardımcı oluyor.\n\nYardımcı Roger | N36: Thưa Thủ Lĩnh,\n\nChúng tôi đã nhận được phản hồi về một người chơi <color=#ffa200>khai thác lỗi trong trò chơi để tăng sức mạnh bất hợp pháp</color>, gây ra các bất thường dữ liệu trong trò chơi. Hãy yên tâm, chúng tôi đã <color=#ffa200>tiến hành các biện pháp</color> để xử lý người chơi này.\n\nChúng tôi chân thành xin lỗi vì bất kỳ trải nghiệm tiêu cực nào mà bạn có thể đã gặp phải. Đây là một món quà đặc biệt dành cho bạn.\n\nMột lần nữa xin được cảm ơn bạn đã hỗ trợ. Nếu bạn nhận thấy bất kỳ lỗi hoặc hành vi bất thường nào, vui lòng báo cáo cho chúng tôi. Phản hồi của bạn giúp chúng tôi mang đến trải nghiệm trò chơi tốt hơn cho tất cả người chơi.\n\nPhụ tá Roger
B37: 举报类BUG（利用游戏漏洞获利）奖励 | C37: 举报奖励 | D37: Report Reward | E37: Récompense de signalement | F37: Melde-Belohnung | G37: Recompensa de relatório | H37: 舉報獎勵 | I37: Hadiah Laporan | J37: รางวัลสำหรับการรายงาน | K37: Reporte de la Recompensa | L37: Награда за сообщение | M37: Rapor Ödülü | N37: Phần thưởng Báo cáo
C38: 亲爱的指挥官：\n\n感谢您帮助我们保护Age of Apes的公平环境。我们已对有异常操作的玩家采取措施。\n\n再次感谢您对Age of Apes的支持和热爱。欢迎您报告注意到的错误和异常行为，这有助于我们为所有人提供更好的游戏体验。\n\n罗杰副官 | D38: Dear Captain,\n\nThank you for helping to protect the fair gaming environment of Age of Apes! We have taken measures against the player you reported for abnormal operations.\n\nThanks again for your support. If you notice any errors or abnormal behavior, please don't hesitate to report them. Your feedback helps us to provide a better gaming experience for all players.\n\nDeputy Roger | E38: Cher capitaine,\n\nMerci de nous aider à préserver un environnement de jeu équitable pour Age of Apes! Nous avons pris des mesures à l'encontre du joueur que vous avez signalé pour opérations anormales.\n\nMerci encore pour votre soutien. Si vous constatez des erreurs ou des comportements anormaux, n'hésitez pas à nous en faire part. C'est grâce à vos commentaires que nous pouvons proposer une expérience de jeu optimale pour tous les joueurs.\n\nRoger l'assistant | F38: Lieber Captain,\n\nVielen Dank, dass du dabei hilfst, die faire Spielumgebung von Age of Apes zu bewahren! Wir haben Maßnahmen gegen den Spieler ergriffen, den du wegen irregulärer Handlungen gemeldet hast.\n\nVielen Dank nochmals für deine Unterstützung. Wenn du irgendwelche Fehler oder regelwidriges Verhalten bemerkst, zögere bitte nicht, dies zu melden. Dein Feedback hilft uns dabei, ein besseres Spielerlebnis für alle Spieler zu gewährleisten.\n\nAdjudant Roger | G38: Caro Capitão,\n\nAgradecemos sua ajuda em manter o ambiente de jogo justo em Ages of Apes! Tomamos as medidas cabíveis a respeito do jogador que você reportou por comportamento suspeito.\n\nNossa equipe agradece seu suporte. Caso note quaisquer erros ou comportamentos suspeitos, não deixe de falar conosco. Seu feedback nos ajuda a melhorar a experiência de jogo para todos os jogadores.\n\nDelegado Roger | H38: 親愛的指揮官：\n\n感謝您幫助我們保護Age of Apes的公平環境。我們已對有異常操作的玩家採取措施。\n\n再次感謝您對Age of Apes的支持和熱愛。歡迎您報告注意到的錯誤和異常行為，這有助於我們為所有人提供更好的遊戲體驗。\n\n羅傑副官 | I38: Kapten yang terhormat,\n\nTerima kasih telah membantu melindungi lingkungan permainan yang adil di Age of Apes! Kami telah mengambil tindakan terhadap pemain yang kamu laporkan untuk operasi abnormal.\n\nTerima kasih sekali lagi atas dukunganmu. Jika kamu melihat adanya kesalahan atau perilaku tidak normal, jangan ragu untuk melaporkannya. Umpan balikmu membantu kami memberikan pengalaman bermain game yang lebih baik untuk semua pemain.\n\nDeputi Roger | J38: ถึงท่านผู้บัญชาการ\n\nขอขอบคุณที่ช่วยปกป้องสภาพแวดล้อมการเล่นเกม Age of Apes ให้มีความยุติธรรม! เราได้ดำเนินมาตรการกับผู้เล่นที่นายรายงานว่ามีการใช้วิธีการที่ผิดปกติ\n\nขอขอบคุณอีกครั้งสำหรับการสนับสนุน หากนายสังเกตเห็นข้อผิดพลาดหรือพฤติกรรมที่ผิดปกติ โปรดอย่าลังเลที่จะรายงานเรา ความคิดเห็นของนายจะช่วยให้เราสามารถมอบประสบการณ์การเล่นเกมที่ดีขึ้นให้กับผู้เล่นทุกคนได้\n\nท่านรองโรเจอร์ | K38: Querido Capitán,\n\n¡Gracias por ayudarnos a proteger un entorno de juego justo para Age of Apes! Hemos tomado medidas contra el jugador que reportaste por operaciones anormales. \n\nMuchas gracias nuevamente por tu apoyo. Si te das cuenta de cualquier error o comportamiento anormal, por favor, no dudes en reportarlo. Tus comentarios nos ayudan a proporcionar una mejor experiencia de juego para todos los jugadores.\n\nComisario Roger | L38: Уважаемый капитан!\n\nСпасибо за то, что помогаете защитить честную игру в мире Age of Apes! Мы приняли меры против игрока, об аномальных действиях которого вы сообщили. \n\nЕще раз благодарим за поддержку. Если вы заметите какие-либо ошибки или аномальное поведение, пожалуйста, сразу сообщайте о них. Ваши отзывы помогают нам сделать игру лучше для всех игроков.\n\nПомощник Роджер | M38: Sevgili Kaptan,\n\nAge of Apes’in adil oyun ortamını korumamıza yardımcı olduğun için teşekkürler! Anormal eylemler konusunda raporladığın oyuncuya yönelik önlemler aldık.\n\nDesteğin için bir kez daha teşekkürler. Herhangi bir hata veya anormal davranış görürsen, lütfen bunları raporlamaktan çekinme. Geri bildirimin tüm oyunculara daha iyi bir oyun deneyimi sunmamız konusunda bize yardımcı oluyor.\n\nYardımcı Roger | N38: Thưa Thủ Lĩnh,\n\nCảm ơn bạn vì đã giúp bảo vệ môi trường chơi game công bằng ở Age of Apes! Chúng tôi đã thực hiện các biện pháp đối phó với người chơi được bạn báo cáo vì các thao tác bất thường.\n\nMột lần nữa xin được cảm ơn bạn đã hỗ trợ. Nếu bạn nhận thấy bất kỳ lỗi hoặc hành vi bất thường nào, vui lòng báo cáo cho chúng tôi. Phản hồi của bạn giúp chúng tôi mang đến trải nghiệm trò chơi tốt hơn cho tất cả người chơi.\n\nPhụ tá Roger
B39: 体验类BUG（影响玩家体验）奖励 | C39: BUG汇报奖励 | D39: Bug Report Reward | E39: Récompense de signalement d'un bug | F39: Belohnung für Fehlerberichte | G39: Recompensa ao reportar bugs | H39: BUG匯報獎勵 | I39: Hadiah Laporan Bug | J39: รางวัลสำหรับการรายงานข้อบกพร่อง | K39: Recompensa por reporte de fallos | L39: Награда за сообщение об ошибке | M39: Hata Raporu Ödülleri | N39: Phần thưởng Báo cáo Lỗi
C40: 亲爱的指挥官：\n\n感谢您发现游戏内的异常问题并反馈给我们，帮助Age of Apes为所有猴子们提供更好的游戏体验！\n\n我们将继续完善游戏，希望您越来越喜欢它！再次感谢您对Age of Apes的支持和热爱！\n\n罗杰副官 | D40: Dear Captain,\n\nThank you for finding and reporting game abnormalities and helping us to provide a better gaming experience for all players.\n\nWe will work hard to keep improving the game. Thanks again for your support and love for Age of Apes!\n\nMay the bananas be with you and see you around the Tavern!\n\nDeputy Roger | E40: Cher capitaine,\n\nMerci d'avoir repéré et signalé une faille dans le jeu! C'est grâce à vos signalements que nous pouvons offrir une expérience optimale à tous les joueurs.\n\nNous poursuivons nos efforts pour continuer d'améliorer le jeu. Merci pour votre soutien et votre amour pour Age of Apes!\n\nQue les bananes soient avec vous! On se retrouve à la taverne!\n\nRoger l'assistant | F40: Lieber Captain,\n\nVielen Dank, dass du Anomalien im Spiel gefunden und gemeldet hast und uns hilfst, allen Spielern ein besseres Spielerlebnis zu bieten.\n\nWir werden hart daran arbeiten, das Spiel weiter zu verbessern. Nochmals vielen Dank für deine Unterstützung und deine Begeisterung für Age of Apes!\n\nMögen die Bananen mit dir sein und wir sehen uns in der Taverne!\n\nAdjudant Roger | G40: Caro Capitão,\n\nAgradecemos sua ajuda ao encontrar e reportar anormalidades no jogo e por nos ajudar a fornecer uma melhor experiência de jogo para todos.\n\nEstamos trabalhando para melhorar o jogo. Agradecemos novamente pelo seu apoio e carinho por Ages of Apes!\n\nQue as bananas estejam com você! Nos vemos na taverna!\n\nDelegado Roger | H40: 親愛的指揮官：\n\n感謝您發現遊戲內的異常問題並反饋給我們，幫助Age of Apes為所有猴子們提供更好的遊戲體驗！\n\n我們將繼續完善遊戲，希望您越來越喜歡它！再次感謝您對Age of Apes的支持和熱愛！\n\n羅傑副官 | I40: Kapten yang terhormat,\n\nTerima kasih telah menemukan dan melaporkan kelainan game dan membantu kami memberikan pengalaman bermain game yang lebih baik untuk semua pemain.\n\nKami akan bekerja keras untuk terus meningkatkan game. Sekali lagi terima kasih atas dukungan dan cintanya untuk Age of Apes!\n\nSemoga pisang menyertaimu dan sampai jumpa di sekitar Kedai!\n\nDeputi Roger | J40: ถึงท่านผู้บัญชาการ\n\nขอขอบคุณที่ช่วยค้นหาและรายงานความผิดปกติของเกม ซึ่งจะช่วยให้เราสามารถมอบประสบการณ์การเล่นเกมที่ดียิ่งขึ้นให้กับผู้เล่นทุกคนได้\n\nเราจะทำงานอย่างหนักเพื่อปรับปรุงเกมต่อไป ขอขอบคุณอีกครั้งสำหรับการสนับสนุนและความรักที่มีให้กับ Age of Apes!\n\nขอให้กล้วยจงสถิตย์อยู่กับนาย แล้วไว้เจอกันแถว ๆ โรงแรมนะ!\n\nท่านรองโรเจอร์ | K40: Querido Capitán, \n\nGracias por encontrar y reportar anomalidades dentro del juego y ayudarnos a proporcionar una mejor experiencia para todos los jugadores. \n\nTrabajaremos duro para mantenernos mejorando el juego. ¡Gracias nuevamente por tu apoyo y amor por Age of Apes! \n\n¡Que las bananas sean contigo y nos vemos en la Taberna!\n\nComisario Roger | L40: Уважаемый капитан!\n\nСпасибо, что сообщили о выявленной некорректной работе игры и помогли нам предоставить игрокам более хорошие впечатления.\n\nМы продолжим усердную работу над улучшением игры. Еще раз спасибо за поддержку и любовь к Age of Apes!\n\nДа пребудут с вами бананы — и увидимся в таверне!\n\nПомощник Роджер | M40: Sevgili Kaptan,\n\nOyundaki anormallikleri bulup raporlayarak tüm oyunculara daha iyi bir oyun deneyimi sunmamıza yardımcı olduğun için teşekkürler.\n\nOyunu geliştirmek için çok çalışmaya devam edeceğiz. Age of Apes’e desteğin ve gösterdiğin sevgi için bir kez daha teşekkürler!\n\nMuzlar seninle olsun, Tavernada görüşmek üzere!\n\nYardımcı Roger | N40: Thưa Thủ Lĩnh,\n\nCảm ơn bạn đã phát hiện và báo cáo sự bất thường trong trò chơi, giúp chúng tôi mang đến trải nghiệm trò chơi tốt hơn cho tất cả những người chơi khác.\n\nChúng tôi sẽ nỗ lực chăm chỉ để tiếp tục cải thiện trò chơi. Một lần nữa, xin cảm ơn sự ủng hộ và tình yêu mà bạn đã dành cho Age of Apes!\n\nChúc kho của bạn luôn đầy chuối và hẹn gặp bạn ở Tửu Quán!\n\nPhụ tá Roger
B41: 全服表扬 | C41: 感谢xx反馈BUG | D41: Thank You to xx for Bug Report | E41: Merci à xx pour son signalement d'un bug | F41: Vielen Dank an xx für den Hinweis auf Programmfehler | G41: Agradecimento a xx por reportar bugs | H41: 感謝xx反饋BUG | I41: Terima Kasih kepada xx untuk Laporan Bug | J41: ขอขอบคุณxx สำหรับการรายงานข้อผิดพลาด | K41: Gracias a xx por su Reporte de Fallos | L41: Спасибо игроку xx за сообщение об ошибке | M41: xx, Hata Raporu İçin Teşekkürler | N41: Lời cảm ơn gửi đến xx vì đã Báo cáo Lỗi
C42: 亲爱的指挥官：\n\n感谢<color=#ffa200>xxx玩家</color>发现游戏内的异常问题并反馈给我们！这将有助于我们为所有人提供更好的游戏体验。\n\n我们鼓励所有猴子都能参与其中，发现游戏内的错误和部分玩家利用漏洞获利的异常行为，请及时通过Discord社区、游戏内的客服服务渠道告诉我们，一经BUG被核实，我们将对及时上报的玩家发放奖励！\n\n罗杰副官 | D42: Dear Captain,\n\nWe want to give a big thanks to <color=#ffa200>player xxx</color> for finding and informing us of abnormalities in the game! This feedback will help us to provide a better gaming experience for all players.\n\nIf you notice any errors or abnormal behavior (such as players using exploits), please don't hesitate to report them. Please get in touch through our official Discord community or our customer support channels. Once the errors are verified, we will send rewards to the reporting players as a token of our appreciation.\n\nDeputy Roger | E42: Cher capitaine,\n\nNous tenions à remercier chaleureusement <color=#ffa200>le joueur xxx</color> d'avoir repéré des failles dans le jeu et de les avoir signalées à nos équipes. Ce signalement va nous aider à offrir une expérience optimale à tous les joueurs. \n\nSi vous faites face à une erreur ou un comportement anormal (comme des joueurs profitant de failles), n'hésitez pas à nous en faire part via notre serveur Discord ou le service client. Après vérification des erreurs, une récompense est envoyée en remerciement aux joueurs ayant effectué des signalements. \n\nRoger l'assistant | F42: Lieber Captain,\n\nWir möchten dem <color=#ffa200>Spieler xxx</color> ein großes Dankeschön dafür aussprechen, dass er Auffälligkeiten im Spiel gefunden und uns darüber informiert hat! Dieses Feedback wird uns dabei helfen, ein besseres Spielerlebnis für alle Spieler zu gewährleisten.\n\nWenn du Hinweise auf Fehler oder irreguläres Verhalten (z.B. Spieler, die Exploits nutzen) bemerkst, zögere bitte nicht, diese zu melden. Bitte melde dich über unseren offiziellen Discord-Kanal oder unseren Kundensupport-Kanal. Sobald die Fehler verifiziert sind, werden wir den meldenden Spielern als Zeichen unserer Wertschätzung Belohnungen zusenden.\n\nAdjudant Roger | G42: Caro Capitão,\n\nQueremos agradecer ao <color=#ffa200>jogador xxx</color> por encontrar e nos avisar sobre anormalidades dentro do jogo! Este feedback nos ajuda a melhorar a experiência de jogo para todo mundo.\n\nSe notar quaisquer erros ou comportamentos suspeitos (por exemplo, jogadores abusando de bugs), não deixe de falar conosco sobre isso. Entre em contato pelo nosso canal oficial no Discord ou suporte ao cliente. Assim que os erros forem verificados, enviaremos recompensas para os jogadores como agradecimento pela ajuda.\n\nDelegado Roger | H42: 親愛的指揮官：\n\n感謝<color=#ffa200>xxx玩家</color>發現遊戲內的異常問題並反饋給我們！這將有助於我們為所有人提供更好的遊戲體驗。\n\n我們鼓勵所有猴子都能參與其中，發現遊戲內的錯誤和部分玩家利用漏洞獲利的異常行為，請及時通過Discord社區、遊戲內的客服服務渠道告訴我們，一經BUG被核實，我們將對及時上報的玩家發放獎勵！\n\n羅傑副官 | I42: Kapten yang terhormat,\n\nKami ingin berterima kasih banyak kepada <color=#ffa200>pemain xxx</color> karena menemukan dan memberi tahu kami tentang ketidaknormalan dalam game! Umpan balik ini akan membantu kami memberikan pengalaman bermain game yang lebih baik untuk semua pemain.\n\nJika kamu melihat kesalahan atau perilaku tidak normal (seperti pemain menggunakan eksploitasi), jangan ragu untuk melaporkannya. Hubungi komunitas Discord resmi kami atau saluran dukungan pelanggan kami. Setelah kesalahan diverifikasi, kami akan mengirimkan hadiah kepada pemain pelapor sebagai tanda penghargaan kami.\n\nDeputi Roger | J42: ถึงท่านผู้บัญชาการ\n\nเราอยากขอบคุณ<color=#ffa200>ผู้เล่นนาม xxx</color> สำหรับการค้นหาและแจ้งให้เราทราบถึงความผิดปกติในเกม! ความคิดเห็นนี้จะช่วยให้เราสามารถมอบประสบการณ์การเล่นเกมที่ดียิ่งขึ้นให้กับผู้เล่นทุกคนได้\n\nหากนายสังเกตเห็นข้อผิดพลาดหรือพฤติกรรมที่ผิดปกติ (เช่น ผู้เล่นที่ใช้ช่องโหว่เพื่อเอาเปรียบ) โปรดอย่าลังเลที่จะรายงานเรา โปรดติดต่อผ่านชุมชน Discord อย่างเป็นทางการหรือช่องทางการสนับสนุนลูกค้าของเรา เมื่อตรวจสอบข้อผิดพลาดแล้ว เราจะส่งรางวัลให้กับผู้เล่นที่รายงานปัญหาต่าง ๆ เพื่อใช้แทนคำขอบคุณจากเรา\n\nท่านรองโรเจอร์ | K42: Querido Capitán,\n\n¡Queremos dar un enorme agradecimiento al <color=#ffa200>jugador xxx</color> por encontrar e informarnos de anormalidades dentro del juego! Estos comentarios nos ayudan a proporcionar una mejor experiencia de juego para todos los jugadores. \n\nSi te das cuenta de cualquier error o de algún comportamiento anormal (como por ejemplo jugadores aprovechándose de errores en el juego) por favor no dudes en reportarlo. Por favor, ponte en contacto con nuestro oficial en la comunidad de Discord o mediante nuestros canales se soporte al cliente. Una vez que los errores sean verificados, enviaremos recompensas a los jugadores que realizaron los reportes como una muestra de nuestro aprecio.\n\nComisario Roger | L42: Уважаемый капитан!\n\nМы хотим выразить огромную благодарность <color=#ffa200>игроку xxx</color> за то, что он сообщил нам о выявленных аномалиях в игре! Этот отзыв поможет нам сделать игру лучше для всех игроков.\n\nЕсли вы заметите какие-либо ошибки или аномальное поведение (например, игроков, использующих эксплойты), то, пожалуйста, не стесняйтесь сообщать о них. Пишите нам в Discord или в игровую службу поддержки. Если ошибка подтвердится, то в знак признательности мы отправим награду сообщившим о ней игрокам.\n\nПомощник Роджер | M42: Sevgili Kaptan,\n\n<color=#ffa200>xxx adlı oyuncuya</color> oyundaki anormallikleri bulduğu ve bize bildirdiği için çok teşekkürler! Bu geri bildirim tüm oyunculara daha iyi bir oyun deneyimi sunmamız konusunda bize yardım edecek.\n\nHerhangi bir hata veya anormal davranış (istismar yolları kullanan oyuncular gibi) görürsen, lütfen bunları raporlamaktan çekinme. Lütfen resmî Discord topluluğumuzdan veya müşteri destek kanallarımızdan bize ulaş. Hatalar doğrulandıktan sonra, teşekkür amacıyla raporlayan oyunculara ödüller göndereceğiz.\n\nYardımcı Roger | N42: Thưa Thủ Lĩnh,\n\nChúng tôi muốn gửi lời cảm ơn sâu sắc đến <color=#ffa200>người chơi xxx</color> vì đã phát hiện và thông báo những bất thường trong trò chơi cho chúng tôi! Phản hồi này sẽ giúp chúng tôi mang đến trải nghiệm trò chơi tốt hơn cho tất cả người chơi.\n\nNếu bạn nhận thấy bất kỳ lỗi hoặc hành vi bất thường nào (chẳng hạn như hành vi khai thác của người dùng), vui lòng báo cáo cho chúng tôi. Vui lòng liên hệ qua cộng đồng Discord chính thức hoặc các kênh hỗ trợ khách hàng của chúng tôi. Sau khi xác minh xong các lỗi, chúng tôi sẽ gửi phần thưởng cho những người chơi đã báo cáo để thể hiện lòng thành của mình.\n\nPhụ tá Roger
A43: 开服合服 | B43: 开新服 | C43: 新服开放通知 | D43: New Server Opened | E43: Ouverture d'un nouveau serveur | F43: Neuer Server ist geöffnet | G43: Novo servidor aberto | H43: 新服開放通知 | I43: Server Baru Dibuka | J43: เปิดเซิร์ฟเวอร์ใหม่แล้ว | K43: Apertura de nuevo servidor | L43: Открыт новый сервер | M43: Yeni Sunucu Açıldı | N43: Khai trương máy chủ mới
C44: 亲爱的指挥官：\n\n很高兴地告诉你，我们即将在<color=#ffa200>2021-04-01 00:00 UTC</color>开启新的服务器：<color=#ffa200>2000502-Omega</color>。\n我们期待您能加入对未知Omega的探索，赢得这场关于香蕉的竞赛！\n\n罗杰副官 | D44: Dear Captain,\n\nWe're excited to announce that the new server, <color=#ffa200>2000502-Omega</color> will officially open on <color=#ffa200>2021-04-01 00:00 UTC</color>.\n\nWe hope you'll come explore the mysterious Omega and win this race for the banana in the sky!\n\nDeputy Roger | E44: Cher capitaine,\n\nNous avons le plaisir de vous annoncer que l'ouverture officielle du nouveau serveur <color=#ffa200>2000502-Omega</color> aura lieu le <color=#ffa200>01-04-2021 à 00:00 TU</color>.\n\nNous avons hâte de vous voir explorer la mystérieuse Oméga et être le premier à accéder à la banane géante dans le ciel!\n\nRoger l'assistant | F44: Lieber Captain,\n\nWir freuen uns ankündigen zu können, dass der neue Server, <color=#ffa200>2000502-Omega</color> offiziell am <color=#ffa200>01.04.2021 00:00 UTC</color> geöffnet wird.\n\nWir hoffen, dass du Omega erkunden und das Rennen um die Banane im Himmel gewinnen wirst!\n\nAdjudant Roger | G44: Caro Capitão,\n\nEstamos animados em anunciar que o novo servidor, o <color=#ffa200>2000502-Omega</color> será aberto oficialmente em <color=#ffa200>01/04/2021, à 00:00 (UTC)</color>.\n\nEsperamos que você venha explorar o misterioso Omega e ganhe esta corrida pela banana celeste!\n\nDelegado Roger | H44: 親愛的指揮官：\n\n很高興地告訴你，我們即將在<color=#ffa200>2021-04-01 00:00 UTC</color>開啟新的服務器：<color=#ffa200>2000502-Omega</color>。\n我們期待您能加入對未知Omega的探索，贏得這場關於香蕉的競賽！\n\n羅傑副官 | I44: Kapten yang terhormat,\n\nKami sangat senang mengumumkan bahwa server baru,<color=#ffa200>2000502-Omega</color> akan dibuka secara resmi pada <color=#ffa200>2021-04-01 00:00 UTC</color>.\n\nKami harap kamu akan datang menjelajahi Omega misterius dan memenangkan perlombaan untuk mendapatkan pisang di langit!\n\nDeputi Roger | J44: ถึงท่านผู้บัญชาการ\n\nเรารู้สึกตื่นเต้นสุด ๆ ที่จะประกาศว่าเซิร์ฟเวอร์ใหม่ของเรา <color=#ffa200>2000502-โอเมกา</color> จะเปิดอย่างเป็นทางการในวันที่ <color=#ffa200>01-04-2021 00:00 ตามเวลา UTC</color>\n\nเราหวังว่านายจะได้มาร่วมสำรวจโอเมกาลึกลับ และชนะการแข่งขันเพื่อชิงกล้วยบนท้องฟ้านี้นะ!\n\nท่านรองโรเจอร์ | K44: Querido Capitán, \n\nEstamos muy emocionados de anunciarte que nuestro nuevo servidor <color=#ffa200>2000502-Omega</color> abrirá oficialmente el día <color=#ffa200>01-04-2021 00:00 UTC</color>.\n\n¡Esperamos que vengas a explorar el misterioso Omega y que ganes esta carrera por la banana en el cielo!\n\nComisario Roger | L44: Уважаемый капитан!\n\nМы рады сообщить, что новый сервер <color=#ffa200>2000502-Omega</color> официально открывается в <color=#ffa200>00:00 01.04.2021 (UTC)</color>.\n\nНадеемся, что вы придете исследовать таинственный сервер Omega и сразитесь в гонке за бананом в небе!\n\nПомощник Роджер | M44: Sevgili Kaptan,\n\nYeni sunucu <color=#ffa200>2000502-Omega</color>’nın <color=#ffa200>01.04.2021’de (UTC)</color> resmen açılacağını duyurmaktan mutluluk duyuyoruz.\n\nGelip gizemli Omega’yı keşfetmeni ve gökyüzündeki muz için yapılan bu yarışı kazanmanı bekliyoruz!\n\nYardımcı Roger | N44: Thưa Thủ Lĩnh,\n\nChúng tôi rất vui mừng được thông báo rằng máy chủ mới, <color=#ffa200>2000502-Omega</color> sẽ chính thức được mở ra vào lúc <color=#ffa200>00:00 ngày 01/04/2021 UTC</color>.\n\nChúng tôi hy vọng bạn sẽ khám phá Omega bí ẩn và giành chiến thắng trong cuộc đua chuối trong không gian!\n\nPhụ tá Roger
B45: 合服公告 | C45: 服务器合并公告 | D45: Server Merge Notice | E45: Fusion de serveurs | F45: Hinweis zur Serverfusion | G45: Aviso de junção de servidores | H45: 服務器合併公告 | I45: Pemberitahuan Penggabungan Server | J45: ประกาศเกี่ยวกับการรวมเซิร์ฟเวอร์ | K45: Aviso de Fusión de Servidor | L45: Уведомление о слиянии серверов | M45: Sunucu Birleştirme Bildirimi | N45: Thông báo hợp nhất máy chủ
C46: 亲爱的指挥官：\n\n为了维持服务器的活跃，并平衡各服务器实力，我们即将对您的服务器进行合服，详细安排如下：\n【合服时间】<color=#ffa200>2021-02-01 06:00:00至2021-02-01 10:00:00（UTC时间）</color>；\n\n【合并服务器列表】\n2000402、2000502、2000602、2000702、2000802、2000902、2001002、2001102、2001202将合并至2001202服务器；\n\n【合服注意事项】\n-在<color=#ffa200>合服前7日内（2021-01-25后）</color>，服务器将无法进行注册，同时不再开启新的活动。合服完成后将恢复正常；\n-请在合服前提前领取邮件奖励，合服完成后，所有的邮件及邮件附件将被清除；\n-合服期间，参与合服的服务器处于停服维护状态，玩家不能登录。合服完成后，玩家可正常进入游戏；\n-合服完成后，若玩家在多个相关区都有角色，迁移至新区后多角色可以并存。多角色玩家可在账号界面查看并选择该区下的不同角色；\n-合服完成后，太空里程碑将从第一阶段重新开始，迷雾全服开启，玩家可以进行部落转换；\n-合服完成后，联盟、部落领土及建筑将清空；\n-合服完成后，部落火箭、铁轨将清空；\n-合服完成后，排行榜重新计算；\n-合服完成后，清除所有遗迹数据中立建筑数据，处于初始的争夺状态；\n-合服完成后，火箭发射进程将清除；\n-合服完成后，地图上资源点、野怪重新刷新；\n-合服完成后，所有行军队列、采集中的部队全部遣返回主城；\n-合服完成后，所有受到影响的玩家可以获得以下补偿：\n改名卡*1\nCD*10000\n60分钟训练加速*15\n60分钟研究加速*15\n60分钟建筑加速*15\n50,000粮食*20\n50,000钢铁*20\n\n感谢您对Age of Apes的理解与支持，祝愿火箭发射顺利！\n\n罗杰副官 | D46: Dear Captain,\n\nTo keep servers active and to balance the overall power among them, your server has been scheduled for merging. Details are as follows:\n\n[Time]\n<color=#ffa200>2021-02-01 06:00:00 UTC to 2021-02-01 10:00:00 UTC</color>\n\n[Servers]\nServers 2000402, 2000502, 2000602, 2000702, 2000802, 2000902, 2001002, 2001102, 2001202 will be merged into server 2001202.\n\n[Important Notes]\n- In the <color=#ffa200>7 days before the merge (i.e. after 2021-01-25)</color>, affected servers will not accept account registrations or hold new events. These functions will go back to normal after the server merge is complete.\n- Please claim mail rewards before the merge. After the merge is complete, all mail and mail attachments will be cleared.\n- During the merge, affected servers will undergo maintenance and you will not be able to access the game. You may log in as normal once the merge is complete.\n- If you have multiple roles in various affected servers, these will all be migrated to the new server. You can view and select roles in the Player Info - Settings - Role Manager interface.\n- After the merge, Space Milestones will start from the first stage, fog areas will reset, and players may change Clans.\n- After the merge, Clan and Gang territory and buildings will be cleared.\n- After the merge, Clan Rocket and Railways will be cleared.\n- After the merge, Rankings will reset.\n- After the merge, all data for Ruins and public buildings will be cleared, return to their initial state, and available for occupation.\n- After the merge, Rocket launch progress will be cleared.\n- After the merge, resource spots and mutants on the map will refresh.\n- After the merge, all marching and gathering troops will return to the City.\n- After the merge, all affected players will receive the following compensation:\nRename Avatar *1\nCD*10,000\n60 min Training Speedup*15\n60 min Research Speedup*15\n60 min Building Speedup*15\n50k Food *20\n50k Iron *20\n\nThank you for your support and understanding! See you around the Tavern!\n\nDeputy Roger | E46: Cher capitaine,\n\nAfin de maintenir l'activité et garantir un équilibre global de puissance, une fusion de votre serveur a été programmée comme suit:\n\n[Date]\n<color=#ffa200>Du 01/02/2021 à 06:00:00 TU au 01/02/2021 à 10:00:00 TU</color>\n\n[Serveurs]\nLes serveurs 2000402, 2000502, 2000602, 2000702, 2000802, 2000902, 2001002, 2001102, 2001202 vont être intégrés au serveur 2001202.\n\n\n[A savoir]\n- Dans les <color=#ffa200>7 jours précédant la fusion (c'est-à-dire après le 25-01-2021)</color>, aucun compte ne pourra plus être créé et plus aucun évènement ne pourra plus être organisé sur le serveur. Une fois la fusion terminée, ces fonctions seront rétablies. \n- Veuillez récupérer vos récompenses avant la fusion. Tous les messages ainsi que les pièces jointes seront effacés après la fusion des serveurs.\n- Les serveurs concernés seront en maintenance le temps de la fusion. Vous ne pourrez donc pas vous connecter pendant cet intervalle. Les serveurs seront à nouveau accessibles une fois la fusion terminée. \n- Si vous possédez plusieurs compte sur différents serveurs concernés par la fusion, ceux-ci seront tous migrés sur le nouveau serveur. Pour voir et sélectionner vos comptes, appuyez sur votre avatar en haut à gauche de votre écran (infos joueur) > icône en forme de rouage (réglages) > Compte.\n- Après la fusion, les évènements de l'espace seront réinitialisés au niveau 1, les zones de brume remises à zéro et les joueurs pourront changer de clan s'ils le souhaitent.\n- Après la fusion, les territoires et bâtiments des clans et des gangs seront réinitialisés.\n- Après la fusion, les fusées de clan ainsi que les chemins de fer seront supprimés.\n- Après la fusion, les classements seront remis à zéro\n- Après la fusion, toutes les données relatives aux ruines et aux bâtiments neutres seront effacées, ces derniers seront réinitialisés et pourront donc à nouveau être occupés.\n- Après la fusion, la progression du lancement de la fusée sera remise à zéro.\n- Après la fusion, les points de ressources et les mutants sur la carte seront actualisés.\n- Après la fusion, toutes les troupes en déplacement ou en collecte de ressources seront rapatriées dans la ville.\n- Après la fusion, tous les joueurs affectés recevront les compensations suivantes: \nUn changement de pseudo\n10000 CD\n15 accélérateurs d'entraînement de 60min\n15 accélérateurs de recherche de 60min\n15 accélérateurs de construction de 60min\n20x 50k de nourriture\n20x 50k de ferraille\n\nMerci pour votre compréhension et votre soutien, on se retrouve à la taverne!\n\nRoger l'assistant | F46: Lieber Captain,\n\nUm die Server weiterhin aktiv zu halten und die Machtverhältnisse zwischen ihnen ausgewogen zu halten, wurde dein Server für eine Zusammenlegung (Serverfusion) ausgewählt. Details sind im Folgenden aufgeführt:\n\n[Zeit]\n<color=#ffa200>1.02.2021 06:00:00 UTC bis 01.02.2021 10:00:00 UTC</color>\n\n[Server]\nServers 2000402, 2000502, 2000602, 2000702, 2000802, 2000902, 2001002, 2001102, 2001202 werden zu Server 2001202 zusammengelegt.\n\n[Wichtige Hinweise]\n\n- In den sieben Tagen vor der Serverfusion (d.h. nach dem 25.01.2021) werden die betroffenen Server keine Kontoanmeldungen mehr annehmen und keine neuen Events durchführen. Diese Vorgänge werden nach Abschluss der Serverfusion wieder normal ablaufen.\n- Bitte beanspruche Mail-Belohnungen vor der Serverfusion. Nach Abschluss der Fusion werden alle Mails und Mailanhänge gelöscht.\n- Während der Serverfusion werden die betroffenen Server gewartet und du wirst nicht auf das Spiel zugreifen können. Sobald die Fusion abgeschlossen ist, kannst du dich wieder normal einloggen.\n- Wenn du mehrere Charaktere auf verschiedenen betroffenen Servern hast, werden diese alle auf den neuen Server übertragen. Du kannst die Charaktere im Interface Spieler-Info > Einstellungen > Rollenverwaltung betrachten und auswählen.\n- Nach der Serverfusion beginnen die Weltraum-Meilensteine wieder von der ersten Stufe an, die Nebelgebiete werden zurückgesetzt, und die Spieler können die Horde wechseln.\n- Nach der Serverfusion werden Horden und Clan-Territorien und -Gebäude geräumt.\n- Nach der Serverfusion werden Hordenraketen und -Eisenbahnschienen zurückgesetzt.\n- Nach der Serverfusion werden die Ranglisten zurückgesetzt.\n- Nach der Serverfusion werden alle Daten für Ruinen und öffentliche Gebäude gelöscht und sind wieder in ihrem ursprünglichen Zustand und zur Besetzung verfügbar.\n- Nach der Serverfusion wird der Raketenstart-Fortschritt zurückgesetzt.\n- Nach der Serverfusion werden Ressourcenpunkte und Mutanten auf der Karte aktualisiert.\n- Nach der Serverfusion kehren alle marschierenden und sammelnden Truppen in die Stadt zurück.\n- Nach der Serverfusion erhalten alle betroffenen Spieler die folgende Entschädigung:\nAvatar umbenennen*1\nCD*10.000\n60 Min. Ausbildungsbeschleunigung*15\n60 Min. Forschungsbeschleunigung*15\n60 Min. Baubeschleunigung*15\nNahrung*20\nEisen*20\nCD*10.000\n\nVielen Dank für deine Unterstützung und dein Verständnis! \n\nWir sehen uns in der Taverne! | G46: Caro Capitão,\n\nA fim de manter os servidores ativos e balancear o poder geral entre eles, foi agendada uma junção para o seu servidor. Seguem-se os detalhes:\n\n[Time]\n<color=#ffa200>De 01/02/2021 6h (UTC) a 01/02/2021 10h (UTC)</color>\n\n[Servidores]\nOs servidores 2000402, 2000502, 2000602, 2000702, 2000802, 2000902, 2001002, 2001102, 2001202 serão integrados ao 2001202.\n\n[Avisos importantes]\n- Durante os <color=#ffa200>7 dias antes da integração (após 25/01/2021)</color>, os servidores afetados não aceitarão novos registros, assim como não haverá novos eventos. Tais funções voltarão ao normal depois que a junção estiver completa.\n- Lembre-se de resgatar todas as recompensas na caixa de entrada antes da junção. Depois disso, todos os anexos e mensagens da caixa de entrada serão apagados.\n- Durante a junção, os servidores afetados entrarão em manutenção e você não poderá acessar o jogo. Você poderá entrar normalmente assim que a junção estiver completa.\n- Caso você tenha várias funções em mais de um servidor afetado, elas serão migradas para o novo servidor. Veja e selecione as funções na interface: Informações do jogador - Configurações - Gerenciador de Funções.\n- Depois da junção, marcos espaciais voltarão à primeira fase, as áreas de névoa serão reiniciadas e os jogadores poderão trocar de clã.\n- Depois da junção, os territórios e estruturas dos clãs e das gangues serão apagados.\n- Depois da junção, ferrovias e foguetes dos clãs serão apagados.\n- Depois da junção, as classificações serão reiniciadas.\n- Depois da junção, ruínas e estruturas públicas serão apagadas, retornando ao estado inicial delas, o que as deixará disponíveis para ocupação.\n- Depois da junção, os avanços nos lançamentos de foguetes serão apagados.\n- Depois da junção, pontos de recursos e mutantes no mapa serão atualizados.\n- Depois da junção, todas as tropas em deslocamento e que estejam coletando recursos voltarão para a cidade.\n- Depois da junção, todos os jogadores afetados receberão o seguinte como compensação:\nAvatar renomeado x 1\nCD x 10.000\nAceleradores de treinamento de 60 minutos x 15\nAceleradores de pequisa de 60 minutos x 15\nAceleradores de construção de 60 minutos x 15\n50k de comida x 20\n50k de ferro x 20\nCD x 10.000\n\nAgradecemos sua compreensão e apoio! Vemos você na taverna!\n\nDelegado Roger | H46: 親愛的指揮官：\n\n為了維持服務器的活躍，並平衡各服務器實力，我們即將對您的服務器進行合服，詳細安排如下：\n【合服時間】<color=#ffa200>2021-02-01 06:00:00至2021-02-01 10:00:00（UTC時間）</color>；\n\n【合併服務器列表】\n2000402、2000502、2000602、2000702、2000802、2000902、2001002、2001102、2001202將合併至2001202服務器；\n\n【合服注意事項】\n-在<color=#ffa200>合服前7日內（2021-01-25後）</color>，服務器將無法進行註冊，同時不再開啟新的活動。合服完成後將恢復正常；\n-請在合服前提前領取郵件獎勵，合服完成後，所有的郵件及郵件附件將被清除；\n-合服期間，參與合服的服務器處於停服維護狀態，玩家不能登錄。合服完成後，玩家可正常進入遊戲；\n-合服完成後，若玩家在多個相關區都有角色，遷移至新區後多角色可以並存。多角色玩家可在賬號界面查看並選擇該區下的不同角色；\n-合服完成後，太空里程碑將從第一階段重新開始，迷霧全服開啟，玩家可以進行部落轉換；\n-合服完成後，聯盟、部落領土及建築將清空；\n-合服完成後，部落火箭、鐵軌將清空；\n-合服完成後，排行榜重新計算；\n-合服完成後，清除所有遺跡數據中立建築數據，處於初始的爭奪狀態；\n-合服完成後，火箭發射進程將清除；\n-合服完成後，地圖上資源點、野怪重新刷新；\n-合服完成後，所有行軍隊列、採集中的部隊全部遣返回主城；\n-合服完成後，所有受到影響的玩家可以獲得以下補償：\n改名卡*1\nCD*10000\n60分鐘訓練加速*15\n60分鐘研究加速*15\n60分鍾建築加速*15\n50,000糧食*20\n50,000鋼鐵*20\n\n感謝你對Age of Apes的理解與支持，祝愿火箭發射順利！\n\n羅傑副官 | I46: Kapten yang terhormat,\n\nUntuk menjaga server tetap aktif dan untuk menyeimbangkan kekuatan keseluruhan di antaranya, servermu telah dijadwalkan untuk digabungkan. Detailnya adalah sebagai berikut:\n\n[Waktu]\n<color=#ffa200>2021-02-01 06:00:00 UTC hingga 2021-02-01 10:00:00 UTC</color>\n\n[Server]\nServers 2000402, 2000502, 2000602, 2000702, 2000802, 2000902, 2001002, 2001102, 2001202 akan digabungkan dengan server 2001202.\n\n[Catatan Penting]\n- In the <color=#ffa200>7 hari sebelum penggabungan (mis. setelah 2021-01-25)</color>, server yang terpengaruh tidak akan menerima pendaftaran akun atau mengadakan acara baru. Fungsi ini akan kembali normal setelah penggabungan server selesai.\n- Klaim hadiah kotak masuk sebelum penggabungan. Setelah penggabungan selesai, semua kotak masuk dan lampiran kotak masuk akan dihapus.\n- Selama penggabungan, server yang terpengaruh akan menjalani pemeliharaan dan kamu tidak akan bisa mengakses game. Kamu bisa masuk seperti biasa setelah penggabungan selesai.\n- Jika kamu memiliki banyak peran di berbagai server yang terpengaruh, semuanya akan dipindahkan ke server baru. Kamu bisa melihat dan memilih peran di Info Pemain - Pengaturan - antarmuka Manajer Peran.\n- Setelah penggabungan, Tonggak Luar Angkasa akan dimulai dari tahap pertama, area kabut akan diatur ulang, dan pemain bisa berganti Klan.\n- Setelah penggabungan, wilayah dan bangunan Klan dan Geng akan dihapus.\n- Setelah penggabungan, Roket dan Rel Kereta Api Klan akan dihapus.\n- Setelah penggabungan, Peringkat akan diatur ulang.\n- Setelah penggabungan, semua data Reruntuhan dan bangunan umum akan dibersihkan, kembali ke keadaan semula, dan tersedia untuk ditempati.\n- Setelah penggabungan, progres peluncuran Roket akan dihapus.\n- Setelah penggabungan, tempat sumber daya dan mutan di peta akan diperbarui.\n- Setelah penggabungan, semua pasukan yang berbaris dan berkumpul akan kembali ke Kota.\n- Setelah penggabungan, semua pemain yang terpengaruh akan menerima kompensasi berikut:\nUbah nama Avatar *1\nCD*10.000\n60 menit Percepatan Latihan*15\n60 menit Percepatan Riset*15\n60 menit Percepatan Gedung*15\n50k Makanan *20\n50k Besi *20\nCD*10000\n\nTerima kasih atas dukungan dan pengertianmu! Sampai jumpa di sekitar Kedai!\n\nDeputi Roger | J46: ถึงท่านผู้บัญชาการ\n\nเพื่อให้เซิร์ฟเวอร์ใช้งานได้อย่างเป็นปกติและเพื่อความสมดุลของค่าพลังโดยรวมระหว่างเซิร์ฟเวอร์ เราจึงกำหนดเวลาสำหรับการรวมเซิร์ฟเวอร์ของนายเข้าด้วยกันดังรายละเอียดต่อไปนี้:\n\n[เวลา]\n<color=#ffa200>วันที่ 01-02-2021 06:00:00 UTC ถึง 01-02-2021 10:00:00 UTC</color>\n\n[เซิร์ฟเวอร์]\nเซิร์ฟเวอร์ 2000402, 2000502, 2000602, 2000702, 2000802, 2000902, 2001002, 2001102, 2001202 จะถูกรวมเข้ากับเซิร์ฟเวอร์ 2001202\n\n[หมายเหตุสำคัญ]\n- ในช่วงเวลา<color=#ffa200> 7 วันก่อนการรวม (เช่น หลังวันที่ 25-01-2021)</color> เซิร์ฟเวอร์ที่ได้รับผลกระทบจะไม่ยอมรับการลงทะเบียนบัญชีใหม่หรือการจัดกิจกรรมใหม่ใด ๆ โดยฟังก์ชันเหล่านี้จะกลับคืนสู่สภาวะปกติหลังจากการรวมเซิร์ฟเวอร์เสร็จสมบูรณ์แล้ว\n- โปรดรับรางวัลทางเมลก่อนการรวม เนื่องจากเมื่อการรวมเซิร์ฟเวอร์เสร็จสมบูรณ์แล้ว อีเมลและไฟล์แนบทั้งหมดจะถูกล้างออกไป\n- ในระหว่างการรวม เราจะทำการบำรุงรักษาเซิร์ฟเวอร์ที่ได้รับผลกระทบ ซึ่งนายจะไม่สามารถเข้าเล่นเกมได้ โดยนายจะสามารถเข้าสู่ระบบได้ตามปกติเมื่อการรวมเสร็จสมบูรณ์\n- หากนายทำหน้าที่หลายบทบาทในเซิร์ฟเวอร์ที่ได้รับผลกระทบ หน้าที่ทั้งหมดจะถูกย้ายไปที่เซิร์ฟเวอร์ใหม่ โดยนายสามารถดูและเลือกบทบาทได้ในอินเตอร์เฟสข้อมูลผู้เล่น - การตั้งค่า - ตัวจัดการบทบาท\n- หลังการรวม เหตุการณ์สำคัญแห่งอวกาศจะเริ่มต้นใหม่จากด่านแรก พื้นที่หมอกจะถูกรีเซ็ต และผู้เล่นจะสามารถเปลี่ยนเผ่าได้\n- หลังการรวม อาณาเขตและสิ่งปลูกสร้างของเผ่าและแก๊งจะถูกล้างใหม่\n- หลังการรวม จรวดและรางรถไฟของเผ่าจะถูกล้างใหม่\n- หลังการรวม อันดับจะถูกรีเซ็ต\n- หลังการรวม ข้อมูลทั้งหมดของซากปรักหักพังและสิ่งปลูกสร้างสาธารณะจะถูกล้างกลับสู่สถานะเริ่มต้น ซึ่งพร้อมให้ทุกคนเข้าการยึดครอง\n- หลังการรวม ความคืบหน้าในการปล่อยจรวดจะถูกล้างใหม่\n- หลังการรวม จุดทรัพยากรและเหล่ามิวแตนต์บนแผนที่จะถูกรีเฟรชใหม่\n- หลังการรวม กองทหารที่เดินทัพและออกเก็บรวมรวมทรัพยากรทั้งหมดจะกลับไปที่เมือง\n- หลังการรวม ผู้เล่นที่ได้รับผลกระทบทั้งหมดจะได้รับของขวัญชดเชยดังต่อไปนี้:\nไอเทมเปลี่ยนชื่ออวาตาร์ 1 ชิ้น\nซีดี 10,000 แผ่น\nไอเทมเร่งความเร็ว 60 นาที 15 ชิ้น\nไอเทมเร่งการวิจัย 60 นาที 15 ชิ้น\nไอเทมเร่งความเร็วการก่อสร้าง 60 นาที 15 ชิ้น\nอาหาร 50k 20 ชิ้น\nเหล็ก 50k 20 ชิ้น\nซีดี *10000 แผ่น\n\nขอบคุณสำหรับการสนับสนุนและความเข้าใจ! แล้วไว้เจอกันแถว ๆ โรงแรมนะ!\n\nท่านรองโรเจอร์ | K46: Querido Capitán, \n\nPara mantener los servidores activos y balancear el poder en general entre ellos, tu servidor ha sido programado para una fusión. Los detalles son los siguientes:\n\n[Hora]\n<color=#ffa200>01-02-2021 06:00:00 UTC a las 01-02-2021 10:00:00 UTC</color>\n\n[Servidores]\nLos servidores 2000402, 2000502, 2000602, 2000702, 2000802, 2000902, 2001002, 2001102, 2001202 serán fusionados en el servidor 2001202.\n\n[Notas importantes]\n- Durante los <color=#ffa200>7 días anteriores a la fusión (por ej. después del 25-01-2021)</color>, los servidores afectados no aceptaran registros de cuentas realizarán eventos nuevos. Estas funciones regresaran a la normalidad después de que la fusión del servidor esté completa. \n- Por favor, reclama las recompensas por correo antes de la fusión. Después de que la fusión este completa, todos los correos y archivos adjuntos de correo serán eliminados. \n- Durante la fusión, los servidores afectados estarán bajo mantenimiento y no te será posible acceder al jugo. Podrás conectarte normalmente cuando la fusión este completa. \n- Si tienes múltiples roles en los servidores afectados, todos ellos serán migrados hacia el nuevo servidor. Puedes ver y seleccionar los roles en la Información del Jugador – Configuraciones – Interface de Administración de Roles. \n- Después de la fusión, los Logros del Espacio comenzarán desde la primera etapa, las áreas de niebla serán reiniciadas y los jugadores podrán cambiar de Clanes. \n- Después de la fusión, el territorio del Clan y de la Banda y los edificios serán eliminados. \n- Después de la fusión, el Cohete del Clan y las Vías del Tren serán eliminadas. \n- Después de la fusión, las Clasificaciones serán reiniciadas. \n- Después de la fusión, todos los datos de las Ruinas y de los edificios públicos serán eliminados, regresados a su estado inicial y estarán disponibles para ocupación. \n- Después de la fusión, el progreso en el lanzamiento del Cohete será eliminado. \n- Después de la fusión, los puntos de recursos y los mutantes en el mapa serán actualizados. \n- Después de la fusión, todas las tropas en marcha y recolectando regresarán a la Ciudad. \n- Después de la fusión todos los jugadores afectados recibirán la siguiente compensación:\nRenombrar Avatar *1\nCD*10,000\nAcelerador de Entrenamiento de 60 min *15\nAcelerador de Investigación de 60 min *15\nAcelerador de Construcción de 60 min *15\n50k de Comida *20\n50k de Hierro *20\nCD*10000\n\n¡Gracias por tu apoyo y comprensión! Nos vemos en la Taberna.\n\n\nComisario Roger | L46: Уважаемый капитан!\n\nДля поддержания активности на серверах и сохранения баланса общей мощи на них, мы проводим слияние серверов, которое затронет и ваш сервер. Вот подробности:\n\n[Время]\n<color=#ffa200>с 06:00 01.02.2021 по 10:00 01.02.2021 (UTC)</color>\n\n[Серверы]\nСерверы 2000402, 2000502, 2000602, 2000702, 2000802, 2000902, 2001002, 2001102 и 2001202 будут объединены в сервер 2001202.\n\n[Важные примечания]\n– В течение <color=#ffa200>7 дней до слияния (то есть с 25.01.2021)</color> на упомянутых серверах не будут проводиться ни новые события, ни регистрация новых учетных записей. Эти функции вернутся после завершения слияния серверов.\n– Пожалуйста, получите награды из почты до слияния. После завершения слияния вся почта и почтовые вложения будут очищены.\n– Во время слияния затронутые серверы будут закрыты на техобслуживание, и вы не сможете войти в игру. Вы сможете войти в систему после завершения слияния.\n– Если у вас было несколько персонажей на разных затронутых серверах, все они будут перенесены на новый сервер. Вы сможете просматривать и выбирать роли в разделе «Сведения об игроке > Настройки > Управление ролями».\n– После слияния космические рубежи вернутся на первый этап, области тумана будут сброшены, а игроки смогут поменять кланы.\n– После слияния территории и постройки кланов и банд будут сброшены.\n– После слияния ракеты и железные дороги кланов будут сброшены.\n– После слияния рейтинг будет сброшен.\n– После слияния все данные о руинах и общественных зданиях будут сброшены; объекты вернутся в исходное состояние и будут доступны для оккупации.\n– После слияния прогресс запуска ракет будет сброшен.\n– После слияния обновятся точки ресурсов и мутанты на карте.\n– После слияния все войска на марше и собирающие войска вернутся в город.\n– После слияния все игроки, которых оно затронуло, получат следующую компенсацию:\nСмена имени x1\nCD x10 000\nУскорители обучения на 60 мин. x15\nУскорители исследований на 60 мин. x15\nУскорители строительства на 60 мин. x15\n50K ед. пищи x20\n50K ед. железа x20\n\nБлагодарим за поддержку и понимание. Увидимся в таверне!\n\nПомощник Роджер | M46: Sevgili Kaptan,\n\nSunucuların etkinliğini sağlamak ve toplam güçlerini dengelemek için sunucun başka sunucularla birleştirilecek. Detaylar şöyle:\n\n[Zaman]\n<color=#ffa200>01.02.2021, 06:00:00 (UTC) ile 01.02.2021, 10:00:00 (UTC) arası</color>\n\n[Sunucular]\n2000402, 2000502, 2000602, 2000702, 2000802, 2000902, 2001002, 2001102, 2001202 sunucuları 2001202 sunucusu ile birleştirilecek.\n\n[Önemli Notlar]\n- <color=#ffa200>Birleşme öncesindeki 7 gün içinde (ör. 25.01.2021 sonrası)</color>, etkilenen sunucular hesap kaydı kabul etmeyecek veya buralarda yeni etkinlik düzenlenmeyecek. Bu işlevler sunucu birleşmesi tamamlandıktan sonra normale dönecek.\n- Lütfen birleşme öncesinde posta ödüllerini al. Birleşme tamamlandıktan sonra tüm postalar ve posta ekleri ortadan kalkar.\n- Birleşme sırasında, etkilenen sunucular bakıma girecek ve bu sürede oyuna erişim sağlayamayacaksın. Birleşme tamamlanınca normal şekilde giriş yapabilirsin.\n- Etkilenen çeşitli sunucularda birden fazla rolün varsa, bunların tümü yeni sunucuyla birleştirilecek. Oyuncu Bilgisi - Ayarlar - Rol Yöneticisi arayüzünden rolleri görebilir ve seçebilirsin.\n- Birleşme sonrasında, Uzay Dönüm Noktaları ilk aşamadan başlar, sis alanları sıfırlanır ve oyuncular Klan değiştirebilir.\n- Birleşme sonrasında Klan, Çete bölgesi ve binalar ortadan kalkar.\n- Birleşme sonrasında Klan Roketi ve Demir Yolları ortadan kalkar.\n- Birleşme sonrasında Sıralamalar sıfırlanır.\n- Birleşme sonrasında Harabe ve kamu binası verileri ortadan kalkar, ilk durumlarına geri dönerler ve işgal edilebilir hâle gelirler.\n- Birleşme sonrasında Roket fırlatma süreci başa döner.\n- Birleşme sonrasında haritadaki kaynak noktaları ve mutantlar yenilenir.\n- Birleşme sonrasında seferdeki ve toplama durumundaki tüm birlikler Şehre döner.\n- Birleşme sonrasında etkilenen tüm oyuncular şu telafileri alır:\nAvatarı Yeniden Adlandır *1\nCD *10.000\n60 dk Eğitim Hızlandırıcı *15\n60 dk Araştırma Hızlandırıcı *15\n60 dk İnşaat Hızlandırıcı *15\n50.000 Yiyecek *20\n50.000 Demir *20\nCD *10.000\n\nDesteğin ve anlayışın için teşekkürler! Tavernada görüşürüz!\n\nYardımcı Roger | N46: Thưa Thủ Lĩnh,\n\nĐể các máy chủ tiếp tục hoạt động tích cực và cân bằng sức mạnh tổng thể giữa các máy chủ này, chúng tôi đã lên lịch hợp nhất cho máy chủ của bạn. Thông tin chi tiết như sau:\n\n[Thời gian]\n<color=#ffa200>06:00:00 UTC ngày 01/02/2021 đến 10:00:00 UTC ngày 01/02/2021</color>\n\n[Máy chủ]\nCác máy chủ 2000402, 2000502, 2000602, 2000702, 2000802, 2000902, 2001002, 2001102, 2001202 sẽ được hợp thành máy chủ 2001202.\n\n[Thông báo quan trọng]\n- Trong vòng <color=#ffa200>7 ngày trước khi hợp nhất (chẳng hạn như 25/01/2021)</color>, các máy chủ bị ảnh hưởng sẽ không thể đăng ký tài khoản mới hoặc tổ chức các sự kiện mới. Các chức năng này sẽ hoạt động bình thường trở lại sau khi quá trình hợp nhất máy chủ hoàn tất.\n- Vui lòng nhận phần thưởng trong thư trước khi hợp nhất. Sau khi quá trình hợp nhất hoàn tất, tất cả thư và quà đính kèm trong thư sẽ bị xóa.\n- Trong quá trình hợp nhất, các máy chủ bị ảnh hưởng sẽ trong thời gian bảo trì và bạn sẽ không thể truy cập vào trò chơi. Bạn có thể đăng nhập bình thường sau khi quá trình hợp nhất hoàn tất.\n- Nếu bạn có nhiều nhân vật trong nhiều máy chủ bị ảnh hưởng, tất cả các nhân vật này sẽ được chuyển sang máy chủ mới. Bạn có thể xem và chọn nhân vật trong giao diện Thông tin người chơi - Cài đặt - Quản lý nhân vật.\n- Sau khi hợp nhất, Cột Mốc Không Gian sẽ bắt đầu từ giai đoạn đầu tiên, các khu vực sương mù sẽ thiết lập lại và người chơi có thể đổi Bộ Lạc.\n- Sau khi hợp nhất, lãnh thổ và các công trình của Bộ Lạc và Bang Hội sẽ bị xóa.\n- Sau khi hợp nhất, Hỏa Tiễn và Đường Sắt Bộ Lạc sẽ bị xóa.\n- Sau khi hợp nhất, BXH sẽ thiết lập lại.\n- Sau khi hợp nhất, tất cả dữ liệu Tàn Tích và công trình công cộng sẽ bị xóa, trở về trạng thái ban đầu và sẵn sàng để chiếm đóng.\n- Sau khi hợp nhất, tiến trình phóng Hỏa Tiễn sẽ bị xóa.\n- Sau khi hợp nhất, các điểm tài nguyên và Vượn Đột Biến trên bản đồ sẽ được làm mới.\n- Sau khi hợp nhất, tất cả binh lính đang hành quân và tập kết sẽ trở về Thành Phố.\n- Sau khi hợp nhất, tất cả người chơi bị ảnh hưởng sẽ nhận được phần thưởng bồi thường như sau:\nĐổi Tên Hình Đại Diện *1\nCD*10.000\nVật Phẩm Tăng Tốc Huấn Luyện 60 phút*15\nVật Phẩm Tăng Tốc Nghiên Cứu 60 phút*15\nVật Phẩm Tăng Tốc Xây Dựng 60 phút*15\n50k Thực Phẩm *20\n50k Sắt *20\nCD*10000\n\nCảm ơn bạn đã thông cảm và hỗ trợ! Hẹn gặp lại ở Tửu Quán nhé!\n\nPhụ tá Roger
B47: 合服补偿 | C47: 合服补偿 | D47: Server Merge Compensation | E47: Compensation pour la fusion des serveurs | F47: Entschädigung für Serverfusion | G47: Compensação pela junção de servidores | H47: 合服補償 | I47: Kompensasi Penggabungan Server | J47: การชดเชยกรณีการรวมเซิร์ฟเวอร์ | K47: Compensación por la Fusión de Servidor | L47: Компенсация за слияние серверов | M47: Sunucu Birleştirme Telafisi | N47: Quà đền bù hợp nhất máy chủ
C48: 亲爱的指挥官：\n\n以下是你的合服补偿，请注意查收。\n\n感谢您对Age of Apes的理解与支持，祝愿火箭发射顺利！\n\n罗杰副官 | D48: Dear Captain,\n\nPlease claim your server merge compensation:\n\nThank you for your understanding and support! See you around the Tavern!\n\nDeputy Roger | E48: Cher capitaine,\n\nVous trouverez ci-dessous votre compensation pour la fusion des serveurs:\n\nMerci pour votre compréhension et votre soutien! On se retrouve à la taverne!\n\nRoger l'assistant | F48: Lieber Captain,\n\nBitte fordere deine Entschädigung für die Serverfusion ein::\n\nVielen Dank für dein Verständnis und deine Unterstützung! Wir sehen uns in der Taverne!\n\nAdjudant Roger | G48: Caro Capitão,\n\nResgate a compensação pela junção de servidores:\n\nAgradecemos sua compreensão e suporte! Vemos você na taverna!\n\nDelegado Roger | H48: 親愛的指揮官：\n\n以下是你的合服補償，請注意查收。\n\n感謝你對Age of Apes的理解與支持，祝愿火箭發射順利！\n\n羅傑副官 | I48: Kapten yang terhormat,\n\nKlaim kompensasi penggabungan servermu:\n\nTerima kasih atas pengertian dan dukunganmu! Sampai Jumpa di Sekitar Kedai\n\nDeputi Roger | J48: ถึงท่านผู้บัญชาการ\n\nโปรดรับของขวัญชดเชยกรณีการรวมเซิร์ฟเวอร์ของนายต่อไปนี้:\n\nขอขอบคุณสำหรับความเข้าใจและการสนับสนุน! แล้วไว้เจอกันแถว ๆ โรงแรมนะ!\n\nท่านรองโรเจอร์ | K48: Querido Capitán, \n\nPor favor, reclama tu compensación por la fusión de servidores: \n\nGracias por tu comprensión y apoyo. ¡Nos vemos en la Taberna!\n\nComisario Roger | L48: Уважаемый капитан!\n\nПожалуйста, заберите компенсацию за слияние серверов:\n\nСпасибо за понимание и поддержку. Увидимся в таверне!\n\nПомощник Роджер | M48: Sevgili Kaptan,\n\nLütfen sunucu birleştirme telafini al:\n\nAnlayışın ve desteğin için teşekkürler! Tavernada görüşürüz!\n\nYardımcı Roger | N48: Thưa Thủ Lĩnh,\n\nVui lòng nhận quà đền bù hợp nhất máy chủ của bạn:\n\nCảm ơn bạn đã thông cảm và hỗ trợ! Hẹn gặp lại ở Tửu Quán nhé!\n\nPhụ tá Roger
A49: 更新调整 | B49: 英雄平衡性调整补偿 | C49: 关于斗士的补偿说明 | D49: Fighter Compensation | E49: Compensation pour l'équilibrage des combattants | F49: Kämpfer-Entschädigung | G49: Compensação de combatente | H49: 關於鬥士的補償說明 | I49: Kompensasi Pejuang | J49: การชดเชยกรณีการปรับเปลี่ยนนักสู้ | K49: Compensación al Luchador | L49: Компенсация за героев | M49: Savaşçı Telafisi | N49: Đền Bù Chiến Binh
C50: 亲爱的指挥官： 由于最近进行了英雄平衡性调整，我们将为您送上一份补偿：\n\n谢谢你对我们的支持，我们将不断改进，希望能得到您的理解和支持，下一次在酒馆中再次干杯!\n\n罗杰副官 | D50: Dear Captain,\n\nTo compensate for the recent adjustments in the Fighter system, we'd like to offer you the following reward:\n\nThank you for your understanding and support as we continue to improve and progress. See you around the Tavern!\n\nDeputy Roger | E50: Cher capitaine,\n\nSuite aux récents équilibrages dans le système des combattants, nous avons décidé de vous offrir la compensation suivante:\n\nMerci pour votre compréhension et votre soutien. Nous mettons tout en œuvre pour continuer à progresser et améliorer le jeu.\n\nOn se retrouve à la taverne!\n\nRoger l'assistant | F50: Lieber Captain,\n\nUm die kürzlichen Anpassungen im Kämpfer-System zu kompensieren, möchten wir dir die folgende Belohnung anbieten:\n\nVielen Dank für dein Verständnis und deine Unterstützung, während wir uns weiter verbessern und vorankommen. Wir sehen uns in der Taverne!\n\nAdjudant Roger | G50: Caro Capitão,\n\nPara compensar os ajustes recentes no sistema de combatentes, gostaríamos de oferecer a seguinte recompensa:\n\nAgradecemos pela sua compreensão e suporte ao passo que continuamos melhorando. Vemos você na taverna!\n\nDelegado Roger | H50: 親愛的指揮官： 由於最近進行了英雄平衡性調整，我們將為您送上一份補償：\n\n謝謝你對我們的支持，我們將不斷改進，希望能得到您的理解和支持，下一次在酒館中再次乾杯!\n\n羅傑副官 | I50: Kapten yang terhormat,\n\nUntuk mengimbangi penyesuaian terbaru dalam sistem Pejuang, kami ingin menawarkan hadiah berikut:\n\nTerima kasih atas pengertian dan dukunganmu sementara kami terus meningkatkan dan membuat kemajuan. Sampai jumpa di sekitar Kedai!\n\nDeputi Roger | J50: ถึงท่านผู้บัญชาการ\n\nโปรดรับของขวัญชดเชยกรณีการปรับเปลี่ยนระบบนักสู้ของนายดังต่อไปนี้:\n\nขอขอบคุณสำหรับความเข้าใจและการสนับสนุนของนายในการปรับปรุงและพัฒนาอย่างต่อเนื่องของเรา แล้วไว้เจอกันแถว ๆ โรงแรมนะ!\n\nท่านรองโรเจอร์ | K50: Querido Capitán, \n\nPara compensar por los ajustes recientes al sistema de Luchador, deseamos ofrecerte la siguiente recompensa:\n\nGracias por tu comprensión y apoyo mientras continuamos mejorando y progresando. ¡Nos vemos en la Taberna!\n\nComisario Roger | L50: Уважаемый капитан!\n\nВ качестве компенсации за недавнюю корректировку системы героев мы хотим предложить вам следующую награду:\n\nСпасибо за понимание и поддержку наших мер по улучшению и развитию игры. Увидимся в таверне!\n\nПомощник Роджер | M50: Sevgili Kaptan,\n\nYakın zamanda Savaşçı sisteminde yapılan düzenlemelerin telafisi olarak sana şu ödülü sunmak istiyoruz:\n\nGelişme ve ilerleme sürecimizdeki anlayışın ve desteğin için teşekkürler. Tavernada görüşürüz!\n\nYardımcı Roger | N50: Thưa Thủ Lĩnh,\n\nĐể đền bù cho những điều chỉnh gần đây trong hệ thống Chiến Binh, chúng tôi muốn tặng bạn phần thưởng sau:\n\nCảm ơn các bạn đã thông cảm và ủng hộ trong thời gian chúng tôi tiếp tục cải thiện và tiến bộ. Hẹn gặp lại ở Tửu Quán nhé!\n\nPhụ tá Roger
B51: 数值平衡性调整补偿 | C51: 关于平衡性的补偿说明 | D51: Balance Adjustment Compensation | E51: Compensation pour les équilibrages | F51: Entschädigung für Balance-Anpassung | G51: Compensação pelo ajuste no balanceamento | H51: 關於平衡性的補償說明 | I51: Kompensasi Penyesuaian Saldo | J51: การชดเชยกรณีการปรับสมดุล | K51: Compensación de Ajuste de Balance | L51: Компенсация за корректировку баланса | M51: Denge Düzenlemesi Telafisi | N51: Đền Bù Điều Chỉnh Cân Bằng
C52: 亲爱的指挥官：\n\n由于最近进行了数值平衡性调整，我们将为您送上一份补偿：\n\n谢谢你对我们的支持，我们将不断改进，希望能得到您的理解和支持，下一次在酒馆中再次干杯!\n\n罗杰副官 | D52: Dear Captain,\n\nWe have included a reward for you as compensation for the recent stat balance adjustments:\n\nThank you for the understanding and support as we continue to improve. See you around the Tavern!\n\nDeputy Roger | E52: Cher capitaine,\n\nSuite aux récents équilibrages des statistiques, nous avons décidé de vous offrir la compensation suivante:\n\nMerci pour votre compréhension et votre soutien. Nous mettons tout en œuvre pour continuer à progresser et améliorer le jeu. \n\nOn se retrouve à la taverne!\n\nRoger l'assistant | F52: Lieber Captain,\n\nAls Entschädigung für die kürzlich vorgenommenen Balance-Anpassungen haben wir eine Belohnung beigefügt:\n\nVielen Dank für dein Verständnis und deine Unterstützung, während wir uns weiter verbessern. Wir sehen uns in der Taverne!\n\nAdjudant Roger | G52: Caro Capitão,\n\nIncluímos uma recompensa para você como compensação pelo balanceamento de atributos mais recente:\n\nAgradecemos sua compreensão e suporte ao passo que continuamos melhorando. Vemos você na taverna!\n\nDelegado Roger | H52: 親愛的指揮官：\n\n由於最近進行了數值平衡性調整，我們將為您送上一份補償：\n\n謝謝你對我們的支持，我們將不斷改進，希望能得到您的理解和支持，下一次在酒館中再次乾杯!\n\n羅傑副官 | I52: Kapten yang terhormat,\n\nKami telah menyertakan hadiah untukmu sebagai kompensasi atas penyesuaian saldo status terbaru:\n\nTerima kasih atas pengertian dan dukunganmu sementara kami terus meningkatkan game. Sampai jumpa di sekitar Kedai!\n\nDeputi Roger | J52: ถึงท่านผู้บัญชาการ\n\nโปรดรับของขวัญชดเชยกรณีการปรับสมดุลของค่าพลังล่าสุดดังต่อไปนี้:\n\nขอขอบคุณสำหรับความเข้าใจและการสนับสนุนการปรับปรุงอย่างต่อเนื่องของเรา แล้วไว้เจอกันแถว ๆ โรงแรมนะ!\n\nท่านรองโรเจอร์ | K52: Querido Capitán, \n\nHemos incluido una recompensa para ti como compensación por el reciente ajuste para balancear estadísticas: \n\n¡Gracias por tu comprensión y apoyo mientras continuamos mejorando! Nos vemos en la Taberna.\n\nComisario Roger | L52: Уважаемый капитан!\n\nВ качестве компенсации за недавнюю корректировку баланса мы отправили вам награду:\n\nСпасибо за понимание и поддержку наших мер по улучшению игры. Увидимся в таверне!\n\nПомощник Роджер | M52: Sevgili Kaptan,\n\nSon özellik dengesi düzenlemesi için sana telafi olarak bir ödül sunuyoruz:\n\nGelişme sürecimizdeki anlayışın ve desteğin için teşekkürler. Tavernada görüşürüz!\n\nYardımcı Roger | N52: Thưa Thủ Lĩnh,\n\nChúng tôi có kèm theo một phần thưởng tặng bạn để đền bù cho những đợt điều chỉnh cân bằng chỉ số gần đây:\n\nCảm ơn các bạn đã thấu hiểu và hỗ trợ chúng tôi tiếp tục cải thiện. Hẹn gặp lại ở Tửu Quán nhé!\n\nPhụ tá Roger
B53: 数值平衡性调整说明 | C53: 0.26.0版本平衡性调整说明 | D53: Version 0.26.0 Balance Adjustments | E53: Equilibrage version 0.26.0 | F53: Version 0.26.0 Balance-Anpassungen | G53: Ajustes de balanceamento da versão 0.26.0 | H53: 0.26.0版本平衡性調整說明 | I53: Penyesuaian Saldo Versi 0.26.0 | J53: เวอร์ชัน 0.26.0 การปรับสมดุล | K53: Ajustes de Balance para la Versión 0.26.0 | L53: Настройки баланса в версии 0.26.0 | M53: Sürüm 0.26.0 Denge Düzenlemeleri | N53: Điều Chỉnh Cân Bằng Phiên Bản 0.26.0
C54: 亲爱的指挥官：\n\n为了确保整体的游戏平衡，我们在即将更新的0.26.0版本进行了以下<color=#ffa200>数值调整</color>：\n\nxxxxx\n\n\n对于本次调整，我们将会进行以下的补偿：\n\nxxxxx\n\n谢谢您对我们的支持，我们将不断改进，希望能得到您的理解和支持，下一次在酒馆中再次干杯!\n\n罗杰副官 | D54: Dear Captain,\n\nIn order to increase overall balance in the game, the upcoming 0.26.0 version update will include the following <color=#ffa200>stat adjustments</color>:\n\nxxxxx\n\nWe apologize for the inconvenience and will be issuing the following reward as compensation:\n\nxxxxx\n\nThank you for your understanding and support as we continue to improve. See you around the Tavern!\n\nDeputy Roger | E54: Cher capitaine,\n\nAfin d'équilibrer globalement le jeu, les <color=#ffa200>modifications des statistiques</color> suivantes prendront effet dans la prochaine mise à jour 0.26.0 du jeu:\n\nxxxxx\n\nVeuillez nous excuser pour ce désagrément. Les compensations suivantes vous seront offertes:\n\nxxxxx\n\nMerci pour votre compréhension et votre soutien. Nous mettons tout en œuvre pour continuer à progresser et améliorer le jeu. \n\nOn se retrouve à la taverne!\n\nRoger l'assistant | F54: Lieber Captain,\n\nUm die allgemeine Balance im Spiel zu erhöhen, wird das kommende Versionsupdate 0.26.0 die folgenden <color=#ffa200>Balance-Anpassungen</color> beinhalten:\n\nxxxxx\n\nWir entschuldigen uns für die Unannehmlichkeiten und werden als Entschädigung die folgende Belohnung ausgeben:\n\nxxxxx\n\nVielen Dank für dein Verständnis und deine Unterstützung, während wir uns weiter verbessern. Wir sehen uns in der Taverne!\n\nAdjudant Roger | G54: Caro Capitão,\n\nPara melhorar o balanceamento geral dentro do jogo, a versão 0.26.0 incluirá os seguintes <color=#ffa200>ajustes de atributos</color>:\n\nxxxxx\n\nLamentamos por quaisquer inconveniências e enviaremos a seguinte recompensa para você como compensação:\n\nxxxxx\n\nAgradecemos pela sua compreensão e suporte ao passo que continuamos melhorando. Vemos você na taverna!\n\nDelegado Roger | H54: 親愛的指揮官：\n\n為了確保整體的遊戲平衡，我們在即將更新的0.26.0版本進行了以下<color=#ffa200>數值調整</color>：\n\nxxxxx\n\n\n對於本次調整，我們將會進行以下的補償：\n\nxxxxx\n\n謝謝您對我們的支持，我們將不斷改進，希望能得到您的理解和支持，下一次在酒館中再次乾杯!\n\n羅傑副官 | I54: Kapten yang terhormat,\n\nUntuk meningkatkan keseimbangan keseluruhan dalam game, pembaruan versi 0.26.0 mendatang akan mencakup <color=#ffa200>penyesuaian status</color> berikut ini:\n\nxxxxx\n\nKami mohon maaf atas ketidaknyamanan ini dan akan memberikan hadiah berikut sebagai kompensasi:\n\nxxxxx\n\nTerima kasih atas pengertian dan dukunganmu sementara kami terus meningkatkan game. Sampai jumpa di sekitar Kedai!\n\nDeputi Roger | J54: ถึงท่านผู้บัญชาการ\n\nเพื่อเพิ่มความสมดุลโดยรวมในเกม การอัปเดตเวอร์ชัน 0.26.0 ที่กำลังจะมีขึ้นจะมีการปรับ<color=#ffa200>ค่าพลัง</color>ดังต่อไปนี้:\n\nxxxxx\n\nขออภัยในความไม่สะดวก โดยเราขอมอบรางวัลดังต่อไปนี้ให้เพื่อเป็นการชดเชย:\n\nxxxxx\n\nขอขอบคุณสำหรับความเข้าใจและการสนับสนุนในการปรับปรุงอย่างต่อเนื่องของเรา แล้วไว้เจอกันแถว ๆ โรงแรมนะ!\n\nท่านรองโรเจอร์ | K54: Querido Capitán, \n\nPara poder aumentar el balance en general dentro del juego, la próxima actualización del juego a la versión 0.26.0 incluirá el siguiente <color=#ffa200>ajuste de estadísticas</color>:\n\nxxxxx\n\nNos disculpamos por el inconveniente y estaremos enviando la siguiente recompensa como compensación:\n\nxxxxx\n\nGracias por tu comprensión y apoyo mientras continuamos mejorando. ¡Nos vemos en la Taberna!\n\nComisario Roger | L54: Уважаемый капитан!\n\nВ целях улучшения общего баланса игры мы вносим следующие <color=#ffa200>изменения показателей</color> в обновлении до версии 0.26.0:\n\nxxxxx\n\nПриносим извинения за неудобства и хотим предложить следующую награду в качестве компенсации:\n\nxxxxx\n\nСпасибо за понимание и поддержку наших мер по улучшению игры. Увидимся в таверне!\n\nПомощник Роджер | M54: Sevgili Kaptan,\n\nOyundaki genel dengeyi artırmak için, sunulacak 0.26.0 sürüm güncellemesi şu <color=#ffa200>özellik düzenlemelerini</color> içerecek:\n\nxxxxx\n\nVerdiğimiz sıkıntıdan ötürü özür dileriz, telafi olarak şu ödülü sunacağız:\n\nxxxxx\n\nGelişme sürecimizdeki anlayışın ve desteğin için teşekkürler. Tavernada görüşürüz!\n\nYardımcı Roger | N54: Thưa Thủ Lĩnh,\n\nĐể tăng cân bằng tổng thể trong trò chơi, bản cập nhật phiên bản 0.26.0 sắp tới sẽ bao gồm những <color=#ffa200>điều chỉnh chỉ số</color> sau:\n\nxxxxx\n\nChúng tôi xin lỗi vì các hành động bất tiện này và sẽ trao những phần thưởng sau đây để đền bù:\n\nxxxxx\n\nCảm ơn các bạn đã thông cảm và ủng hộ trong thời gian chúng tôi tiếp tục cải thiện trò chơi. Hẹn gặp lại ở Tửu Quán nhé!\n\nPhụ tá Roger
A55: 活动相关 （持续更新） | B55: 决战卫星之巅开启 | C55: 决战卫星之巅活动已开启 | D55: Astral Coliseum Event Open Now | E55: L'évènement du Colisée astral a commencé | F55: Astral-Kolosseum ist jetzt geöffnet | G55: Coliseu Astral está aberto agora | H55: 決戰衛星之巔活動已開啟 | I55: Acara Koloseum Astral Dibuka Sekarang | J55: กิจกรรมโคลีเซียมดวงดาวพร้อมให้เล่นแล้ว | K55: Evento del Coliseo Astral abierto ahora | L55: Событие в Астральном Колизее открыто | M55: Yıldız Kolezyumu Etkinliği Açıldı | N55: Sự kiện Đại Đấu Trường Thiên Thể hiện đã mở
C56: 亲爱的指挥官：\n\n我们已经开启新的一轮“决战卫星之巅”，本次活动报名时间为<color=#ffa200>2020-12-29 00:00至2021-01-01 00:00 UTC </color>，请抓紧时间报名。\n\n根据热情玩家在社区反馈的问题，我们进行了以下优化：\n\nxxxx\n\n以上就是我们这个版本针对战场做出的所有改动，您还可以点击主界面右上方的活动入口了解具体信息。\n\n我们会继续关注大家的反馈和建议，通过持续优化提升游戏品质，给您带来更好的游戏体验。\n\n欢迎大家通过Discord官方社区或游戏内客服服务和我们积极沟通。\n\n祝愿大家在卫星战场上尽情战斗，赢得奖励与荣耀！\n感谢您对Age of Apes的理解与支持，祝愿火箭发射顺利！\n\n罗杰副官 | D56: Dear Captain,\n\nA new round of Astral Coliseum has begun. The registration period for this round of the event is from<color=#ffa200>2020-12-29 00:00 UTC to 2021-01-01 00:00 UTC</color>. Hurry and register!\n\nBased on the feedback from enthusiastic players in our community, we have made the following optimizations:\n\nxxxxx\n\nThese are all of the changes made to Astral Coliseum in the current version. Tap the event portal in the main interface for more details.\n\nWe will continue to listen to your feedback and keep optimizing to bring you a better gaming experience.\n\nPlease don't hesitate to get in touch with us via Discord or the in-game customer support. [-1#Official Discord](herf=https://discord.gg/RncnPNw)\n\nFight to the end, monkeys! Rewards and honor shall be yours!\n\nThank you for your understanding and support. See you around the Tavern!\n\nDeputy Roger | E56: Cher capitaine,\n\nUne nouvelle manche du Colisée astral a commencé. Les inscriptions sont ouvertes du <color=#ffa200>29-12-2020 à 00:00 TU au 01-01-2021 à 00:00 TU</color>. Dépêchez-vous de vous inscrire!\n\nGrâce aux commentaires enthousiastes des joueurs, nous avons amélioré certains aspects de l’évènement:\n\nxxxxx\n\nVoilà les changements apportés à cette nouvelle version du Colisée astral. Pour en savoir plus, appuyez sur l’icône de l’évènement dans l’interface principale.\n\nNous continuons de lire tous vos retours et d'optimiser encore le jeu afin de vous offrir la meilleure expérience possible.\n\nNous vous invitons à nous faire part de toutes vos remarques via Discord ou via le service client en jeu. [-1#Official Discord](herf=https://discord.gg/RncnPNw)\n\nNe cessez jamais de vous battre, primate! Vous obtiendrez la gloire et les récompenses que vous méritez!\n\nMerci pour votre compréhension et votre soutien. On se retrouve à la taverne!\n\nRoger l'assistant | F56: Lieber Captain,\n\nEine neue Runde des Astral-Kolosseums hat begonnen. Der Anmeldezeitraum für diese Runde des Events ist von <color=#ffa200>29.12.2020 00:00 UTC bis 01.01.2021 00:00 UTC</color>. Also melde dich schnell an!\nBasierend auf dem Feedback von begeisterten Spielern aus unserer Community haben wir folgende Optimierungen vorgenommen:\n\nxxxxx\n\nDas sind alle Änderungen, die in der aktuellen Version am Astral-Kolosseum vorgenommen wurden. Tippe auf das Event-Portal im Haupt-Interface für weitere Details.\n\nWir werden weiterhin auf euer Feedback hören und Optimierungen vornehmen, um euch ein besseres Spielerlebnis zu bieten.\n\nBitte zögere nicht, mit uns über Discord oder den Ingame-Kundensupport in Kontakt zu treten. [-1#Offizieller Discord](herf=https://discord.gg/RncnPNw)\n\nKämpft bis zum Ende, meine Affen! Belohnungen und Ehre sollen euch gehören!\n\nVielen Dank für dein Verständnis und deine Unterstützung. Wir sehen uns in der Taverne!\n\nAdjudant Roger | G56: Caro Capitão,\n\nUma nova rodada do Coliseu Astral começou. O período para fazer o registro para esta rodada do evento começa vai <color=#ffa200>da meia-noite de 29/12/2020 à meia-noite de 01/01/2021 (ambos em fusos UTC)</color>. Faça o registro agora!\n\nCom base no feedback que recebemos dos jogadores de nossa comunidade, fizemos as seguintes melhorias:\n\nxxxxx\n\nEssas são as melhorias que fizemos no Coliseu Astral para a versão atual. Toque no portal do evento na interface principal para detalhes adicionais.\n\nContinuaremos a ouvir seu feedback, mantendo assim a experiência de jogo otimizada.\n\nNão deixe de entrar em contato conosco no Discord ou no suporte ao cliente dentro do jogo. [-1#Discord Oficial](herf=https://discord.gg/RncnPNw)\n\nMacacos, lutem até o fim! As honras e recompensas serão todas suas!\n\nNossa equipe agradece seu apoio e compreensão. Vemos você na taverna!\n\nDelegado Roger | H56: 親愛的指揮官：\n\n我們已經開啟新的一輪“決戰衛星之巔”，本次活動報名時間為<color=#ffa200>2020-12-29 00:00至2021-01-01 00:00 UTC </color>，請抓緊時間報名。\n\n根據熱情玩家在社區反饋的問題，我們進行了以下優化：\n\nxxxx\n\n以上就是我們這個版本針對戰場做出的所有改動，您還可以點擊主界面右上方的活動入口了解具體信息。\n\n我們會繼續關注大家的反饋和建議，通過持續優化提升遊戲品質，給您帶來更好的遊戲體驗。\n\n歡迎大家通過Discord官方社區或遊戲內客服服務和我們積極溝通。\n\n祝愿大家在衛星戰場上盡情戰鬥，贏得獎勵與榮耀！\n感謝您對Age of Apes的理解與支持，祝愿火箭發射順利！\n\n羅傑副官 | I56: Kapten yang terhormat,\n\nBabak baru Koloseum Astral telah dimulai. Periode pendaftaran untuk babak acara ini adalah mulai dari<color=#ffa200>2020-12-29 00:00 UTC hingga 2021-01-01 00:00 UTC</color>. Segera daftar!\n\nBerdasarkan umpan balik dari para pemain yang antusias di komunitas, kami telah melakukan pengoptimalan berikut:\n\nxxxxx\n\nIni semua adalah perubahan yang dilakukan pada Koloseum Astral di versi terbaru. Ketuk portal acara di antarmuka utama untuk lebih jelasnya.\n\nKami akan terus mendengarkan umpan balikmu dan terus mengoptimalkan untuk memberimu pengalaman bermain yang lebih baik.\n\nJangan ragu untuk menghubungi kami melalui Discord atau dukungan pelanggan dalam game. [-1#Official Discord](herf=https://discord.gg/RncnPNw)\n\nBerjuang hingga akhir, kera! Hadiah dan Kehormatan akan menjadi milikmu!\n\nTerima kasih atas pengertian dan dukunganmu. Sampai Jumpa di Sekitar Kedai!\n\nDeputi Roger | J56: ถึงท่านผู้บัญชาการ\n\nโคลีเซียมดวงดาวรอบใหม่เริ่มขึ้นแล้ว ระยะเวลาการลงทะเบียนสำหรับกิจกรรมรอบนี้คือตั้งแต่วันที่<color=#ffa200> 19-12-2020 00:00 UTC ถึง 01-01-2021 00:00 UTC</color> นายรีบไปลงทะเบียนโดยด่วนเลยนะ!\n\nจากข้อเสนอแนะจากผู้เล่นสุดกระตือรือร้นในชุมชนของเรา เราจึงได้ทำการเพิ่มประสิทธิภาพดังต่อไปนี้:\n\nxxxxx\n\nนี่คือการเปลี่ยนแปลงทั้งหมดที่เกิดขึ้นกับโคลีเซียมดวงดาวในเวอร์ชันปัจจุบัน แตะที่พอร์ทัลเหตุการณ์ในอินเทอร์เฟสหลักเพื่อดูรายละเอียดเพิ่มเติม\n\nเรายินดีรับฟังความคิดเห็นของนายเสมอและทำการปรับปรุงอย่างต่อเนื่องเพื่อนำเสนอประสบการณ์การเล่นเกมที่ดียิ่ง ๆ ขึ้นไป\n\nโปรดอย่าลังเลที่จะติดต่อเราผ่านทาง Discord หรือฝ่ายสนับสนุนลูกค้าในเกม [-1#Official Discord](herf=https://discord.gg/RncnPNw)\n\nสู้ให้สุดนะ เจ้าลิง! แล้วรางวัลและเกียรติยศทั้งปวงจะเป็นของนาย!\n\nขอขอบคุณสำหรับความเข้าใจและการสนับสนุนของนาย แล้วไว้เจอกันแถว ๆ โรงแรมนะ!\n\nท่านรองโรเจอร์ | K56: Querido Capitán,\n\nUna nueva partida del Coliseo Astral ha comenzado. El periodo de registro para esta partida del evento es del<color=#ffa200>29-12-2929 00:00 UTC al 01-01-2021 00:00 UTC</color>.\n\nBasándonos en los comentarios de los entusiastas jugadores en nuestra comunidad, hemos realizado las siguientes optimizaciones: \n\nXxxxx\n\nEstos son todos los cambios realizados al Coliseo Astral en su versión actual. Toca en el portal del evento en la interface principal para más detalles. \n\nContinuaremos escuchando tus comentarios y optimizando para traerte una mejor experiencia de juego. \n\nPor favor, no dudes en ponerte en contacto con nosotros mediante Discord o a través del soporte al cliente del juego. [-1#Discord Oficial](herf=https://discord.gg/RncnPNw)\n\n¡Luchen hasta el final monos! ¡Las recompensas y el honor serán suyos!\n\n\nGracias por tu comprensión y apoyo. ¡Nos vemos en la Taberna!\n\nComisario Roger | L56: Уважаемый капитан!\n\nНачался новый раунд «Астрального Колизея». Период регистрации для этого раунда: <color=#ffa200>00:00 29.12.2020 — 00:00 01.01.2021 (UTC)</color>. Спешите регистрироваться!\n\nПрочитав отзывы энтузиастов нашего сообщества, мы внесли в игру следующие улучшения:\n\nxxxxx\n\nЭто все изменения, которые мы внесли в «Астральный Колизей» в текущей версии. Нажмите на портал событий в главном интерфейсе для получения подробной информации.\n\nМы продолжим изучать ваши отзывы и оптимизировать качество игры, чтобы оставить у вас наилучшие впечатления.\n\nВы в любой момент можете написать нам в Discord или в игровую службу поддержки. [-1#Сервер Discord](herf=https://discord.gg/RncnPNw).\n\nСражайтесь до конца, приматы! Вас ждут награды и слава!\n\nСпасибо за понимание и поддержку. Увидимся в таверне!\n\nПомощник Роджер | M56: Sevgili Kaptan,\n\nYeni bir Yıldız Kolezyumu raundu başladı. Etkinliğin bu raundunun kayıt dönemi <color=#ffa200>29.12.2020 00.00 - 01.01.2021 00.00 (UTC)</color> arası. Acele et ve kaydol!\n\nTopluluğumuzdaki heyecan dolu oyuncuların geri bildirimleriyle şu optimizasyonları yaptık:\n\nxxxxx\n\nMevcut sürümdeki tüm Yıldız Kolezyumu değişiklikleri bunlar. Daha fazla bilgi için ana arayüzdeki etkinlik portalına dokun.\n\nGeri bildirimlerini dinlemeye ve sana daha iyi bir deneyim sunmak adına optimize etmeye devam edeceğiz.\n\nDiscord üzerinden veya oyun içi müşteri desteğinden bize ulaşabilirsin. [-1#Resmî Discord](herf=https://discord.gg/RncnPNw)\n\nMaymunlar, sonuna kadar savaşın! Ödüller ve onur senin olsun!\n\nAnlayışın ve desteğin için teşekkürler. Tavernada görüşürüz!\n\nYardımcı Roger | N56: Thưa Thủ Lĩnh,\n\nVòng đấu mới của Đại Đấu Trường Thiên Thể đã bắt đầu. Thời gian đăng ký cho vòng sự kiện này từ<color=#ffa200>00:00 UTC ngày 19/12/2020 đến 00:00 UTC ngày 01/01/2021</color>. Hãy nhanh tay đăng ký!\n\nDựa trên phản hồi từ những người chơi nhiệt tình trong cộng đồng, chúng tôi đã thực hiện các tối ưu hóa sau:\n\nxxxxx\n\nĐây là tất cả những thay đổi của Đại Đấu Trường Thiên Thể trong phiên bản hiện tại. Hãy nhấn vào cổng sự kiện trong giao diện chính để biết thêm chi tiết.\n\nChúng tôi sẽ tiếp tục lắng nghe phản hồi của bạn để tiếp tục tối ưu hóa và mang lại cho bạn trải nghiệm chơi game tốt hơn.\n\nVui lòng liên hệ với chúng tôi qua Discord hoặc bộ phận hỗ trợ khách hàng trong trò chơi. [-1# Discord chính thức](herf=https://discord.gg/RncnPNw)\n\nHãy chiến đấu đến khoảnh khắc cuối cùng, các đồng chí khỉ! Phần thưởng và danh dự sẽ thuộc về bạn!\n\nCảm ơn bạn đã thông cảm và hỗ trợ. Hẹn gặp lại ở Tửu Quán nhé!\n\nPhụ tá Roger
B57: 狂飙拉力赛任务无法完成问题已解决 | C57: 狂飙拉力赛任务无法完成问题已解决 | D57: Cyclone Rally Quest Issue Fixed | H57: 狂飆拉力賽任務無法完成問題已解決
C58: 亲爱的指挥官： 由于罗杰不小心弄乱了文件，您可能会遇到无法完成狂飙拉力赛部分任务的问题，我们已经修复了该问题，特此为您送上一份补偿： 谢谢您对我们的支持，我们将不断改进，希望能得到您的理解和支持，下一次在酒馆中再次干杯! | D58: Dear Captain, Roger messed up the files so you may have encountered a problem completing certain Cyclone Rally quests. This issue has already been fixed. We apologize for the inconvenience and offer this small reward as compensation: Thank you for your understanding and support as we continue to improve. See you around the Tavern! | H58: 親愛的指揮官： 由於羅傑不小心弄亂了文件，您可能會遇到無法完成狂飆拉力賽部分任務的問題，我們已經修復了該問題，特此為您送上一份補償： 謝謝您對我們的支持，我們將不斷改進，希望能得到您的理解和支持，下一次在酒館中再次乾杯!
B59: 怒气值异常问题修复 | C59: 怒气值异常问题修复 | D59: Rage Issue Fixed | H59: 怒氣值異常問題修復 | L59: Исправлена проблема с яростью
C60: 亲爱的指挥官： 由于城市电路故障，您在战斗中可能会出现<color=#ffa200>怒气值异常</color>等情况，目前我们<color=#ffa200>已修复</color>电路。 为您带来不便深感歉意，在此为您送上一份补偿，请注意查收。 感谢您对Age of Apes的理解与支持，祝愿火箭发射顺利！ 您的基地顾问罗杰 | D60: Dear Captain, Due to circuit malfunctions, you may have experienced <color=#ffa200>Rage stat errors</color> in battle. We have already <color=#ffa200>fixed</color> this issue. We apologize for the inconvenience and have included a small gift for you as compensation. Thank you for your understanding and support. See you around the Tavern! Your trusty helper, Roger | H60: 親愛的指揮官： 由於城市電路故障，您在戰鬥中可能會出現<color=#ffa200>怒氣值異常</color>等情況，目前我們<color=#ffa200>已修復</color>電路。 為您帶來不便深感歉意，在此為您送上一份補償，請注意查收。 感謝您對Age of Apes的理解與支持，祝愿火箭發射順利！ 您的基地顧問羅傑 | L60: Уважаемый капитан! Из-за сбоев в работе микросхем вы могли столкнуться с <color=#ffa200>проблемой учета ярости</color> в бою. Мы уже <color=#ffa200>исправили</color> эту неполадку. Приносим извинения за неудобства и отправляем вам небольшой подарок в качестве компенсации! Спасибо за понимание и поддержку. Увидимся в таверне! Ваш верный помощник, Роджер
B61: 决战卫星之巅奖励丢失 | C61: 奖励异常补偿 | D61: Reward Error Compensation | H61: 獎勵異常補償
C62: 亲爱的指挥官： 由于城市里混乱的道路，您没能收到本次决战卫星之巅中匹配失败的奖励。\n我们的团队已经解决了这个问题，这是您应得的奖励！\n我们对您遇到的麻烦深表歉意。感谢您对Age of Apes的理解和支持。祝您畅饮所有香蕉冰沙! | D62: Dear Captain, Due to circuit malfunctions, you did not receive the match failure reward for this Astral Coliseum. \nWe have resolved this issue and have included the reward that is due to you. \nWe sincerely apologize for the inconvenience. Thank you for your understanding and support! See you around the Tavern! | H62: 親愛的指揮官： 由於城市裡混亂的道路，您沒能收到本次決戰衛星之巔中匹配失敗的獎勵。 \n我們的團隊已經解決了這個問題，這是您應得的獎勵！ \n我們對您遇到的麻煩深表歉意。感謝您對Age of Apes的理解和支持。祝您暢飲所有香蕉冰沙!
B63: 决战卫星之巅时间调整 | C63: 决战卫星之巅时间调整 | D63: Astral Coliseum Date Change | H63: 決戰衛星之巔時間調整
C64: 亲爱的指挥官：\n\n为了能让更多玩家参与决战卫星之巅活动，我们将本期决战卫星之巅的战斗时间调整到了<color=#ffa200>2021-05-07</color>，请猴子们做好准备迎接战斗！\n\n本次时间调整是我们为猴子们提供更好游戏体验的尝试，<color=#ffa200>仅本次有效</color>，之后的决战卫星之巅战斗时间以活动说明为准。\n\n请大家在卫星战场上尽情战斗，赢得奖励与荣耀！\n\n您的基地顾问罗杰 | D64: Dear Captain,\n\nIn order to allow more players to participate in Astral Coliseum, battles for the current Astral Coliseum event will now take place on <color=#ffa200>2021-05-07</color>. Please prepare accordingly!\n\nThis date change was made to provide you with a better gaming experience, and it is <color=#ffa200>only valid for this event</color>. Please refer to specific event announcements for future Astral Coliseum battle dates.\n\nFight to the end, monkeys! Rewards and honor shall be yours!\n\nDeputy Roger | H64: 親愛的指揮官：\n\n為了能讓更多玩家參與決戰衛星之巔活動，我們將本期決戰衛星之巔的戰鬥時間調整到了<color=#ffa200>2021-05-07</color>，請猴子們做好準備迎接戰鬥！ \n\n本次時間調整是我們為猴子們提供更好遊戲體驗的嘗試，<color=#ffa200>僅本次有效</color>，之後的決戰衛星之巔戰鬥時間以活動說明為準。 \n\n請大家在衛星戰場上盡情戰鬥，贏得獎勵與榮耀！ \n\n您的基地顧問羅傑
B65: 地图改动补偿 | C65: 地图改动补偿 | D65: Map Change Compensation | E65: Dédommagement pour modification de la carte | F65: Entschädigung für Änderungen an der Karte | G65: Compensação pela Mudança de Mapa | H65: 地圖改動補償 | I65: Kompensasi Perubahan Peta | J65: การชดเชยการเปลี่ยนแปลงแผนที่ | K65: Compensación por cambio de mapa | L65: Компенсация за изменение карты | M65: Harita Değişikliği Telafisi | N65: Đền Bù Thay Đổi Bản Đồ
C66: 亲爱的指挥官：\n我们在最近的更新中修改了地图，这可能导致您丢失某些占领的地图单位、修建的帮派建筑，或基地被移动。\n以下是给您的补偿，请收下。 | D66: Dear Captain, \nWe made changes to the map in the most recent game update. This may have caused you to lose certain occupied map units or Gang buildings, or to have your City moved. \nWe have included a reward for you as compensation. Thank you for your understanding and support. | E66: Capitaine,\nNous avons modifié la carte lors de la dernière mise à jour du jeu. En raison de ces changements, vous avez peut-être perdu des unités, des bâtiments de gang, ou votre ville a été déplacée.\nVoici un cadeau en dédommagement. Merci pour votre compréhension et votre soutien. | F66: Hallo Captain, \nWir haben mit dem letzten Spielupdate Änderungen an der Karte vorgenommen. Dies kann dazu geführt haben, dass du bestimmte besetzte Karteneinheiten oder Clan-Gebäude verloren hast oder dass deine Stadt versetzt wurde. \nWir haben als Entschädigung eine Belohnung für dich beigefügt. Vielen Dank für dein Verständnis und deine Unterstützung. | G66: Caro Capitão, \nFizemos algumas mudanças no mapa na atualização mais recente do jogo. Isso pode ter feito você perder algumas unidades no mapa ocupado, estruturas da gangue ou sua cidade mudou de lugar. \nIncluímos uma recompensa para você como compensação. Nossa equipe agradece seu apoio e compreensão. | H66: 親愛的指揮官：\n我們在最近的更新中修改了地圖，這可能導致您丟失某些佔領的地圖單位、修建的幫派建築，或基地被移動。 \n以下是給您的補償，請收下。 | I66: Kapten yang terhormat, \nKami membuat perubahan pada peta di pembaruan game terkini. Ini mungkin akan mengakibatkanmu kehilangan unit peta atau bangunan Geng tertentu yang diduduki, atau memindahkan Kotamu. \nKami telah menyertakan hadiah untukmu sebagai kompensasi. Terima kasih atas pengertian dan dukunganmu. | J66: ถึงกัปตัน\nเราได้ทำการเปลี่ยนแปลงแผนที่ในการอัปเดตเกมล่าสุด ซึ่งอาจทำให้คุณสูญเสียหน่วยทหารที่ทำการครอบครองอยู่บนแผนที่หรือสิ่งปลูกสร้างของแก๊ง หรือเมืองของคุณอาจถูกย้ายตำแหน่ง\nเราจึงขอส่งรางวัลนี้มาให้คุณแทนคำขออภัย ขอขอบคุณสำหรับความเข้าใจและการสนับสนุนของคุณ | K66: Querido Capitán: \nHemos realizado cambios en el mapa durante la más reciente actualización del juego. Esto puede haber provocado que perdieras algunas unidades de mapa ocupadas o edificios de la Banda, o, que tu Ciudad se haya movido de lugar. \nHemos incluido una recompensa para ti como compensación. Gracias por tu comprensión y apoyo. | L66: Уважаемый капитан! \nВ последнем обновлении игры мы внесли изменения в карту. Это могло привести к потерям тех или иных оккупированных построек на карте или зданий банды, а также к перемещению вашего города. \nВ качестве компенсации мы отправляем вам эту награду. Спасибо за понимание и поддержку. | M66: Sevgili Kaptan, \nEn son oyun güncellemesinde haritada değişiklikler yaptık. Bu işgal edilen belirli harita birimlerini veya Çete binalarını kaybetmene veya Şehrinin taşınmasına neden olabilir. \nTelafi olarak senin için bir ödül ekledik. Anlayışın ve desteğin için teşekkürler. | N66: Thưa Thủ Lĩnh, \nChúng tôi đã thực hiện một số thay đổi về bản đồ trong bản cập nhật trò chơi gần đây nhất. Việc này có thể khiến bạn bị mất các đơn vị bản đồ hoặc các công trình Bang Hội đã chiếm đóng, hoặc Thành Phố của bạn bị di chuyển. \nChúng tôi đã đính kèm một phần thưởng để bù đắp cho bạn. Cảm ơn bạn đã thông cảm và ủng hộ chúng tôi.
B67: 新版本问题修复 | C67: 新版本问题已修复 | D67: New Version Fixes | E67: Corrections de la nouvelle version | F67: Neue Versionskorrekturen | G67: Novos ajustes de versão | H67: 新版本問題已修復 | I67: Perbaikan Versi Baru | J67: การแก้ไขในเวอร์ชันใหม่ | K67: Nuevas correcciones de versión | L67: Исправления в новой версии | M67: Yeni Sürüm Düzeltmeleri | N67: Đã sửa lỗi phiên bản mới
C68: 亲爱的指挥官： 0.30.0版本更新后我们收到了很多反馈意见，根据反馈意见我们已针对以下内容<color=#ffa200>进行了修复</color>： xxx 为您带来不便深感歉意，在此为您送上一份补偿。 我们将不断改进，希望能得到你的理解与支持，祝愿火箭发射顺利！ 罗杰副官 | D68: Dear Captain, We have received your feedback after the version 0.30.0 update. Based on your suggestions, we have <color=#ffa200>implemented fixes</color> for the following issues: xxx We apologize for the inconvenience and have included a small gift for you as compensation. Thank you for your understanding and support as we continue to improve. See you around the Tavern! Deputy Roger | E68: Capitaine, Nous avons reçu des retours concernant la nouvelle version 0.30.0. Grâce à vos commentaires, nous avons <color=#ffa200>corrigé les problèmes</color> suivants: xxx Nous vous prions de nous excuser pour la gêne occasionnée, et vous offrons un petit cadeau en dédommagement. Merci pour votre compréhension et votre soutien sans faille. A bientôt à la taverne! Votre assistant, Roger | F68: Lieber Captain, Wir haben dein Feedback nach dem Versionsupdate 0.30.0 erhalten. Aufgrund deiner Vorschläge haben wir für folgende Probleme <color=#ffa200>Korrekturen implementiert</color>: xxx Wir bitten, mögliche Unannehmlichkeiten zu entschuldigen, und haben ein kleines Geschenk als Kompensation beigefügt. Danke für dein Verständnis und deine Unterstützung, während wir ständig an Verbesserungen arbeiten! Wir sehen uns in der Taverne! Adjutant Roger | G68: Caro Capitão, Recebemos seu feedback após a atualização da versão 0.30.0. Com base nas suas sugestões, <color=#ffa200>implementamos melhorias</color> nos seguintes problemas: xxx Lamentamos pela inconveniência e incluímos um brinde para você como compensação. Nossa equipe agradece sua compreensão e apoio ao passo que continuamos melhorando. Vemos você na taverna! Delegado Roger | H68: 親愛的指揮官： 0.30.0版本更新後我們收到了很多反饋意見，根據反饋意見我們已針對以下內容<color=#ffa200>進行了修復</color>： xxx 為您帶來不便深感歉意，在此為您送上一份補償。 我們將不斷改進，希望能得到你的理解與支持，祝愿火箭發射順利！ 羅傑副官 | I68: Kapten yang terhormat, Kami telah menerima tanggapanmu setelah pembaruan versi 0.30.0. Berdasarkan saranmu, kami telah <color=#ffa200>mengimplementasikan perbaikan</color> untuk masalah berikut: xxx Maaf atas ketidaknyamanan ini dan kami telah menyertakan hadiah kecil untukmu sebagai kompensasi. Terima kasih atas pengertian dan dukunganmu sementara kami terus meningkatkan game. Sampai jumpa di Kedai! Deputi Roger | J68: ถึงกัปตัน เราได้รับข้อเสนอแนะของคุณหลังจากอัปเดตเวอร์ชัน 0.30.0 แล้ว จากคำแนะนำของคุณ เราจึง<color=#ffa200>ทำการแก้ไข</color>ปัญหาต่อไปนี้: xxx เราขออภัยในความไม่สะดวกและขอมอบของขวัญเล็ก ๆ น้อย ๆ ไว้แทนคำขออภัย ขอขอบคุณสำหรับความเข้าใจและการสนับสนุนของคุณในขณะที่เราทำการปรับปรุงอย่างต่อเนื่อง ไว้เจอกันแถว ๆ โรงแรมนะ! รองโรเจอร์ | K68: Querido Capitán: Hemos recibido tus comentarios después de la actualización 0.30.0. De acuerdo a tus sugerencias hemos <color=#ffa200>implementado correcciones</color> para los siguientes problemas: xxx Nos disculpamos por los inconvenientes y hemos incluido un pequeño regalo para ti como compensación. Gracias por tu comprensión y apoyo mientras continuamos mejorando. ¡Nos vemos en la Taberna! Comisario Roger | L68: Уважаемый капитан! Мы получили ваши отзывы после обновления до версии 0.30.0. Основываясь на ваших предложениях, мы <color=#ffa200>внесли исправления</color> для следующих проблем: xxx Приносим извинения за доставленные неудобства и в качестве компенсации отправляем вам небольшой подарок. Спасибо за понимание и поддержку наших мер по улучшению игры. Увидимся в таверне! Помощник Роджер | M68: Sevgili Kaptan, 0.30.0 güncellemesinin ardından geri bildirimlerini aldık. Tavsiyelerin doğrultusunda şu konulara yönelik <color=#ffa200>düzeltmeler uyguladık</color>: xxx Verdiğimiz sıkıntıdan ötürü özür dileriz, bunun telafisi olarak sana küçük bir hediye sunuyoruz. Gelişme sürecimizdeki anlayışın ve desteğin için teşekkürler. Tavernada görüşürüz! Yardımcın Roger | N68: Thưa Thủ Lĩnh, Chúng tôi đã nhận được phản hồi của bạn về bản cập nhật phiên bản 0.30.0. Dựa trên đề xuất của bạn, chúng tôi đã <color=#ffa200>thực hiện sửa</color> những vấn đề sau: xxx Chúng tôi chân thành xin lỗi và xin đính kèm một phần quà nhỏ để bù đắp cho bạn. Cảm ơn các bạn đã thấu hiểu và hỗ trợ chúng tôi tiếp tục cải thiện. Hẹn gặp lại ở Tửu Quán nhé! Thay mặt Roger
B69: 活动异常下线 | C69: 活动下线通知 亲爱的指挥官：\n\n你好，由于城市电路发生故障，<color=#ffa200>一网打尽</color>活动需要<color=#ffa200>临时下线进行调整</color>，调整结束后将再次上线。\n为你带来不便深感歉意，在此为你送上一份补偿，请注意查收。\n我们将不断改进，希望能得到你的理解与支持，祝愿火箭发射顺利！\n\n罗杰副官 | D69: Event Offline Dear Captain,\n\nDue to circuit malfunctions, the <color=#ffa200>One Fell Swoop</color> event has been <color=#ffa200>taken offline for emergency adjustments</color>. It will be re-launched once adjustments have been made.\n\nWe apologize for the inconvenience and have included a small gift for you as compensation.\n\nThank you for your understanding and support as we continue to improve. See you around the Tavern!\n\nDeputy Roger
B70: 圣诞节邮件 | C70: 圣诞节赠礼！
B71: 圣诞节邮件 | C71: 亲爱的指挥官： 猿猴世界迎来了一年一度的圣诞节，惊喜圣诞夜、圣诞晚会活动也在持续进行，为了庆祝圣诞，特此为您送上一份奖励： 谢谢您对我们的支持，我们将不断改进，希望能得到您的理解和支持，下一次在酒馆中再次干杯!
B72: 问卷公告 | C72: 来自前线的信 | D72: LETTER FROM THE FRONT | E72: LETTRE DU FRONT | F72: BRIEF VON DER FRONT | G72: CARTA DO FRONTE | H72: 來自前線的信 | I72: SURAT DARI BARIS DEPAN | J72: จดหมายจากด่านหน้า | K72: CARTAS DESDE EL FRENTE | L72: ПИСЬМО С ФРОНТА | M72: CEPHEDEN MEKTUP | N72: THƯ TỪ TIỀN TUYẾN
C73: 1. 在<color=#ffa200>2022-01-21 00:00 UTC</color>之前完成问卷，您将获得<color=#ffa200>200CD</color>奖励；\n2. 奖励将会在完成问卷后发放；\n3. 每位玩家只能获得一次奖励；\n4. 您填写的内容我们仅供内部分析使用； | D73: 1. Complete the survey before <color=#ffa200>2022-01-21 00:00 UTC</color> to receive <color=#ffa200>200 CDs</color>.\n2. The reward will be issued after you've completed the survey. \n3. Each player can only get the reward once. \n4. Your survey answers are for internal analysis only. | E73: 1. Répondez à l'enquête avant le <color=#ffa200>21/01/2022 à 00:00 (TU)</color> pour recevoir <color=#ffa200>200 CD</color>.\n2. La récompense vous sera versée quand vous aurez répondu à l'enquête.\n3. Les joueurs ne peuvent recevoir cette récompense qu'une seule fois.\n4. Vos réponses sont utilisées à des fins d'analyse en interne uniquement. | F73: 1. Schließe die Umfrage vor <color=#ffa200>00:00 UTC am 21.1.2022</color> ab, um <color=#ffa200>200 CDs</color> zu erhalten.\n2. Die Belohnung wird nach Abschluss der Umfrage vergeben.\n3. Jeder Spieler kann diese Belohnung nur jeweils einmal erhalten.\n4. Deine Antworten auf die Umfrage werden nur für interne Analysen benutzt. | G73: 1. Conclua a pesquisa antes de <color=#ffa200>21/01/2022, meia-noite UTC</color>, para receber <color=#ffa200>200 CDs</color>.\n2. A recompensa serão enviada após a conclusão da pesquisa. \n3. Cada jogador só pode conseguir a recompensa uma vez. \n4. Suas respostas serão usadas somente para análise interna de nossa equipe. | H73: 1. 在<color=#ffa200>2022-01-21 00:00 UTC</color>之前完成問卷，您將獲得<color=#ffa200>200CD</color>獎勵；\n2. 獎勵將會在完成問卷後發放；\n3. 每位玩家只能獲得一次獎勵；\n4. 您填寫的內容我們僅供內部分析使用； | I73: 1. Selesaikan survei sebelum <color=#ffa200>21-01-2022 00:00 UTC</color> untuk mendapat <color=#ffa200>200 CD</color>.\n2. Hadiah akan diberikan setelah kamu menyelesaikan survei. \n3. Setiap pemain hanya dapat menerima hadiah sekali. \n4. Jawaban surveimu hanya untuk analisis internal. | J73: 1. ทำแบบสำรวจให้เสร็จก่อนวันที่ <color=#ffa200>21-01-2022 00:00 UTC</color> เพื่อรับ<color=#ffa200>ซีดี 200 แผ่น</color>\n2. ระบบจะมอบรางวัลนี้ให้หลังจากที่คุณทำแบบสำรวจเสร็จแล้ว\n3. ผู้เล่นแต่ละคนสามารถรับรางวัลนี้ได้เพียงครั้งเดียว\n4. คำตอบแบบสำรวจของคุณมีไว้สำหรับการวิเคราะห์ภายในเท่านั้น | K73: 1. Completa la encuesta antes del <color=#ffa200>21-01-2022 00:00 UTC</color> para recibir <color=#ffa200>200 CD</color>.\n2. La recompensa se emitirá después de que hayas completado la encuesta.\n3. Cada jugador solo puede obtener la recompensa una vez.\n4. Las respuestas de tu encuesta son únicamente para análisis interno. | L73: 1. Пройдите опрос до <color=#ffa200>00:00 UTC 21.01.2022</color>, чтобы получить <color=#ffa200>200 CD</color>.\n2. Эта награда выдается, когда вы заканчиваете проходить опрос.\n3. Каждый игрок может получить награду только один раз.\n4. Ваши ответы на вопросы предназначены только для внутреннего анализа. | M73: 1. Anketi <color=#ffa200>21.01.2022 00.00’dan (UTC)</color> önce tamamla ve <color=#ffa200>200 CD</color> kazan.\n2. Bu ödül, anketi tamamlamanın ardından verilir. \n3. Her oyuncu ödülü sadece bir kez alabilir. \n4. Anket cevapların sadece dâhilî analiz için kullanılacak. | N73: 1. Hãy hoàn thành khảo sát trước <color=#ffa200>00:00 ngày 21/01/2022 (giờ UTC)</color> để nhận <color=#ffa200>200 CD</color>.\n2. Phần thưởng này sẽ được phát sau khi bạn làm xong khảo sát. \n3. Mỗi người chơi chỉ có thể nhận phần thưởng này một lần. \n4. Những câu trả lời của bạn trong khảo sát chỉ được sử dụng trong phân tích nội bộ.
C74: 奖励补偿发放 | D74: Reward Re-Send
B75: 地图数据异常 | C75: 亲爱的指挥官：\n由于游戏内数据异常，这可能导致您丢失某些占领的地图单位、修建的帮派建筑，或基地被移动。\n以下是给您的补偿，请收下。 | D75: Dear Captain, \nDue to data abnormalities, this may have caused you to lose certain occupied map units or Gang buildings, or to have your City moved. \nWe have included a reward for you as compensation. Thank you for your understanding and support.
C76: 掉落错误问题说明 | D76: Drop rewards Error
B77: 掉落错误问题说明 | C77: 亲爱的指挥官：\n\n由于数据异常，钻探机器人掉落奖励错误，我们<color=#ffa200>正在紧急修复</color>。\n为您带来不便深感歉意，在此为您送上一份补偿，请注意查收。\n感谢您对Age of Apes的理解与支持，祝愿火箭发射顺利！\n\n罗杰副官 | D77: Dear Captain, Due to data errors, the drop rewards for Drill Bots were incorrectly configured. We are working hard to fix these issues as quickly as possible.We apologize for the inconvenience and have included a small gift for you as compensation. Thank you for your understanding and support. See you around the Tavern! Deputy Roger
C78: 谷歌充值已修复 | D78: Google Pay Fixed
B79: 谷歌支付失败问题说明 | C79: 亲爱的指挥官：\n\n由于谷歌支付出现故障，使用谷歌支付的玩家可能会出现<color=#ffa200>充值异常</color>的情况，谷歌<color=#ffa200>已经修复，支付恢复正常</color>。\n为您带来不便深感歉意。\n感谢您对Age of Apes的理解与支持，祝愿火箭发射顺利！\n\n罗杰副官 | D79: Dear Captain, \n\nDue to an issue with Google Pay, you may have experienced <color=#ffa200>payment errors</color> when using this payment method. Google <color=#ffa200>has fixed this issue and payments can be processed as normal</color>. \n\nWe sincerely apologize for any inconvenience. Thank you for your understanding and support, see you around the Tavern!\n\nDeputy Roger
C80: 万圣节活动合服公告
C81: 亲爱的指挥官：\n\n以下是你的合服补偿，请注意查收。\n\n感谢您对Age of Apes的理解与支持，祝愿火箭发射顺利！\n\n罗杰副官
B82: 服务器无法登录补偿 | C82: 服务器登录问题补偿 | D82: Login Error Compensation
C83: 亲爱的指挥官：\n\n由于服务器波动异常，导致您所在地区出现<color=#ffa200>无法正常登录游戏</color>的情况，目前服务器异常问题已<color=#ffa200>成功修复</color>。在此为您送上一份补偿，请注意查收。\n\n感谢您对Age of Apes的理解与支持，祝愿火箭发射顺利！\n\n罗杰副官 | D83: Dear Captain, \n\nDue to server issues, players in your region encountered an <color=#ffa200>error when trying to log into the game</color>. This issue has now been <color=#ffa200>fixed</color>. \n\nWe sincerely apologize for the inconvenience and have included a small gift for you as compensation.\n\nThank you for your continued understanding and support. See you around the Tavern!\n\nDeputy Roger
B84: 万圣节活动合服补偿 | C84: 万圣节活动合服补偿
C85: 亲爱的指挥官： 由于合服，万圣节相关活动提前关闭，现在惊喜狂欢夜已经重新开启，在所有开启的惊喜狂欢夜活动中（包括本次及上次）只要消耗超过60张南瓜奖券（包括60张）且未获得过南瓜古堡（永久），我们会在2022年11月3日前通过邮件单独给您进行南瓜古堡的发放。 如有疑惑，欢迎大家通过Discord官方社区或游戏内客服服务和我们积极沟通。 以下是你的万圣节合服补偿，请注意查收： 感谢您对Age of Apes的理解与支持，祝愿火箭发射顺利！ 罗杰副官
B86: 万圣节活动皮肤补偿 | C86: 万圣节活动皮肤补偿
C87: 亲爱的指挥官： 由于合服，万圣节相关活动提前关闭，现在惊喜狂欢夜已经重新开启，在所有开启的惊喜狂欢夜活动中（包括本次及上次）您消耗超过60张南瓜奖券（包括60张）且未获得过南瓜古堡（永久）。 以下是你的万圣节皮肤补偿，请注意查收： 感谢您对Age of Apes的理解与支持，祝愿火箭发射顺利！ 罗杰副官
B89: AC战场重新报名 | C89: 决战卫星之巅报名异常说明 | D89: [Astral Coliseum] Registration Error Compensation
C90: 亲爱的指挥官： 由于数据异常，部分玩家出现活动报名失败的问题。此问题现已修复。如您希望继续参与活动，尽快重新进行活动报名。为您带来不便深感歉意，在此为您送上一份补偿，请注意查收。\n感谢您对Age of Apes的理解与支持，祝愿火箭发射顺利！\n\n罗杰副官 | D90: Dear Captain,\n\nDue to server issues, players in your sever encountered an <color=#ffa200>error when trying to register for [Astral Coliseum]</color>. This issue has now been fixed.<color=#ffa200>If you'd still like to participate in this event, please re-register as soon as possible.</color>\nWe sincerely apologize for the inconvenience and have included a small gift for you as compensation.\n\nThank you for your continued understanding and support. See you around the Tavern!\n\nDeputy Roger
B91: 发热卡顿问题修复 | C91: 新版本性能问题补偿 | D91: Compensation for Post-Update Performance Issues
C92: 亲爱的指挥官： 针对新版本更新后出现的发热、卡顿等游戏性能问题，我们已经进行了紧急修复，并将在最近的版本更新中发布，请您关注后续版本更新通知。为您带来不便深感歉意，在此为您送上一份补偿，请注意查收。\n感谢您对Age of Apes的理解与支持，祝愿火箭发射顺利！\n\n罗杰副官 | D92: Dear Captain, \n\nWe're currently completing fixes on performance issues (overheating, lagging, etc.) that have appeared after the recent version update. These fixes will be implemented in the next update (please see upcoming announcements for details). \n\nWe sincerely apologize for the inconvenience and have included a small gift for you as compensation.\n\nThank you for your continued understanding and support. See you around the Tavern!\n\nDeputy Roger
B93: 手动开BP 补偿 | C93: 狂飙拉力赛开启延迟补偿
C94: 亲爱的指挥官：\n\n由于服务器数据异常，导致您所在服务器出现<color=#ffa200>狂飙拉力赛活动未按时开启</color>的问题，目前此活动已<color=#ffa200>正常开启</color>。在此为您送上一份补偿，请注意查收。\n\n感谢您对猿族时代的理解与支持，祝愿火箭发射顺利！\n\n罗杰副官
B95: 合服导致BP关闭，重开 | C95: 飞驰拉力赛重新开启的说明
C96: 亲爱的指挥官： 由于服务器合并产生的数据影响，合服前开启的飞驰拉力赛已提前结束。我们将在11月22日0时重新开启新赛季的飞驰拉力赛，欢迎各位指挥官前往参加。 注意事项： 1、对于在合服前已购买了飞驰拉力赛狂野车手或冠军车手礼包的指挥官，我们将在新一期活动开启后，通过邮件为您发放激活道具，领取后即可继承上一期活动中的车手权益，请关注后续邮件通知，及时领取。 2、重新开启的飞驰拉力赛为全新一期的新赛季活动，不会继承上一期的活动等级及任务进度，请各位指挥官在起点重新出发。 在此为您送上一份补偿，请注意查收。感谢您对猿族时代的理解与支持，祝愿火箭发射顺利！ 罗杰副官
B97: BP重开补发激活道具-9.99 | C97: 亲爱的指挥官： 新赛季飞驰拉力赛活动已开启。您在因合服而提前结束的上赛季活动中购买了狂野车手礼包，领取此邮件奖励，您将重新激活新赛季狂野车手权益，解锁豪华补给站奖励。 感谢您对猿族时代的理解与支持，愿您在新赛季活动中继续驰骋赛场！ 罗杰副官
B98: BP重开补发激活道具-19.99&11.99 | C98: 亲爱的指挥官： 新赛季飞驰拉力赛活动已开启。您在因合服而提前结束的上赛季活动中购买了冠军车手礼包，领取此邮件奖励，您将重新激活新赛季冠军车手权益，解锁豪华补给站、典藏补给站及直升10级奖励。 感谢您对猿族时代的理解与支持，愿您在新赛季活动中继续驰骋赛场！ 罗杰副官
B99: 决战卫星之巅入场异常问题补偿 | C99: 亲爱的指挥官： 系统查询到由于服务器数据异常，导致您在上周的决战卫星之巅活动中未能成功进入战场。 在此为您送上一份补偿，请注意查收。感谢您对猿族时代的理解与支持，祝愿火箭发射顺利！ 罗杰副官 | D99: Compensation - Astral Coliseum Access Error Dear Captain, Due to server errors, you were unable to enter the Astral Coliseum battleground in last week's event. We sincerely apologize for the inconvenience and have included a gift for you as compensation. Thank you for your understanding and support as we continue to improve. See you around the Tavern! Deputy Roger
B100: 决战卫星之巅入场异常问题补偿 | C100: 亲爱的指挥官： 系统检测到由于服务器数据异常，导致上周的决战卫星之巅活动中，您所匹配到的对手未能成功进入战场。 在此为您送上一份补偿，请注意查收。感谢您对猿族时代的理解与支持，祝愿火箭发射顺利！ 罗杰副官 | D100: Dear Captain, Due to server errors, the opponent you were matched with was unable to enter the Astral Coliseum battleground in last week's event. We sincerely apologize for the inconvenience and have included a gift for you as compensation. Thank you for your understanding and support as we continue to improve. See you around the Tavern! Deputy Roger
B101: 全国禁娱停服公告 | C101: 12月6日服务器暂停登录通知 亲爱的指挥官： 由于2022年12月6日全国将举行重要悼念活动，停止公共娱乐活动。猿族时代将在2022年12月6日0:00至12月7日0:00（共1天）临时关闭服务器，届时您将无法登录游戏。 为保障全体指挥官的资产安全，系统将在12月6日0:00-12月8日0:00自动为所有玩家开启48小时护盾保护，停服期间未领取的订阅卡奖励将通过邮件统一发放。 其他停服补偿将在12月7日服务器重新开启后为您发放。感谢您对猿族时代的理解与支持，祝愿火箭发射顺利！ 罗杰副官
...

Sheet 3、结尾&落款
A1: 使用场景 | B1: cn | C1: en-loc | D1: fr | E1: de | F1: po | G1: zh | H1: id | I1: th | J1: sp | K1: ru | L1: tr | M1: vi
A2: 补偿 | B2: 为您带来不便深感歉意，在此为您送上一份补偿，请注意查收。 感谢你对Age of Apes的理解与支持，祝愿火箭发射顺利！ 罗杰副官 | C2: We apologize for the inconvenience. Here's a gift to make it up to you! Thanks for your understanding and support. See you around the Tavern! | D2: Veuillez nous excuser pour la gêne occasionnée. En guise de dédommagement, nous vous offrons ce cadeau. Merci pour votre compréhension et votre soutien, on se retrouve à la taverne! | E2: Wir entschuldigen uns für die Unannehmlichkeiten. Hier ist ein Geschenk, um dich dafür zu entschädigen! Vielen Dank für dein Verständnis und deine Unterstützung. Wir sehen uns in der Taverne! | F2: Pedimos desculpas pela inconveniência. Aqui está um presente para compensar! Agradecemos pela compreensão e apoio. Nos vemos na taverna! | G2: 為你帶來不便，我們深感抱歉。請接受這份禮物，作為補償！ 感謝你的理解及支持！我們酒館見！ | H2: Maaf atas ketidaknyamanannya. Berikut hadiah sebagai tanda maaf kami! Terima kasih atas pengertian dan dukunganmu. Sampai jumpa di sekitar Kedai! | I2: เราขออภัยสำหรับความไม่สะดวก นี่คือของขวัญที่คุณจะต้องถูกใจ! ขอบคุณสำหรับความเข้าใจและการให้ความสนับสนุนของคุณ แล้วพบกันใหม่ที่โรงแรม! | J2: ¡Te presentamos una disculpa por este inconveniente, así que te enviamos el siguiente regalo para compensarte! ¡Gracias por tu comprensión y apoyo! Nos vemos en la Taberna. | K2: Приносим извинения за неудобства. Вот вам подарок в качестве компенсации! Спасибо за понимание и поддержку. Увидимся в таверне! | L2: Verdiğimiz sıkıntıdan ötürü özür dileriz. Bu durumu telafi etme amaçlı bir hediyemiz var! Anlayışın ve desteğin için teşekkürler. Tavernada görüşürüz! | M2: Chúng tôi xin lỗi vì sự bất tiện này. Đây là một món quà để bù đắp cho bạn! Cảm ơn bạn đã thông cảm và luôn ủng hộ Age of Apes. Hẹn gặp lại bạn ở Tửu Quán!
A3: 通用 | B3: 谢谢你对我们的支持，我们将不断改进，希望能得到您的理解和支持，下一次在酒馆中再次干杯! 罗杰副官 | C3: Thank you for the understanding and support as we continue to improve. See you around the Tavern! | D3: Merci pour votre compréhension et votre soutien sans faille, tandis que nous continuons d'améliorer Age of Apes. Retrouvons-nous à la taverne! | E3: Vielen Dank für dein Verständnis und deine Unterstützung, während wir uns weiter verbessern. Wir sehen uns in der Taverne! | F3: Agradecemos sua compreensão e suporte! Nos vemos na taverna! | G3: 謝謝你對我們的支持，我們將不斷改進，希望能得到你的理解和支持，下一次在酒館中再次乾杯! | H3: Terima kasih atas pengertian dan dukungan selama kami melakukan peningkatan. Sampai jumpa di sekitar Kedai! | I3: ขอขอบคุณสำหรับความเข้าใจและการสนับสนุนสิ่งต่าง ๆ ที่เราปรับปรุงไปอย่างต่อเนื่อง ไว้เจอกันแถว ๆ โรงแรมนะ! | J3: Gracias por tu comprensión y apoyo mientras continuamos mejorando. ¡Nos vemos en la Taberna! | K3: Спасибо за понимание и поддержку наших мер по улучшению игры. Увидимся в таверне! | L3: Gelişme sürecimizdeki anlayışın ve desteğin için teşekkürler. Tavernada görüşürüz! | M3: Cảm ơn các bạn đã thấu hiểu và hỗ trợ chúng tôi tiếp tục cải thiện. Hẹn gặp lại ở Tửu Quán nhé!
A4: 通用 | B4: 感谢你对的理解与支持，祝愿火箭发射顺利！ 罗杰副官 | C4: Thanks for your understanding and support. See you around the Tavern! | D4: Merci pour votre compréhension et votre soutien, on se retrouve à la taverne! | E4: Vielen Dank für dein Verständnis und deine Unterstützung. Wir sehen uns in der Taverne! | F4: Agradecemos pela compreensão e apoio. Nos vemos na taverna! | G4: 感謝你對的理解與支持，祝愿火箭發射順利！ | H4: Terima kasih atas pengertian dan dukunganmu. Sampai jumpa di sekitar Kedai! | I4: ขอบคุณสำหรับความเข้าใจและการให้ความสนับสนุนของคุณ แล้วพบกันใหม่ที่โรงแรม! | J4: ¡Gracias por tu comprensión y apoyo! Nos vemos en la Taberna. | K4: Спасибо за понимание и поддержку. Увидимся в таверне! | L4: Anlayışın ve desteğin için teşekkürler. Tavernada görüşürüz! | M4: Cảm ơn bạn đã thông cảm và luôn ủng hộ Age of Apes. Hẹn gặp lại bạn ở Tửu Quán!
A5: 通用 | B5: 非常感谢您对我们的理解和支持，我们将不断改进，愿您可以享受在猴子世界游玩的快乐。 罗杰副官 | C5: Thank you very much for your understanding and support, and see you around the Tavern! | D5: Merci pour votre compréhension et votre soutien sans faille. On se retrouve à la taverne! | E5: Vielen Dank für euer Verständnis und eure Unterstützung, und wir sehen uns in der Taverne!" | F5: Agradecemos pela sua compreensão e apoio. Nos vemos na taverna! | G5: 非常感謝您對我們的理解和支持，我們將不斷改進，願您可以享受在猴子世界遊玩的快樂。 | H5: Terima kasih banyak atas pengertian dan dukungannya, sampai jumpa di sekitar Kedai! | I5: ขอขอบคุณอย่างยิ่งสำหรับความเข้าใจและการสนับสนุนของคุณ แล้วเจอกันรอบ ๆ โรงแรมนะ! | J5: ¡Muchas gracias por tu comprensión y apoyo y nos vemos en la Taberna! | K5: Большое спасибо за понимание и поддержку. Увидимся в таверне! | L5: Anlayışın ve desteğin için teşekkürler, Tavernada görüşürüz! | M5: Xin chân thành cảm ơn các bạn đã thông cảm và ủng hộ, hẹn gặp lại các bạn ở Tửu Quán!
A6: 社区反馈 | B6: 感谢您对Age of Apes的理解与支持。如果您有意见或建议，也欢迎您通过客服或社区进行反馈，我们会认真听取，祝愿火箭发射顺利！ [-1#点击加入Discord社区](herf=https://discord.gg/fK3gtph) 罗杰副官 | C6: Thank you for your understanding and support. If you have any other questions or suggestions, please don't hesitate to contact us via the in-game customer support or the community. See you around the Tavern! | G6: 感謝您對Age of Apes的理解與支持。如果您有意見或建議，也歡迎您通過客服或社區進行反饋，我們會認真聽取，祝愿火箭發射順利！

Sheet 补偿规则
A1: 补偿规则
A2: 1.系统/活动BUG通常需要发一封说明邮件和BUG已修复邮件。 2.以下均是额外补偿，如对玩家造成损失，需统一/单独补上玩家损失部分（这个为默认规则，将不在下方详细指出）。 3.如果BUG需要维护部署，需按BUG补偿+日常维护（日常维护的补偿跟随维护邮件即可，不叠加在bug补偿邮件中）进行补偿。 4.以下均基础补偿规则，如遇特殊情况，有单独需求，可在补偿中附加BUG相关道具。 5.事故中的分级将由具体情况具体分析。
A6: 分类 | B6: 具体情况 | C6: 详细补偿
A7: 日常维护 | B7: 维护半小时内 | C7: 15分钟训练加速*2
B8: 维护超半小时 | C8: 超时15分钟 = 15分钟训练加速*1
A9: 版本更新 | B9: 版本更新 | C9: 60分钟训练加速*1 + 60分钟科研加速*1 + 60分钟建筑加速*1 + 50,000粮食* 10 + 50,000钢铁*10
A10: 事故 | B10: S级事故 | C10: CD*500 + 60分钟训练加速*4 + 60分钟科研加速*3 + 60分钟建筑加速*3 + 50,000粮食* 20 + 50,000钢铁*20
B11: A级事故 | C11: CD*200 + 60分钟训练加速*1 + 60分钟科研加速*1 + 60分钟建筑加速*1 + 50,000粮食* 10 + 50,000钢铁*10
B12: B级事故 | C12: CD*100 + 15分钟训练加速*10 + 50,000粮食*5 + 50,000钢铁*5
B13: C级事故 | C13: 15分钟训练加速*5 + 50,000粮食*2 + 50,000钢铁*2
A14: 社区相关 | B14: 问卷 | C14: CD*200
B16: 外团奖励 | C16: 500CD一天，一个有效bug+100CD
A17: 事故分级标准 | B17: https://wiki.tap4fun.com/pages/viewpage.action?pageId=47186488
A18: BUG上报奖励规则 | G18: 扣道具（包括道具和代币）
A19: 1.客服&社区（目前常用的两个渠道）前2位反馈问题的玩家，在举报的BUG核实后根据事故级别给予宝石奖励并公告表扬； 2.执行流程：客服&社区上报问题并记录上报玩家的顺序（取各渠道的前1位，可并列2位）→ 项目组验证BUG核实真实性 → 项目组解决BUG → 运营发奖励&公告 面向玩家的解释，不同程度的bug会有一个dev鉴定，dev会根据bug的定级情况发放不同程度的奖励。 | G19: 道具扣除到$500（锚点价值），开启行为限制
G20: 还清后解除
A21: 分类 | B21: 具体情况 | C21: 详细补偿
A22: 事故 | B22: S级事故 | C22: CD*5000（客服）/ 猿猴币*4999 （社区）
B23: A级事故 | C23: CD*2500（客服））/ 猿猴币*1999 （社区）
B24: B级事故 | C24: CD*1000（客服））/ 猿猴币*499 （社区）
B25: C级事故 | C25: CD*500（客服））/ 猿猴币*99 （社区） | J25: 战装刷奖励的玩家 扣除的道具
A27: 客服问题反馈特殊补偿
A28: 分类 | B28: 具体情况 | C28: 详细补偿
A29: 客服问题反馈特殊补偿 | B29: 误解答问题 | C29: CD*200
B30: 特殊问题安慰补偿 | C30: CD*200
A32: 其他奖励
A33: 分类 | B33: 具体情况 | C33: 详细
A34: 用户调研 | B34: 调研问卷 | C34: CD*200

Sheet 4、长版whats new
A1: =IFERROR(__xludf.DUMMYFUNCTION("IMPORTRANGE(""https://docs.google.com/spreadsheets/d/1hnDXdyVS4aonZPp7X5xvrh_3tDY3h-VQ3eDvhBz5-ws/edit#gid=1347130232"",""汇总-长what's new!A1:z100"")"),"") | B1: =IFERROR(__xludf.DUMMYFUNCTION("""COMPUTED_VALUE"""),"CN") -> CN | C1: =IFERROR(__xludf.DUMMYFUNCTION("""COMPUTED_VALUE"""),"EN") -> EN | D1: =IFERROR(__xludf.DUMMYFUNCTION("""COMPUTED_VALUE"""),"FR") -> FR | E1: =IFERROR(__xludf.DUMMYFUNCTION("""COMPUTED_VALUE"""),"DE") -> DE | F1: =IFERROR(__xludf.DUMMYFUNCTION("""COMPUTED_VALUE"""),"PO") -> PO | G1: =IFERROR(__xludf.DUMMYFUNCTION("""COMPUTED_VALUE"""),"ZH") -> ZH | H1: =IFERROR(__xludf.DUMMYFUNCTION("""COMPUTED_VALUE"""),"ID") -> ID | I1: =IFERROR(__xludf.DUMMYFUNCTION("""COMPUTED_VALUE"""),"TH") -> TH | J1: =IFERROR(__xludf.DUMMYFUNCTION("""COMPUTED_VALUE"""),"SP") -> SP | K1: =IFERROR(__xludf.DUMMYFUNCTION("""COMPUTED_VALUE"""),"RU") -> RU | L1: =IFERROR(__xludf.DUMMYFUNCTION("""COMPUTED_VALUE"""),"TR") -> TR | M1: =IFERROR(__xludf.DUMMYFUNCTION("""COMPUTED_VALUE"""),"VI") -> VI | N1: =IFERROR(__xludf.DUMMYFUNCTION("""COMPUTED_VALUE"""),"it") -> it | O1: =IFERROR(__xludf.DUMMYFUNCTION("""COMPUTED_VALUE"""),"pl") -> pl | P1: =IFERROR(__xludf.DUMMYFUNCTION("""COMPUTED_VALUE"""),"ar") -> ar | Q1: =IFERROR(__xludf.DUMMYFUNCTION("""COMPUTED_VALUE"""),"JP") -> JP | R1: =IFERROR(__xludf.DUMMYFUNCTION("""COMPUTED_VALUE"""),"KR") -> KR
